{
"boxscore": {
"teams": [
{
"team": {
"id": "29",
"uid": "s:40~l:46~t:29",
"slug": "memphis-grizzlies",
"location": "Memphis",
"name": "Grizzlies",
"abbreviation": "MEM",
"displayName": "Memphis Grizzlies",
"shortDisplayName": "Grizzlies",
"color": "5D76A8",
"alternateColor": "7399c6",
"logo": "https://a.espncdn.com/i/teamlogos/nba/500/mem.png"
},
"statistics": [
{
"name": "fieldGoalsMade-fieldGoalsAttempted",
"displayValue": "35-87",
"label": "FG"
},
{
"name": "fieldGoalPct",
"displayValue": "40.2",
"abbreviation": "FG%",
"label": "Field Goal %"
},
{
"name": "threePointFieldGoalsMade-threePointFieldGoalsAttempted",
"displayValue": "5-13",
"label": "3PT"
},
{
"name": "threePointFieldGoalPct",
"displayValue": "38.5",
"abbreviation": "3P%",
"label": "Three Point %"
},
{
"name": "freeThrowsMade-freeThrowsAttempted",
"displayValue": "13-20",
"label": "FT"
},
{
"name": "freeThrowPct",
"displayValue": "65.0",
"abbreviation": "FT%",
"label": "Free Throw %"
},
{
"name": "totalRebounds",
"displayValue": "50",
"abbreviation": "REB",
"label": "Rebounds"
},
{
"name": "offensiveRebounds",
"displayValue": "13",
"abbreviation": "OR",
"label": "Offensive Rebounds"
},
{
"name": "defensiveRebounds",
"displayValue": "28",
"abbreviation": "DR",
"label": "Defensive Rebounds"
},
{
"name": "assists",
"displayValue": "21",
"abbreviation": "AST",
"label": "Assists"
},
{
"name": "steals",
"displayValue": "12",
"abbreviation": "STL",
"label": "Steals"
},
{
"name": "blocks",
"displayValue": "4",
"abbreviation": "BLK",
"label": "Blocks"
},
{
"name": "turnovers",
"displayValue": "20",
"abbreviation": "TO",
"label": "Turnovers"
},
{
"name": "teamTurnovers",
"displayValue": "20",
"abbreviation": "TTO",
"label": "Team Turnovers"
},
{
"name": "totalTurnovers",
"displayValue": "40",
"abbreviation": "ToTO",
"label": "Total Turnovers"
},
{
"name": "technicalFouls",
"displayValue": "0",
"abbreviation": "TECH",
"label": "Technical Fouls"
},
{
"name": "totalTechnicalFouls",
"displayValue": "0",
"abbreviation": "TECH",
"label": "Total Technical Fouls"
},
{
"name": "flagrantFouls",
"displayValue": "0",
"abbreviation": "FLAG",
"label": "Flagrant Fouls"
},
{
"name": "turnoverPoints",
"displayValue": "19",
"abbreviation": "PTS OFF TO",
"label": "Points Off Turnovers"
},
{
"name": "fastBreakPoints",
"displayValue": "21",
"abbreviation": "FBPs",
"label": "Fast Break Points"
},
{
"name": "pointsInPaint",
"displayValue": "-1",
"abbreviation": "PIP",
"label": "Points in Paint"
},
{
"name": "fouls",
"displayValue": "22",
"abbreviation": "PF",
"label": "Fouls"
}
]
},
{
"team": {
"id": "28",
"uid": "s:40~l:46~t:28",
"slug": "toronto-raptors",
"location": "Toronto",
"name": "Raptors",
"abbreviation": "TOR",
"displayName": "Toronto Raptors",
"shortDisplayName": "Raptors",
"color": "CE0F41",
"alternateColor": "061922",
"logo": "https://a.espncdn.com/i/teamlogos/nba/500/tor.png"
},
"statistics": [
{
"name": "fieldGoalsMade-fieldGoalsAttempted",
"displayValue": "33-78",
"label": "FG"
},
{
"name": "fieldGoalPct",
"displayValue": "42.3",
"abbreviation": "FG%",
"label": "Field Goal %"
},
{
"name": "threePointFieldGoalsMade-threePointFieldGoalsAttempted",
"displayValue": "3-9",
"label": "3PT"
},
{
"name": "threePointFieldGoalPct",
"displayValue": "33.3",
"abbreviation": "3P%",
"label": "Three Point %"
},
{
"name": "freeThrowsMade-freeThrowsAttempted",
"displayValue": "22-24",
"label": "FT"
},
{
"name": "freeThrowPct",
"displayValue": "91.7",
"abbreviation": "FT%",
"label": "Free Throw %"
},
{
"name": "totalRebounds",
"displayValue": "56",
"abbreviation": "REB",
"label": "Rebounds"
},
{
"name": "offensiveRebounds",
"displayValue": "11",
"abbreviation": "OR",
"label": "Offensive Rebounds"
},
{
"name": "defensiveRebounds",
"displayValue": "33",
"abbreviation": "DR",
"label": "Defensive Rebounds"
},
{
"name": "assists",
"displayValue": "19",
"abbreviation": "AST",
"label": "Assists"
},
{
"name": "steals",
"displayValue": "11",
"abbreviation": "STL",
"label": "Steals"
},
{
"name": "blocks",
"displayValue": "7",
"abbreviation": "BLK",
"label": "Blocks"
},
{
"name": "turnovers",
"displayValue": "20",
"abbreviation": "TO",
"label": "Turnovers"
},
{
"name": "teamTurnovers",
"displayValue": "20",
"abbreviation": "TTO",
"label": "Team Turnovers"
},
{
"name": "totalTurnovers",
"displayValue": "40",
"abbreviation": "ToTO",
"label": "Total Turnovers"
},
{
"name": "technicalFouls",
"displayValue": "1",
"abbreviation": "TECH",
"label": "Technical Fouls"
},
{
"name": "totalTechnicalFouls",
"displayValue": "1",
"abbreviation": "TECH",
"label": "Total Technical Fouls"
},
{
"name": "flagrantFouls",
"displayValue": "0",
"abbreviation": "FLAG",
"label": "Flagrant Fouls"
},
{
"name": "turnoverPoints",
"displayValue": "25",
"abbreviation": "PTS OFF TO",
"label": "Points Off Turnovers"
},
{
"name": "fastBreakPoints",
"displayValue": "24",
"abbreviation": "FBPs",
"label": "Fast Break Points"
},
{
"name": "pointsInPaint",
"displayValue": "-1",
"abbreviation": "PIP",
"label": "Points in Paint"
},
{
"name": "fouls",
"displayValue": "20",
"abbreviation": "PF",
"label": "Fouls"
}
]
}
],
"players": [
{
"team": {
"id": "29",
"uid": "s:40~l:46~t:29",
"slug": "memphis-grizzlies",
"location": "Memphis",
"name": "Grizzlies",
"abbreviation": "MEM",
"displayName": "Memphis Grizzlies",
"shortDisplayName": "Grizzlies",
"color": "5D76A8",
"alternateColor": "7399c6",
"logo": "https://a.espncdn.com/i/teamlogos/nba/500/mem.png"
},
"statistics": [
{
"names": [
"MIN",
"FG",
"3PT",
"FT",
"OREB",
"DREB",
"REB",
"AST",
"STL",
"BLK",
"TO",
"PF",
"+/-",
"PTS"
],
"keys": [
"minutes",
"fieldGoalsMade-fieldGoalsAttempted",
"threePointFieldGoalsMade-threePointFieldGoalsAttempted",
"freeThrowsMade-freeThrowsAttempted",
"offensiveRebounds",
"defensiveRebounds",
"rebounds",
"assists",
"steals",
"blocks",
"turnovers",
"fouls",
"plusMinus",
"points"
],
"labels": [
"MIN",
"FG",
"3PT",
"FT",
"OREB",
"DREB",
"REB",
"AST",
"STL",
"BLK",
"TO",
"PF",
"+/-",
"PTS"
],
"descriptions": [
"Minutes",
"Field Goals Made/Attempted",
"3-Point Field Goals Made/Attempted",
"Free Throws Made/Attempted",
"Offensive Rebounds",
"Defensive Rebounds",
"Rebounds",
"Assists",
"Steals",
"Blocks",
"Turnovers",
"Personal Fouls",
"Teams net points while player is on the court.",
"Points"
],
"athletes": [
{
"active": false,
"athlete": {
"id": "959",
"uid": "s:40~l:46~a:959",
"guid": "1a4c0232b2ffcfc2e83662782a555868",
"displayName": "Lorenzen Wright",
"shortName": "L. Wright",
"links": [
{
"rel": [
"playercard",
"desktop",
"athlete"
],
"href": "https://www.espn.com/nba/player/_/id/959/lorenzen-wright",
"text": "Player Card"
},
{
"rel": [
"stats",
"desktop",
"athlete"
],
"href": "http://www.espn.com/nba/player/stats/_/id/959/lorenzen-wright",
"text": "Stats"
},
{
"rel": [
"splits",
"desktop",
"athlete"
],
"href": "http://www.espn.com/nba/player/splits/_/id/959/lorenzen-wright",
"text": "Splits"
},
{
"rel": [
"gamelog",
"desktop",
"athlete"
],
"href": "http://www.espn.com/nba/player/gamelog/_/id/959/lorenzen-wright",
"text": "Game Log"
},
{
"rel": [
"news",
"desktop",
"athlete"
],
"href": "http://www.espn.com/nba/player/news/_/id/959/lorenzen-wright",
"text": "News"
},
{
"rel": [
"bio",
"desktop",
"athlete"
],
"href": "http://www.espn.com/nba/player/bio/_/id/959/lorenzen-wright",
"text": "Bio"
},
{
"rel": [
"overview",
"desktop",
"athlete"
],
"href": "http://www.espn.com/nba/player/_/id/959/lorenzen-wright",
"text": "Overview"
},
{
"rel": [
"advancedstats",
"desktop",
"athlete"
],
"href": "http://www.espn.com/nba/player/advancedstats/_/id/959/lorenzen-wright",
"text": "Advanced Stats"
}
],
"jersey": "55",
"position": {
"name": "Power Forward",
"displayName": "Power Forward",
"abbreviation": "PF"
}
},
"starter": true,
"didNotPlay": false,
"ejected": false,
"stats": [
"41",
"4-11",
"0-0",
"3-3",
"2",
"9",
"11",
"3",
"0",
"1",
"6",
"3",
"--",
"11"
]
},
{
"active": false,
"athlete": {
"id": "996",
"uid": "s:40~l:46~a:996",
"guid": "9955bf55e140871b2f0d7e3d74dadd23",
"displayName": "Pau Gasol",
"shortName": "P. Gasol",
"links": [
{
"rel": [
"playercard",
"desktop",
"athlete"
],
"href": "https://www.espn.com/nba/player/_/id/996/pau-gasol",
"text": "Player Card"
},
{
"rel": [
"stats",
"desktop",
"athlete"
],
"href": "http://www.espn.com/nba/player/stats/_/id/996/pau-gasol",
"text": "Stats"
},
{
"rel": [
"splits",
"desktop",
"athlete"
],
"href": "http://www.espn.com/nba/player/splits/_/id/996/pau-gasol",
"text": "Splits"
},
{
"rel": [
"gamelog",
"desktop",
"athlete"
],
"href": "http://www.espn.com/nba/player/gamelog/_/id/996/pau-gasol",
"text": "Game Log"
},
{
"rel": [
"news",
"desktop",
"athlete"
],
"href": "http://www.espn.com/nba/player/news/_/id/996/pau-gasol",
"text": "News"
},
{
"rel": [
"bio",
"desktop",
"athlete"
],
"href": "http://www.espn.com/nba/player/bio/_/id/996/pau-gasol",
"text": "Bio"
},
{
"rel": [
"overview",
"desktop",
"athlete"
],
"href": "http://www.espn.com/nba/player/_/id/996/pau-gasol",
"text": "Overview"
},
{
"rel": [
"advancedstats",
"desktop",
"athlete"
],
"href": "http://www.espn.com/nba/player/advancedstats/_/id/996/pau-gasol",
"text": "Advanced Stats"
}
],
"headshot": {
"href": "https://a.espncdn.com/i/headshots/nba/players/full/996.png",
"alt": "Pau Gasol"
},
"jersey": "16",
"position": {
"name": "Power Forward",
"displayName": "Power Forward",
"abbreviation": "PF"
}
},
"starter": true,
"didNotPlay": false,
"ejected": false,
"stats": [
"40",
"8-18",
"0-0",
"6-9",
"4",
"5",
"9",
"0",
"1",
"3",
"2",
"5",
"--",
"22"
]
},
{
"active": false,
"athlete": {
"id": "114",
"uid": "s:40~l:46~a:114",
"guid": "70826390cf6181ac0e37aea5cb8ac693",
"displayName": "Rodney Buford",
"shortName": "R. Buford",
"links": [
{
"rel": [
"playercard",
"desktop",
"athlete"
],
"href": "https://www.espn.com/nba/player/_/id/114/rodney-buford",
"text": "Player Card"
},
{
"rel": [
"stats",
"desktop",
"athlete"
],
"href": "http://www.espn.com/nba/player/stats/_/id/114/rodney-buford",
"text": "Stats"
},
{
"rel": [
"splits",
"desktop",
"athlete"
],
"href": "http://www.espn.com/nba/player/splits/_/id/114/rodney-buford",
"text": "Splits"
},
{
"rel": [
"gamelog",
"desktop",
"athlete"
],
"href": "http://www.espn.com/nba/player/gamelog/_/id/114/rodney-buford",
"text": "Game Log"
},
{
"rel": [
"news",
"desktop",
"athlete"
],
"href": "http://www.espn.com/nba/player/news/_/id/114/rodney-buford",
"text": "News"
},
{
"rel": [
"bio",
"desktop",
"athlete"
],
"href": "http://www.espn.com/nba/player/bio/_/id/114/rodney-buford",
"text": "Bio"
},
{
"rel": [
"overview",
"desktop",
"athlete"
],
"href": "http://www.espn.com/nba/player/_/id/114/rodney-buford",
"text": "Overview"
},
{
"rel": [
"advancedstats",
"desktop",
"athlete"
],
"href": "http://www.espn.com/nba/player/advancedstats/_/id/114/rodney-buford",
"text": "Advanced Stats"
}
],
"jersey": "2",
"position": {
"name": "Small Forward",
"displayName": "Small Forward",
"abbreviation": "SF"
}
},
"starter": true,
"didNotPlay": false,
"ejected": false,
"stats": [
"43",
"8-20",
"2-5",
"0-0",
"1",
"8",
"9",
"1",
"5",
"0",
"2",
"3",
"--",
"18"
]
},
{
"active": false,
"athlete": {
"id": "976",
"uid": "s:40~l:46~a:976",
"guid": "92971a96f70bce6fc7d91199ee18e5da",
"displayName": "Shane Battier",
"shortName": "S. Battier",
"links": [
{
"rel": [
"playercard",
"desktop",
"athlete"
],
"href": "https://www.espn.com/nba/player/_/id/976/shane-battier",
"text": "Player Card"
},
{
"rel": [
"stats",
"desktop",
"athlete"
],
"href": "http://www.espn.com/nba/player/stats/_/id/976/shane-battier",
"text": "Stats"
},
{
"rel": [
"splits",
"desktop",
"athlete"
],
"href": "http://www.espn.com/nba/player/splits/_/id/976/shane-battier",
"text": "Splits"
},
{
"rel": [
"gamelog",
"desktop",
"athlete"
],
"href": "http://www.espn.com/nba/player/gamelog/_/id/976/shane-battier",
"text": "Game Log"
},
{
"rel": [
"news",
"desktop",
"athlete"
],
"href": "http://www.espn.com/nba/player/news/_/id/976/shane-battier",
"text": "News"
},
{
"rel": [
"bio",
"desktop",
"athlete"
],
"href": "http://www.espn.com/nba/player/bio/_/id/976/shane-battier",
"text": "Bio"
},
{
"rel": [
"overview",
"desktop",
"athlete"
],
"href": "http://www.espn.com/nba/player/_/id/976/shane-battier",
"text": "Overview"
},
{
"rel": [
"advancedstats",
"desktop",
"athlete"
],
"href": "http://www.espn.com/nba/player/advancedstats/_/id/976/shane-battier",
"text": "Advanced Stats"
}
],
"headshot": {
"href": "https://a.espncdn.com/i/headshots/nba/players/full/976.png",
"alt": "Shane Battier"
},
"jersey": "31",
"position": {
"name": "Small Forward",
"displayName": "Small Forward",
"abbreviation": "SF"
}
},
"starter": true,
"didNotPlay": false,
"ejected": false,
"stats": [
"45",
"8-15",
"3-5",
"1-3",
"4",
"1",
"5",
"2",
"3",
"0",
"4",
"2",
"--",
"20"
]
},
{
"active": false,
"athlete": {
"id": "933",
"uid": "s:40~l:46~a:933",
"guid": "e3057b2e0a35460a97c5083006fa038b",
"displayName": "Jason Williams",
"shortName": "J. Williams",
"links": [
{
"rel": [
"playercard",
"desktop",
"athlete"
],
"href": "https://www.espn.com/nba/player/_/id/933/jason-williams",
"text": "Player Card"
},
{
"rel": [
"stats",
"desktop",
"athlete"
],
"href": "http://www.espn.com/nba/player/stats/_/id/933/jason-williams",
"text": "Stats"
},
{
"rel": [
"splits",
"desktop",
"athlete"
],
"href": "http://www.espn.com/nba/player/splits/_/id/933/jason-williams",
"text": "Splits"
},
{
"rel": [
"gamelog",
"desktop",
"athlete"
],
"href": "http://www.espn.com/nba/player/gamelog/_/id/933/jason-williams",
"text": "Game Log"
},
{
"rel": [
"news",
"desktop",
"athlete"
],
"href": "http://www.espn.com/nba/player/news/_/id/933/jason-williams",
"text": "News"
},
{
"rel": [
"bio",
"desktop",
"athlete"
],
"href": "http://www.espn.com/nba/player/bio/_/id/933/jason-williams",
"text": "Bio"
},
{
"rel": [
"overview",
"desktop",
"athlete"
],
"href": "http://www.espn.com/nba/player/_/id/933/jason-williams",
"text": "Overview"
},
{
"rel": [
"advancedstats",
"desktop",
"athlete"
],
"href": "http://www.espn.com/nba/player/advancedstats/_/id/933/jason-williams",
"text": "Advanced Stats"
}
],
"headshot": {
"href": "https://a.espncdn.com/i/headshots/nba/players/full/933.png",
"alt": "Jason Williams"
},
"jersey": "3",
"position": {
"name": "Point Guard",
"displayName": "Point Guard",
"abbreviation": "PG"
}
},
"starter": true,
"didNotPlay": false,
"ejected": false,
"stats": [
"38",
"3-15",
"0-3",
"1-2",
"1",
"3",
"4",
"8",
"2",
"0",
"2",
"2",
"--",
"7"
]
},
{
"active": false,
"athlete": {
"id": "519",
"uid": "s:40~l:46~a:519",
"guid": "bff2bac1077e938476cd9271bb22e028",
"displayName": "Tony Massenburg",
"shortName": "T. Massenburg",
"links": [
{
"rel": [
"playercard",
"desktop",
"athlete"
],
"href": "https://www.espn.com/nba/player/_/id/519/tony-massenburg",
"text": "Player Card"
},
{
"rel": [
"stats",
"desktop",
"athlete"
],
"href": "http://www.espn.com/nba/player/stats/_/id/519/tony-massenburg",
"text": "Stats"
},
{
"rel": [
"splits",
"desktop",
"athlete"
],
"href": "http://www.espn.com/nba/player/splits/_/id/519/tony-massenburg",
"text": "Splits"
},
{
"rel": [
"gamelog",
"desktop",
"athlete"
],
"href": "http://www.espn.com/nba/player/gamelog/_/id/519/tony-massenburg",
"text": "Game Log"
},
{
"rel": [
"news",
"desktop",
"athlete"
],
"href": "http://www.espn.com/nba/player/news/_/id/519/tony-massenburg",
"text": "News"
},
{
"rel": [
"bio",
"desktop",
"athlete"
],
"href": "http://www.espn.com/nba/player/bio/_/id/519/tony-massenburg",
"text": "Bio"
},
{
"rel": [
"overview",
"desktop",
"athlete"
],
"href": "http://www.espn.com/nba/player/_/id/519/tony-massenburg",
"text": "Overview"
},
{
"rel": [
"advancedstats",
"desktop",
"athlete"
],
"href": "http://www.espn.com/nba/player/advancedstats/_/id/519/tony-massenburg",
"text": "Advanced Stats"
}
],
"jersey": "44",
"position": {
"name": "Power Forward",
"displayName": "Power Forward",
"abbreviation": "PF"
}
},
"starter": false,
"didNotPlay": false,
"ejected": false,
"stats": [
"14",
"0-2",
"0-0",
"2-2",
"0",
"2",
"2",
"1",
"0",
"0",
"1",
"5",
"--",
"2"
]
},
{
"active": false,
"athlete": {
"id": "440",
"uid": "s:40~l:46~a:440",
"guid": "7829eeb5ca43b7c9c865a985b98c1435",
"displayName": "Brevin Knight",
"shortName": "B. Knight",
"links": [
{
"rel": [
"playercard",
"desktop",
"athlete"
],
"href": "https://www.espn.com/nba/player/_/id/440/brevin-knight",
"text": "Player Card"
},
{
"rel": [
"stats",
"desktop",
"athlete"
],
"href": "http://www.espn.com/nba/player/stats/_/id/440/brevin-knight",
"text": "Stats"
},
{
"rel": [
"splits",
"desktop",
"athlete"
],
"href": "http://www.espn.com/nba/player/splits/_/id/440/brevin-knight",
"text": "Splits"
},
{
"rel": [
"gamelog",
"desktop",
"athlete"
],
"href": "http://www.espn.com/nba/player/gamelog/_/id/440/brevin-knight",
"text": "Game Log"
},
{
"rel": [
"news",
"desktop",
"athlete"
],
"href": "http://www.espn.com/nba/player/news/_/id/440/brevin-knight",
"text": "News"
},
{
"rel": [
"bio",
"desktop",
"athlete"
],
"href": "http://www.espn.com/nba/player/bio/_/id/440/brevin-knight",
"text": "Bio"
},
{
"rel": [
"overview",
"desktop",
"athlete"
],
"href": "http://www.espn.com/nba/player/_/id/440/brevin-knight",
"text": "Overview"
},
{
"rel": [
"advancedstats",
"desktop",
"athlete"
],
"href": "http://www.espn.com/nba/player/advancedstats/_/id/440/brevin-knight",
"text": "Advanced Stats"
}
],
"jersey": "2",
"position": {
"name": "Point Guard",
"displayName": "Point Guard",
"abbreviation": "PG"
}
},
"starter": false,
"didNotPlay": false,
"ejected": false,
"stats": [
"19",
"4-6",
"0-0",
"0-1",
"1",
"0",
"1",
"6",
"1",
"0",
"3",
"2",
"--",
"8"
]
},
{
"active": false,
"athlete": {
"id": "829",
"uid": "s:40~l:46~a:829",
"guid": "6e7564c0c9b83986ee3afa18f43db82e",
"displayName": "Stromile Swift",
"shortName": "S. Swift",
"links": [
{
"rel": [
"playercard",
"desktop",
"athlete"
],
"href": "https://www.espn.com/nba/player/_/id/829/stromile-swift",
"text": "Player Card"
},
{
"rel": [
"stats",
"desktop",
"athlete"
],
"href": "http://www.espn.com/nba/player/stats/_/id/829/stromile-swift",
"text": "Stats"
},
{
"rel": [
"splits",
"desktop",
"athlete"
],
"href": "http://www.espn.com/nba/player/splits/_/id/829/stromile-swift",
"text": "Splits"
},
{
"rel": [
"gamelog",
"desktop",
"athlete"
],
"href": "http://www.espn.com/nba/player/gamelog/_/id/829/stromile-swift",
"text": "Game Log"
},
{
"rel": [
"news",
"desktop",
"athlete"
],
"href": "http://www.espn.com/nba/player/news/_/id/829/stromile-swift",
"text": "News"
},
{
"rel": [
"bio",
"desktop",
"athlete"
],
"href": "http://www.espn.com/nba/player/bio/_/id/829/stromile-swift",
"text": "Bio"
},
{
"rel": [
"overview",
"desktop",
"athlete"
],
"href": "http://www.espn.com/nba/player/_/id/829/stromile-swift",
"text": "Overview"
},
{
"rel": [
"advancedstats",
"desktop",
"athlete"
],
"href": "http://www.espn.com/nba/player/advancedstats/_/id/829/stromile-swift",
"text": "Advanced Stats"
}
],
"jersey": "4",
"position": {
"name": "Power Forward",
"displayName": "Power Forward",
"abbreviation": "PF"
}
},
"starter": false,
"didNotPlay": true,
"ejected": false,
"stats": []
},
{
"active": false,
"athlete": {
"id": "14",
"uid": "s:40~l:46~a:14",
"guid": "20e6be8977d5d3e720d6c891a5694b5d",
"displayName": "Nick Anderson",
"shortName": "N. Anderson",
"links": [
{
"rel": [
"playercard",
"desktop",
"athlete"
],
"href": "https://www.espn.com/nba/player/_/id/14/nick-anderson",
"text": "Player Card"
},
{
"rel": [
"stats",
"desktop",
"athlete"
],
"href": "http://www.espn.com/nba/player/stats/_/id/14/nick-anderson",
"text": "Stats"
},
{
"rel": [
"splits",
"desktop",
"athlete"
],
"href": "http://www.espn.com/nba/player/splits/_/id/14/nick-anderson",
"text": "Splits"
},
{
"rel": [
"gamelog",
"desktop",
"athlete"
],
"href": "http://www.espn.com/nba/player/gamelog/_/id/14/nick-anderson",
"text": "Game Log"
},
{
"rel": [
"news",
"desktop",
"athlete"
],
"href": "http://www.espn.com/nba/player/news/_/id/14/nick-anderson",
"text": "News"
},
{
"rel": [
"bio",
"desktop",
"athlete"
],
"href": "http://www.espn.com/nba/player/bio/_/id/14/nick-anderson",
"text": "Bio"
},
{
"rel": [
"overview",
"desktop",
"athlete"
],
"href": "http://www.espn.com/nba/player/_/id/14/nick-anderson",
"text": "Overview"
},
{
"rel": [
"advancedstats",
"desktop",
"athlete"
],
"href": "http://www.espn.com/nba/player/advancedstats/_/id/14/nick-anderson",
"text": "Advanced Stats"
}
],
"jersey": "25",
"position": {
"name": "Forward",
"displayName": "Forward",
"abbreviation": "F"
}
},
"starter": false,
"didNotPlay": true,
"ejected": false,
"stats": []
},
{
"active": false,
"athlete": {
"id": "481",
"uid": "s:40~l:46~a:481",
"guid": "30b294bcd5fb1b63e8ea1201ee779917",
"displayName": "Grant Long",
"shortName": "G. Long",
"links": [
{
"rel": [
"playercard",
"desktop",
"athlete"
],
"href": "https://www.espn.com/nba/player/_/id/481/grant-long",
"text": "Player Card"
},
{
"rel": [
"stats",
"desktop",
"athlete"
],
"href": "http://www.espn.com/nba/player/stats/_/id/481/grant-long",
"text": "Stats"
},
{
"rel": [
"splits",
"desktop",
"athlete"
],
"href": "http://www.espn.com/nba/player/splits/_/id/481/grant-long",
"text": "Splits"
},
{
"rel": [
"gamelog",
"desktop",
"athlete"
],
"href": "http://www.espn.com/nba/player/gamelog/_/id/481/grant-long",
"text": "Game Log"
},
{
"rel": [
"news",
"desktop",
"athlete"
],
"href": "http://www.espn.com/nba/player/news/_/id/481/grant-long",
"text": "News"
},
{
"rel": [
"bio",
"desktop",
"athlete"
],
"href": "http://www.espn.com/nba/player/bio/_/id/481/grant-long",
"text": "Bio"
},
{
"rel": [
"overview",
"desktop",
"athlete"
],
"href": "http://www.espn.com/nba/player/_/id/481/grant-long",
"text": "Overview"
},
{
"rel": [
"advancedstats",
"desktop",
"athlete"
],
"href": "http://www.espn.com/nba/player/advancedstats/_/id/481/grant-long",
"text": "Advanced Stats"
}
],
"jersey": "43",
"position": {
"name": "Forward",
"displayName": "Forward",
"abbreviation": "F"
}
},
"starter": false,
"didNotPlay": true,
"ejected": false,
"stats": []
},
{
"active": false,
"athlete": {
"id": "28",
"uid": "s:40~l:46~a:28",
"guid": "daf5f734a1061d2600ee4c3ea26d20e0",
"displayName": "Isaac Austin",
"shortName": "I. Austin",
"links": [
{
"rel": [
"playercard",
"desktop",
"athlete"
],
"href": "https://www.espn.com/nba/player/_/id/28/isaac-austin",
"text": "Player Card"
},
{
"rel": [
"stats",
"desktop",
"athlete"
],
"href": "http://www.espn.com/nba/player/stats/_/id/28/isaac-austin",
"text": "Stats"
},
{
"rel": [
"splits",
"desktop",
"athlete"
],
"href": "http://www.espn.com/nba/player/splits/_/id/28/isaac-austin",
"text": "Splits"
},
{
"rel": [
"gamelog",
"desktop",
"athlete"
],
"href": "http://www.espn.com/nba/player/gamelog/_/id/28/isaac-austin",
"text": "Game Log"
},
{
"rel": [
"news",
"desktop",
"athlete"
],
"href": "http://www.espn.com/nba/player/news/_/id/28/isaac-austin",
"text": "News"
},
{
"rel": [
"bio",
"desktop",
"athlete"
],
"href": "http://www.espn.com/nba/player/bio/_/id/28/isaac-austin",
"text": "Bio"
},
{
"rel": [
"overview",
"desktop",
"athlete"
],
"href": "http://www.espn.com/nba/player/_/id/28/isaac-austin",
"text": "Overview"
},
{
"rel": [
"advancedstats",
"desktop",
"athlete"
],
"href": "http://www.espn.com/nba/player/advancedstats/_/id/28/isaac-austin",
"text": "Advanced Stats"
}
],
"jersey": "9",
"position": {
"name": "Center",
"displayName": "Center",
"abbreviation": "C"
}
},
"starter": false,
"didNotPlay": true,
"ejected": false,
"stats": []
},
{
"active": false,
"athlete": {
"id": "1023",
"uid": "s:40~l:46~a:1023",
"guid": "f2c803df5cbe9ee2eebdb45dce74a8da",
"displayName": "Will Solomon",
"shortName": "W. Solomon",
"links": [
{
"rel": [
"playercard",
"desktop",
"athlete"
],
"href": "https://www.espn.com/nba/player/_/id/1023/will-solomon",
"text": "Player Card"
},
{
"rel": [
"stats",
"desktop",
"athlete"
],
"href": "http://www.espn.com/nba/player/stats/_/id/1023/will-solomon",
"text": "Stats"
},
{
"rel": [
"splits",
"desktop",
"athlete"
],
"href": "http://www.espn.com/nba/player/splits/_/id/1023/will-solomon",
"text": "Splits"
},
{
"rel": [
"gamelog",
"desktop",
"athlete"
],
"href": "http://www.espn.com/nba/player/gamelog/_/id/1023/will-solomon",
"text": "Game Log"
},
{
"rel": [
"news",
"desktop",
"athlete"
],
"href": "http://www.espn.com/nba/player/news/_/id/1023/will-solomon",
"text": "News"
},
{
"rel": [
"bio",
"desktop",
"athlete"
],
"href": "http://www.espn.com/nba/player/bio/_/id/1023/will-solomon",
"text": "Bio"
},
{
"rel": [
"overview",
"desktop",
"athlete"
],
"href": "http://www.espn.com/nba/player/_/id/1023/will-solomon",
"text": "Overview"
},
{
"rel": [
"advancedstats",
"desktop",
"athlete"
],
"href": "http://www.espn.com/nba/player/advancedstats/_/id/1023/will-solomon",
"text": "Advanced Stats"
}
],
"jersey": "17",
"position": {
"name": "Point Guard",
"displayName": "Point Guard",
"abbreviation": "PG"
}
},
"starter": false,
"didNotPlay": true,
"ejected": false,
"stats": []
}
],
"totals": [
"",
"35-87",
"5-13",
"13-20",
"13",
"28",
"41",
"21",
"12",
"4",
"20",
"22",
"",
"88"
]
}
]
},
{
"team": {
"id": "28",
"uid": "s:40~l:46~t:28",
"slug": "toronto-raptors",
"location": "Toronto",
"name": "Raptors",
"abbreviation": "TOR",
"displayName": "Toronto Raptors",
"shortDisplayName": "Raptors",
"color": "CE0F41",
"alternateColor": "061922",
"logo": "https://a.espncdn.com/i/teamlogos/nba/500/tor.png"
},
"statistics": [
{
"names": [
"MIN",
"FG",
"3PT",
"FT",
"OREB",
"DREB",
"REB",
"AST",
"STL",
"BLK",
"TO",
"PF",
"+/-",
"PTS"
],
"keys": [
"minutes",
"fieldGoalsMade-fieldGoalsAttempted",
"threePointFieldGoalsMade-threePointFieldGoalsAttempted",
"freeThrowsMade-freeThrowsAttempted",
"offensiveRebounds",
"defensiveRebounds",
"rebounds",
"assists",
"steals",
"blocks",
"turnovers",
"fouls",
"plusMinus",
"points"
],
"labels": [
"MIN",
"FG",
"3PT",
"FT",
"OREB",
"DREB",
"REB",
"AST",
"STL",
"BLK",
"TO",
"PF",
"+/-",
"PTS"
],
"descriptions": [
"Minutes",
"Field Goals Made/Attempted",
"3-Point Field Goals Made/Attempted",
"Free Throws Made/Attempted",
"Offensive Rebounds",
"Defensive Rebounds",
"Rebounds",
"Assists",
"Steals",
"Blocks",
"Turnovers",
"Personal Fouls",
"Teams net points while player is on the court.",
"Points"
],
"athletes": [
{
"active": false,
"athlete": {
"id": "189",
"uid": "s:40~l:46~a:189",
"guid": "d29eb4e9d4fed18e301749b0afde84f6",
"displayName": "Antonio Davis",
"shortName": "A. Davis",
"links": [
{
"rel": [
"playercard",
"desktop",
"athlete"
],
"href": "https://www.espn.com/nba/player/_/id/189/antonio-davis",
"text": "Player Card"
},
{
"rel": [
"stats",
"desktop",
"athlete"
],
"href": "http://www.espn.com/nba/player/stats/_/id/189/antonio-davis",
"text": "Stats"
},
{
"rel": [
"splits",
"desktop",
"athlete"
],
"href": "http://www.espn.com/nba/player/splits/_/id/189/antonio-davis",
"text": "Splits"
},
{
"rel": [
"gamelog",
"desktop",
"athlete"
],
"href": "http://www.espn.com/nba/player/gamelog/_/id/189/antonio-davis",
"text": "Game Log"
},
{
"rel": [
"news",
"desktop",
"athlete"
],
"href": "http://www.espn.com/nba/player/news/_/id/189/antonio-davis",
"text": "News"
},
{
"rel": [
"bio",
"desktop",
"athlete"
],
"href": "http://www.espn.com/nba/player/bio/_/id/189/antonio-davis",
"text": "Bio"
},
{
"rel": [
"overview",
"desktop",
"athlete"
],
"href": "http://www.espn.com/nba/player/_/id/189/antonio-davis",
"text": "Overview"
},
{
"rel": [
"advancedstats",
"desktop",
"athlete"
],
"href": "http://www.espn.com/nba/player/advancedstats/_/id/189/antonio-davis",
"text": "Advanced Stats"
}
],
"jersey": "33",
"position": {
"name": "Power Forward",
"displayName": "Power Forward",
"abbreviation": "PF"
}
},
"starter": true,
"didNotPlay": false,
"ejected": false,
"stats": [
"40",
"8-15",
"0-0",
"4-4",
"3",
"8",
"11",
"1",
"3",
"3",
"1",
"3",
"--",
"20"
]
},
{
"active": false,
"athlete": {
"id": "619",
"uid": "s:40~l:46~a:619",
"guid": "12a91384b3a3717ecc6707f923a28597",
"displayName": "Hakeem Olajuwon",
"shortName": "H. Olajuwon",
"links": [
{
"rel": [
"playercard",
"desktop",
"athlete"
],
"href": "https://www.espn.com/nba/player/_/id/619/hakeem-olajuwon",
"text": "Player Card"
},
{
"rel": [
"stats",
"desktop",
"athlete"
],
"href": "http://www.espn.com/nba/player/stats/_/id/619/hakeem-olajuwon",
"text": "Stats"
},
{
"rel": [
"splits",
"desktop",
"athlete"
],
"href": "http://www.espn.com/nba/player/splits/_/id/619/hakeem-olajuwon",
"text": "Splits"
},
{
"rel": [
"gamelog",
"desktop",
"athlete"
],
"href": "http://www.espn.com/nba/player/gamelog/_/id/619/hakeem-olajuwon",
"text": "Game Log"
},
{
"rel": [
"news",
"desktop",
"athlete"
],
"href": "http://www.espn.com/nba/player/news/_/id/619/hakeem-olajuwon",
"text": "News"
},
{
"rel": [
"bio",
"desktop",
"athlete"
],
"href": "http://www.espn.com/nba/player/bio/_/id/619/hakeem-olajuwon",
"text": "Bio"
},
{
"rel": [
"overview",
"desktop",
"athlete"
],
"href": "http://www.espn.com/nba/player/_/id/619/hakeem-olajuwon",
"text": "Overview"
},
{
"rel": [
"advancedstats",
"desktop",
"athlete"
],
"href": "http://www.espn.com/nba/player/advancedstats/_/id/619/hakeem-olajuwon",
"text": "Advanced Stats"
}
],
"jersey": "34",
"position": {
"name": "Center",
"displayName": "Center",
"abbreviation": "C"
}
},
"starter": true,
"didNotPlay": false,
"ejected": false,
"stats": [
"24",
"4-10",
"0-0",
"2-4",
"1",
"6",
"7",
"1",
"1",
"1",
"4",
"5",
"--",
"10"
]
},
{
"active": false,
"athlete": {
"id": "931",
"uid": "s:40~l:46~a:931",
"guid": "02dc6303422f1bcd8d8c5a30d4918639",
"displayName": "Alvin Williams",
"shortName": "A. Williams",
"links": [
{
"rel": [
"playercard",
"desktop",
"athlete"
],
"href": "https://www.espn.com/nba/player/_/id/931/alvin-williams",
"text": "Player Card"
},
{
"rel": [
"stats",
"desktop",
"athlete"
],
"href": "http://www.espn.com/nba/player/stats/_/id/931/alvin-williams",
"text": "Stats"
},
{
"rel": [
"splits",
"desktop",
"athlete"
],
"href": "http://www.espn.com/nba/player/splits/_/id/931/alvin-williams",
"text": "Splits"
},
{
"rel": [
"gamelog",
"desktop",
"athlete"
],
"href": "http://www.espn.com/nba/player/gamelog/_/id/931/alvin-williams",
"text": "Game Log"
},
{
"rel": [
"news",
"desktop",
"athlete"
],
"href": "http://www.espn.com/nba/player/news/_/id/931/alvin-williams",
"text": "News"
},
{
"rel": [
"bio",
"desktop",
"athlete"
],
"href": "http://www.espn.com/nba/player/bio/_/id/931/alvin-williams",
"text": "Bio"
},
{
"rel": [
"overview",
"desktop",
"athlete"
],
"href": "http://www.espn.com/nba/player/_/id/931/alvin-williams",
"text": "Overview"
},
{
"rel": [
"advancedstats",
"desktop",
"athlete"
],
"href": "http://www.espn.com/nba/player/advancedstats/_/id/931/alvin-williams",
"text": "Advanced Stats"
}
],
"jersey": "24",
"position": {
"name": "Point Guard",
"displayName": "Point Guard",
"abbreviation": "PG"
}
},
"starter": true,
"didNotPlay": false,
"ejected": false,
"stats": [
"37",
"3-8",
"0-1",
"4-4",
"1",
"2",
"3",
"7",
"2",
"0",
"2",
"1",
"--",
"10"
]
},
{
"active": false,
"athlete": {
"id": "656",
"uid": "s:40~l:46~a:656",
"guid": "7148a4b1d5ed7c674ee0274afd7eb290",
"displayName": "Morris Peterson",
"shortName": "M. Peterson",
"links": [
{
"rel": [
"playercard",
"desktop",
"athlete"
],
"href": "https://www.espn.com/nba/player/_/id/656/morris-peterson",
"text": "Player Card"
},
{
"rel": [
"stats",
"desktop",
"athlete"
],
"href": "http://www.espn.com/nba/player/stats/_/id/656/morris-peterson",
"text": "Stats"
},
{
"rel": [
"splits",
"desktop",
"athlete"
],
"href": "http://www.espn.com/nba/player/splits/_/id/656/morris-peterson",
"text": "Splits"
},
{
"rel": [
"gamelog",
"desktop",
"athlete"
],
"href": "http://www.espn.com/nba/player/gamelog/_/id/656/morris-peterson",
"text": "Game Log"
},
{
"rel": [
"news",
"desktop",
"athlete"
],
"href": "http://www.espn.com/nba/player/news/_/id/656/morris-peterson",
"text": "News"
},
{
"rel": [
"bio",
"desktop",
"athlete"
],
"href": "http://www.espn.com/nba/player/bio/_/id/656/morris-peterson",
"text": "Bio"
},
{
"rel": [
"overview",
"desktop",
"athlete"
],
"href": "http://www.espn.com/nba/player/_/id/656/morris-peterson",
"text": "Overview"
},
{
"rel": [
"advancedstats",
"desktop",
"athlete"
],
"href": "http://www.espn.com/nba/player/advancedstats/_/id/656/morris-peterson",
"text": "Advanced Stats"
}
],
"headshot": {
"href": "https://a.espncdn.com/i/headshots/nba/players/full/656.png",
"alt": "Morris Peterson"
},
"position": {
"name": "Shooting Guard",
"displayName": "Shooting Guard",
"abbreviation": "SG"
}
},
"starter": true,
"didNotPlay": false,
"ejected": false,
"stats": [
"30",
"6-12",
"2-2",
"4-4",
"0",
"1",
"1",
"2",
"1",
"0",
"1",
"1",
"--",
"18"
]
},
{
"active": false,
"athlete": {
"id": "136",
"uid": "s:40~l:46~a:136",
"guid": "b41883b9b15e09c6e17458adb1e38290",
"displayName": "Vince Carter",
"shortName": "V. Carter",
"links": [
{
"rel": [
"playercard",
"desktop",
"athlete"
],
"href": "https://www.espn.com/nba/player/_/id/136/vince-carter",
"text": "Player Card"
},
{
"rel": [
"stats",
"desktop",
"athlete"
],
"href": "http://www.espn.com/nba/player/stats/_/id/136/vince-carter",
"text": "Stats"
},
{
"rel": [
"splits",
"desktop",
"athlete"
],
"href": "http://www.espn.com/nba/player/splits/_/id/136/vince-carter",
"text": "Splits"
},
{
"rel": [
"gamelog",
"desktop",
"athlete"
],
"href": "http://www.espn.com/nba/player/gamelog/_/id/136/vince-carter",
"text": "Game Log"
},
{
"rel": [
"news",
"desktop",
"athlete"
],
"href": "http://www.espn.com/nba/player/news/_/id/136/vince-carter",
"text": "News"
},
{
"rel": [
"bio",
"desktop",
"athlete"
],
"href": "http://www.espn.com/nba/player/bio/_/id/136/vince-carter",
"text": "Bio"
},
{
"rel": [
"overview",
"desktop",
"athlete"
],
"href": "http://www.espn.com/nba/player/_/id/136/vince-carter",
"text": "Overview"
},
{
"rel": [
"advancedstats",
"desktop",
"athlete"
],
"href": "http://www.espn.com/nba/player/advancedstats/_/id/136/vince-carter",
"text": "Advanced Stats"
}
],
"headshot": {
"href": "https://a.espncdn.com/i/headshots/nba/players/full/136.png",
"alt": "Vince Carter"
},
"jersey": "15",
"position": {
"name": "Guard",
"displayName": "Guard",
"abbreviation": "G"
}
},
"starter": true,
"didNotPlay": false,
"ejected": false,
"stats": [
"45",
"9-21",
"1-3",
"4-4",
"2",
"6",
"8",
"7",
"0",
"1",
"2",
"2",
"--",
"23"
]
},
{
"active": false,
"athlete": {
"id": "149",
"uid": "s:40~l:46~a:149",
"guid": "ee7dca7cf929071336de92e6058c4bca",
"displayName": "Keon Clark",
"shortName": "K. Clark",
"links": [
{
"rel": [
"playercard",
"desktop",
"athlete"
],
"href": "https://www.espn.com/nba/player/_/id/149/keon-clark",
"text": "Player Card"
},
{
"rel": [
"stats",
"desktop",
"athlete"
],
"href": "http://www.espn.com/nba/player/stats/_/id/149/keon-clark",
"text": "Stats"
},
{
"rel": [
"splits",
"desktop",
"athlete"
],
"href": "http://www.espn.com/nba/player/splits/_/id/149/keon-clark",
"text": "Splits"
},
{
"rel": [
"gamelog",
"desktop",
"athlete"
],
"href": "http://www.espn.com/nba/player/gamelog/_/id/149/keon-clark",
"text": "Game Log"
},
{
"rel": [
"news",
"desktop",
"athlete"
],
"href": "http://www.espn.com/nba/player/news/_/id/149/keon-clark",
"text": "News"
},
{
"rel": [
"bio",
"desktop",
"athlete"
],
"href": "http://www.espn.com/nba/player/bio/_/id/149/keon-clark",
"text": "Bio"
},
{
"rel": [
"overview",
"desktop",
"athlete"
],
"href": "http://www.espn.com/nba/player/_/id/149/keon-clark",
"text": "Overview"
},
{
"rel": [
"advancedstats",
"desktop",
"athlete"
],
"href": "http://www.espn.com/nba/player/advancedstats/_/id/149/keon-clark",
"text": "Advanced Stats"
}
],
"jersey": "13",
"position": {
"name": "Power Forward",
"displayName": "Power Forward",
"abbreviation": "PF"
}
},
"starter": false,
"didNotPlay": false,
"ejected": false,
"stats": [
"18",
"0-4",
"0-1",
"4-4",
"1",
"5",
"6",
"0",
"1",
"1",
"3",
"4",
"--",
"4"
]
},
{
"active": false,
"athlete": {
"id": "930",
"uid": "s:40~l:46~a:930",
"guid": "3c2bf7103fee9e12ef5b10f931338625",
"displayName": "Jerome Williams",
"shortName": "J. Williams",
"links": [
{
"rel": [
"playercard",
"desktop",
"athlete"
],
"href": "https://www.espn.com/nba/player/_/id/930/jerome-williams",
"text": "Player Card"
},
{
"rel": [
"stats",
"desktop",
"athlete"
],
"href": "http://www.espn.com/nba/player/stats/_/id/930/jerome-williams",
"text": "Stats"
},
{
"rel": [
"splits",
"desktop",
"athlete"
],
"href": "http://www.espn.com/nba/player/splits/_/id/930/jerome-williams",
"text": "Splits"
},
{
"rel": [
"gamelog",
"desktop",
"athlete"
],
"href": "http://www.espn.com/nba/player/gamelog/_/id/930/jerome-williams",
"text": "Game Log"
},
{
"rel": [
"news",
"desktop",
"athlete"
],
"href": "http://www.espn.com/nba/player/news/_/id/930/jerome-williams",
"text": "News"
},
{
"rel": [
"bio",
"desktop",
"athlete"
],
"href": "http://www.espn.com/nba/player/bio/_/id/930/jerome-williams",
"text": "Bio"
},
{
"rel": [
"overview",
"desktop",
"athlete"
],
"href": "http://www.espn.com/nba/player/_/id/930/jerome-williams",
"text": "Overview"
},
{
"rel": [
"advancedstats",
"desktop",
"athlete"
],
"href": "http://www.espn.com/nba/player/advancedstats/_/id/930/jerome-williams",
"text": "Advanced Stats"
}
],
"jersey": "31",
"position": {
"name": "Power Forward",
"displayName": "Power Forward",
"abbreviation": "PF"
}
},
"starter": false,
"didNotPlay": false,
"ejected": false,
"stats": [
"17",
"2-4",
"0-0",
"0-0",
"2",
"4",
"6",
"0",
"2",
"1",
"3",
"2",
"--",
"4"
]
},
{
"active": false,
"athlete": {
"id": "585",
"uid": "s:40~l:46~a:585",
"guid": "467d637522cd73053fcaa70ed17f6229",
"displayName": "Tracy Murray",
"shortName": "T. Murray",
"links": [
{
"rel": [
"playercard",
"desktop",
"athlete"
],
"href": "https://www.espn.com/nba/player/_/id/585/tracy-murray",
"text": "Player Card"
},
{
"rel": [
"stats",
"desktop",
"athlete"
],
"href": "http://www.espn.com/nba/player/stats/_/id/585/tracy-murray",
"text": "Stats"
},
{
"rel": [
"splits",
"desktop",
"athlete"
],
"href": "http://www.espn.com/nba/player/splits/_/id/585/tracy-murray",
"text": "Splits"
},
{
"rel": [
"gamelog",
"desktop",
"athlete"
],
"href": "http://www.espn.com/nba/player/gamelog/_/id/585/tracy-murray",
"text": "Game Log"
},
{
"rel": [
"news",
"desktop",
"athlete"
],
"href": "http://www.espn.com/nba/player/news/_/id/585/tracy-murray",
"text": "News"
},
{
"rel": [
"bio",
"desktop",
"athlete"
],
"href": "http://www.espn.com/nba/player/bio/_/id/585/tracy-murray",
"text": "Bio"
},
{
"rel": [
"overview",
"desktop",
"athlete"
],
"href": "http://www.espn.com/nba/player/_/id/585/tracy-murray",
"text": "Overview"
},
{
"rel": [
"advancedstats",
"desktop",
"athlete"
],
"href": "http://www.espn.com/nba/player/advancedstats/_/id/585/tracy-murray",
"text": "Advanced Stats"
}
],
"jersey": "35",
"position": {
"name": "Small Forward",
"displayName": "Small Forward",
"abbreviation": "SF"
}
},
"starter": false,
"didNotPlay": false,
"ejected": false,
"stats": [
"4",
"0-0",
"0-0",
"0-0",
"0",
"1",
"1",
"0",
"0",
"0",
"0",
"0",
"--",
"0"
]
},
{
"active": false,
"athlete": {
"id": "146",
"uid": "s:40~l:46~a:146",
"guid": "8dd6745b07f0386bd02e2e671d8d3887",
"displayName": "Chris Childs",
"shortName": "C. Childs",
"links": [
{
"rel": [
"playercard",
"desktop",
"athlete"
],
"href": "https://www.espn.com/nba/player/_/id/146/chris-childs",
"text": "Player Card"
},
{
"rel": [
"stats",
"desktop",
"athlete"
],
"href": "http://www.espn.com/nba/player/stats/_/id/146/chris-childs",
"text": "Stats"
},
{
"rel": [
"splits",
"desktop",
"athlete"
],
"href": "http://www.espn.com/nba/player/splits/_/id/146/chris-childs",
"text": "Splits"
},
{
"rel": [
"gamelog",
"desktop",
"athlete"
],
"href": "http://www.espn.com/nba/player/gamelog/_/id/146/chris-childs",
"text": "Game Log"
},
{
"rel": [
"news",
"desktop",
"athlete"
],
"href": "http://www.espn.com/nba/player/news/_/id/146/chris-childs",
"text": "News"
},
{
"rel": [
"bio",
"desktop",
"athlete"
],
"href": "http://www.espn.com/nba/player/bio/_/id/146/chris-childs",
"text": "Bio"
},
{
"rel": [
"overview",
"desktop",
"athlete"
],
"href": "http://www.espn.com/nba/player/_/id/146/chris-childs",
"text": "Overview"
},
{
"rel": [
"advancedstats",
"desktop",
"athlete"
],
"href": "http://www.espn.com/nba/player/advancedstats/_/id/146/chris-childs",
"text": "Advanced Stats"
}
],
"jersey": "11",
"position": {
"name": "Guard",
"displayName": "Guard",
"abbreviation": "G"
}
},
"starter": false,
"didNotPlay": false,
"ejected": false,
"stats": [
"15",
"0-0",
"0-0",
"0-0",
"0",
"0",
"0",
"1",
"1",
"0",
"3",
"1",
"--",
"0"
]
},
{
"active": false,
"athlete": {
"id": "175",
"uid": "s:40~l:46~a:175",
"guid": "3b3038f7ea506c18f88dcb6892c7b72b",
"displayName": "Dell Curry",
"shortName": "D. Curry",
"links": [
{
"rel": [
"playercard",
"desktop",
"athlete"
],
"href": "https://www.espn.com/nba/player/_/id/175/dell-curry",
"text": "Player Card"
},
{
"rel": [
"stats",
"desktop",
"athlete"
],
"href": "http://www.espn.com/nba/player/stats/_/id/175/dell-curry",
"text": "Stats"
},
{
"rel": [
"splits",
"desktop",
"athlete"
],
"href": "http://www.espn.com/nba/player/splits/_/id/175/dell-curry",
"text": "Splits"
},
{
"rel": [
"gamelog",
"desktop",
"athlete"
],
"href": "http://www.espn.com/nba/player/gamelog/_/id/175/dell-curry",
"text": "Game Log"
},
{
"rel": [
"news",
"desktop",
"athlete"
],
"href": "http://www.espn.com/nba/player/news/_/id/175/dell-curry",
"text": "News"
},
{
"rel": [
"bio",
"desktop",
"athlete"
],
"href": "http://www.espn.com/nba/player/bio/_/id/175/dell-curry",
"text": "Bio"
},
{
"rel": [
"overview",
"desktop",
"athlete"
],
"href": "http://www.espn.com/nba/player/_/id/175/dell-curry",
"text": "Overview"
},
{
"rel": [
"advancedstats",
"desktop",
"athlete"
],
"href": "http://www.espn.com/nba/player/advancedstats/_/id/175/dell-curry",
"text": "Advanced Stats"
}
],
"jersey": "99",
"position": {
"name": "Guard",
"displayName": "Guard",
"abbreviation": "G"
}
},
"starter": false,
"didNotPlay": false,
"ejected": false,
"stats": [
"10",
"1-4",
"0-2",
"0-0",
"1",
"0",
"1",
"0",
"0",
"0",
"0",
"1",
"--",
"2"
]
},
{
"active": false,
"athlete": {
"id": "571",
"uid": "s:40~l:46~a:571",
"guid": "4bd5e34bb9ad236bfffd7f59c73261a8",
"displayName": "Eric Montross",
"shortName": "E. Montross",
"links": [
{
"rel": [
"playercard",
"desktop",
"athlete"
],
"href": "https://www.espn.com/nba/player/_/id/571/eric-montross",
"text": "Player Card"
},
{
"rel": [
"stats",
"desktop",
"athlete"
],
"href": "http://www.espn.com/nba/player/stats/_/id/571/eric-montross",
"text": "Stats"
},
{
"rel": [
"splits",
"desktop",
"athlete"
],
"href": "http://www.espn.com/nba/player/splits/_/id/571/eric-montross",
"text": "Splits"
},
{
"rel": [
"gamelog",
"desktop",
"athlete"
],
"href": "http://www.espn.com/nba/player/gamelog/_/id/571/eric-montross",
"text": "Game Log"
},
{
"rel": [
"news",
"desktop",
"athlete"
],
"href": "http://www.espn.com/nba/player/news/_/id/571/eric-montross",
"text": "News"
},
{
"rel": [
"bio",
"desktop",
"athlete"
],
"href": "http://www.espn.com/nba/player/bio/_/id/571/eric-montross",
"text": "Bio"
},
{
"rel": [
"overview",
"desktop",
"athlete"
],
"href": "http://www.espn.com/nba/player/_/id/571/eric-montross",
"text": "Overview"
},
{
"rel": [
"advancedstats",
"desktop",
"athlete"
],
"href": "http://www.espn.com/nba/player/advancedstats/_/id/571/eric-montross",
"text": "Advanced Stats"
}
],
"jersey": "0",
"position": {
"name": "Center",
"displayName": "Center",
"abbreviation": "C"
}
},
"starter": false,
"didNotPlay": true,
"ejected": false,
"stats": []
},
{
"active": false,
"athlete": {
"id": "1055",
"uid": "s:40~l:46~a:1055",
"guid": "a58dfe2baa56ad50085d6210def7160b",
"displayName": "Carlos Arroyo",
"shortName": "C. Arroyo",
"links": [
{
"rel": [
"playercard",
"desktop",
"athlete"
],
"href": "https://www.espn.com/nba/player/_/id/1055/carlos-arroyo",
"text": "Player Card"
},
{
"rel": [
"stats",
"desktop",
"athlete"
],
"href": "http://www.espn.com/nba/player/stats/_/id/1055/carlos-arroyo",
"text": "Stats"
},
{
"rel": [
"splits",
"desktop",
"athlete"
],
"href": "http://www.espn.com/nba/player/splits/_/id/1055/carlos-arroyo",
"text": "Splits"
},
{
"rel": [
"gamelog",
"desktop",
"athlete"
],
"href": "http://www.espn.com/nba/player/gamelog/_/id/1055/carlos-arroyo",
"text": "Game Log"
},
{
"rel": [
"news",
"desktop",
"athlete"
],
"href": "http://www.espn.com/nba/player/news/_/id/1055/carlos-arroyo",
"text": "News"
},
{
"rel": [
"bio",
"desktop",
"athlete"
],
"href": "http://www.espn.com/nba/player/bio/_/id/1055/carlos-arroyo",
"text": "Bio"
},
{
"rel": [
"overview",
"desktop",
"athlete"
],
"href": "http://www.espn.com/nba/player/_/id/1055/carlos-arroyo",
"text": "Overview"
},
{
"rel": [
"advancedstats",
"desktop",
"athlete"
],
"href": "http://www.espn.com/nba/player/advancedstats/_/id/1055/carlos-arroyo",
"text": "Advanced Stats"
}
],
"headshot": {
"href": "https://a.espncdn.com/i/headshots/nba/players/full/1055.png",
"alt": "Carlos Arroyo"
},
"jersey": "45",
"position": {
"name": "Point Guard",
"displayName": "Point Guard",
"abbreviation": "PG"
}
},
"starter": false,
"didNotPlay": true,
"ejected": false,
"stats": []
}
],
"totals": [
"",
"33-78",
"3-9",
"22-24",
"11",
"33",
"44",
"19",
"11",
"7",
"20",
"20",
"",
"91"
]
}
]
}
]
},
"format": {
"regulation": {
"periods": 4,
"displayName": "Quarter",
"slug": "quarter",
"clock": 720.0
},
"overtime": {
"clock": 300.0
}
},
"gameInfo": {
"venue": {
"id": "1838",
"fullName": "Scotiabank Arena",
"shortName": "Scotiabank Arena",
"address": {
"city": "Toronto",
"state": "ON"
},
"capacity": 19800,
"grass": false,
"images": [
{
"href": "https://a.espncdn.com/i/venues/nba/day/1838.jpg",
"width": 2000,
"height": 1125,
"alt": "",
"rel": [
"full",
"day"
]
}
]
},
"attendance": 19800,
"officials": [
{
"fullName": "Joe Forte",
"displayName": "Joe Forte",
"position": {
"name": "Referee",
"displayName": "Referee",
"id": "40"
},
"order": 1
},
{
"fullName": "Mike Mathis",
"displayName": "Mike Mathis",
"position": {
"name": "Referee",
"displayName": "Referee",
"id": "40"
},
"order": 2
},
{
"fullName": "Michael Smith",
"displayName": "Michael Smith",
"position": {
"name": "Referee",
"displayName": "Referee",
"id": "40"
},
"order": 3
}
]
},
"leaders": [
{
"team": {
"id": "28",
"uid": "s:40~l:46~t:28",
"displayName": "Toronto Raptors",
"abbreviation": "TOR",
"links": [
{
"href": "https://www.espn.com/nba/team/_/name/tor/toronto-raptors",
"text": "Clubhouse"
},
{
"href": "https://www.espn.com/nba/team/schedule/_/name/tor",
"text": "Schedule"
}
],
"logo": "https://a.espncdn.com/i/teamlogos/nba/500/tor.png",
"logos": [
{
"href": "https://a.espncdn.com/i/teamlogos/nba/500/tor.png",
"width": 500,
"height": 500,
"alt": "",
"rel": [
"full",
"default"
],
"lastUpdated": "2019-04-09T18:15Z"
},
{
"href": "https://a.espncdn.com/i/teamlogos/nba/500-dark/tor.png",
"width": 500,
"height": 500,
"alt": "",
"rel": [
"full",
"dark"
],
"lastUpdated": "2019-05-31T20:44Z"
}
]
},
"leaders": [
{
"name": "points",
"displayName": "Points",
"leaders": [
{
"displayValue": "23",
"athlete": {
"id": "136",
"uid": "s:40~l:46~a:136",
"guid": "b41883b9b15e09c6e17458adb1e38290",
"lastName": "Carter",
"fullName": "Vince Carter",
"displayName": "Vince Carter",
"shortName": "V. Carter",
"links": [
{
"rel": [
"playercard",
"desktop",
"athlete"
],
"href": "https://www.espn.com/nba/player/_/id/136/vince-carter",
"text": "Player Card"
}
],
"headshot": {
"href": "https://a.espncdn.com/i/headshots/nba/players/full/136.png",
"alt": "Vince Carter"
},
"jersey": "15",
"position": {
"abbreviation": "G"
},
"team": {
"$ref": "http://sports.core.api.espn.pvt/v2/sports/basketball/leagues/nba/seasons/2002/teams/28?lang=en&region=us"
}
},
"statistics": [
{
"name": "points",
"displayName": "Points",
"shortDisplayName": "PTS",
"description": "The number of points scored.",
"abbreviation": "PTS",
"value": 23.0,
"displayValue": "23"
},
{
"name": "fieldGoals",
"displayName": "Field Goals",
"shortDisplayName": "FG",
"description": "Field Goal makes and attempts.",
"abbreviation": "FG",
"value": 0.428571,
"displayValue": "9/21"
},
{
"name": "freeThrows",
"displayName": "Free Throws",
"shortDisplayName": "FT",
"description": "Free Throw makes and attempts.",
"abbreviation": "FT",
"value": 1.0,
"displayValue": "4/4"
}
]
}
]
},
{
"name": "assists",
"displayName": "Assists",
"leaders": [
{
"displayValue": "7",
"athlete": {
"id": "136",
"uid": "s:40~l:46~a:136",
"guid": "b41883b9b15e09c6e17458adb1e38290",
"lastName": "Carter",
"fullName": "Vince Carter",
"displayName": "Vince Carter",
"shortName": "V. Carter",
"links": [
{
"rel": [
"playercard",
"desktop",
"athlete"
],
"href": "https://www.espn.com/nba/player/_/id/136/vince-carter",
"text": "Player Card"
}
],
"headshot": {
"href": "https://a.espncdn.com/i/headshots/nba/players/full/136.png",
"alt": "Vince Carter"
},
"jersey": "15",
"position": {
"abbreviation": "G"
},
"team": {
"$ref": "http://sports.core.api.espn.pvt/v2/sports/basketball/leagues/nba/seasons/2002/teams/28?lang=en&region=us"
}
},
"statistics": [
{
"name": "assists",
"displayName": "Assists",
"shortDisplayName": "AST",
"description": "The number of times a player who passes the ball to a teammate in a way that leads to a score by field goal, meaning that he or she was \"assisting\" in the basket. There is some judgment involved in deciding whether a passer should be credited with an assist.",
"abbreviation": "AST",
"value": 7.0,
"displayValue": "7"
},
{
"name": "turnovers",
"displayName": "Turnovers",
"shortDisplayName": "TO",
"description": "The number of times a player loses possession to the other team.",
"abbreviation": "TO",
"value": 2.0,
"displayValue": "2"
},
{
"name": "minutes",
"displayName": "Minutes",
"shortDisplayName": "MIN",
"description": "The total number of minutes played.",
"abbreviation": "MIN",
"value": 45.0,
"displayValue": "45"
},
{
"name": "assistTurnoverRatio",
"displayName": "Assist To Turnover Ratio",
"shortDisplayName": "AST/TO",
"description": "The average number of assists a player or team records per turnover",
"abbreviation": "AST/TO",
"value": 3.5,
"displayValue": "3.5"
}
]
}
]
},
{
"name": "rebounds",
"displayName": "Rebounds",
"leaders": [
{
"displayValue": "11",
"athlete": {
"id": "189",
"uid": "s:40~l:46~a:189",
"guid": "d29eb4e9d4fed18e301749b0afde84f6",
"lastName": "Davis",
"fullName": "Antonio Davis",
"displayName": "Antonio Davis",
"shortName": "A. Davis",
"links": [
{
"rel": [
"playercard",
"desktop",
"athlete"
],
"href": "https://www.espn.com/nba/player/_/id/189/antonio-davis",
"text": "Player Card"
}
],
"jersey": "33",
"position": {
"abbreviation": "PF"
},
"team": {
"$ref": "http://sports.core.api.espn.pvt/v2/sports/basketball/leagues/nba/seasons/2002/teams/28?lang=en&region=us"
}
},
"statistics": [
{
"name": "rebounds",
"displayName": "Rebounds",
"shortDisplayName": "REB",
"description": "The total number of rebounds (offensive and defensive).",
"abbreviation": "REB",
"value": 11.0,
"displayValue": "11"
},
{
"name": "defensiveRebounds",
"displayName": "Defensive Rebounds",
"shortDisplayName": "DREB",
"description": "The number of times when the defense obtains the possession of the ball after a missed shot by the offense.",
"abbreviation": "DR",
"value": 8.0,
"displayValue": "8"
},
{
"name": "offensiveRebounds",
"displayName": "Offensive Rebounds",
"shortDisplayName": "OREB",
"description": "The number of times when the offense obtains the possession of the ball after a missed shot.",
"abbreviation": "OR",
"value": 3.0,
"displayValue": "3"
}
]
}
]
}
]
},
{
"team": {
"id": "29",
"uid": "s:40~l:46~t:29",
"displayName": "Memphis Grizzlies",
"abbreviation": "MEM",
"links": [
{
"href": "https://www.espn.com/nba/team/_/name/mem/memphis-grizzlies",
"text": "Clubhouse"
},
{
"href": "https://www.espn.com/nba/team/schedule/_/name/mem",
"text": "Schedule"
}
],
"logo": "https://a.espncdn.com/i/teamlogos/nba/500/mem.png",
"logos": [
{
"href": "https://a.espncdn.com/i/teamlogos/nba/500/mem.png",
"width": 500,
"height": 500,
"alt": "",
"rel": [
"full",
"default"
],
"lastUpdated": "2018-10-12T14:51Z"
},
{
"href": "https://a.espncdn.com/i/teamlogos/nba/500-dark/mem.png",
"width": 500,
"height": 500,
"alt": "",
"rel": [
"full",
"dark"
],
"lastUpdated": "2018-10-12T14:51Z"
}
]
},
"leaders": [
{
"name": "points",
"displayName": "Points",
"leaders": [
{
"displayValue": "22",
"athlete": {
"id": "996",
"uid": "s:40~l:46~a:996",
"guid": "9955bf55e140871b2f0d7e3d74dadd23",
"lastName": "Gasol",
"fullName": "Pau Gasol",
"displayName": "Pau Gasol",
"shortName": "P. Gasol",
"links": [
{
"rel": [
"playercard",
"desktop",
"athlete"
],
"href": "https://www.espn.com/nba/player/_/id/996/pau-gasol",
"text": "Player Card"
}
],
"headshot": {
"href": "https://a.espncdn.com/i/headshots/nba/players/full/996.png",
"alt": "Pau Gasol"
},
"jersey": "16",
"position": {
"abbreviation": "PF"
},
"team": {
"$ref": "http://sports.core.api.espn.pvt/v2/sports/basketball/leagues/nba/seasons/2002/teams/29?lang=en&region=us"
}
},
"statistics": [
{
"name": "points",
"displayName": "Points",
"shortDisplayName": "PTS",
"description": "The number of points scored.",
"abbreviation": "PTS",
"value": 22.0,
"displayValue": "22"
},
{
"name": "fieldGoals",
"displayName": "Field Goals",
"shortDisplayName": "FG",
"description": "Field Goal makes and attempts.",
"abbreviation": "FG",
"value": 0.444444,
"displayValue": "8/18"
},
{
"name": "freeThrows",
"displayName": "Free Throws",
"shortDisplayName": "FT",
"description": "Free Throw makes and attempts.",
"abbreviation": "FT",
"value": 0.666667,
"displayValue": "6/9"
}
]
}
]
},
{
"name": "assists",
"displayName": "Assists",
"leaders": [
{
"displayValue": "8",
"athlete": {
"id": "933",
"uid": "s:40~l:46~a:933",
"guid": "e3057b2e0a35460a97c5083006fa038b",
"lastName": "Williams",
"fullName": "Jason Williams",
"displayName": "Jason Williams",
"shortName": "J. Williams",
"links": [
{
"rel": [
"playercard",
"desktop",
"athlete"
],
"href": "https://www.espn.com/nba/player/_/id/933/jason-williams",
"text": "Player Card"
}
],
"headshot": {
"href": "https://a.espncdn.com/i/headshots/nba/players/full/933.png",
"alt": "Jason Williams"
},
"jersey": "3",
"position": {
"abbreviation": "PG"
},
"team": {
"$ref": "http://sports.core.api.espn.pvt/v2/sports/basketball/leagues/nba/seasons/2002/teams/29?lang=en&region=us"
}
},
"statistics": [
{
"name": "assists",
"displayName": "Assists",
"shortDisplayName": "AST",
"description": "The number of times a player who passes the ball to a teammate in a way that leads to a score by field goal, meaning that he or she was \"assisting\" in the basket. There is some judgment involved in deciding whether a passer should be credited with an assist.",
"abbreviation": "AST",
"value": 8.0,
"displayValue": "8"
},
{
"name": "turnovers",
"displayName": "Turnovers",
"shortDisplayName": "TO",
"description": "The number of times a player loses possession to the other team.",
"abbreviation": "TO",
"value": 2.0,
"displayValue": "2"
},
{
"name": "minutes",
"displayName": "Minutes",
"shortDisplayName": "MIN",
"description": "The total number of minutes played.",
"abbreviation": "MIN",
"value": 38.0,
"displayValue": "38"
},
{
"name": "assistTurnoverRatio",
"displayName": "Assist To Turnover Ratio",
"shortDisplayName": "AST/TO",
"description": "The average number of assists a player or team records per turnover",
"abbreviation": "AST/TO",
"value": 4.0,
"displayValue": "4.0"
}
]
}
]
},
{
"name": "rebounds",
"displayName": "Rebounds",
"leaders": [
{
"displayValue": "11",
"athlete": {
"id": "959",
"uid": "s:40~l:46~a:959",
"guid": "1a4c0232b2ffcfc2e83662782a555868",
"lastName": "Wright",
"fullName": "Lorenzen Wright",
"displayName": "Lorenzen Wright",
"shortName": "L. Wright",
"links": [
{
"rel": [
"playercard",
"desktop",
"athlete"
],
"href": "https://www.espn.com/nba/player/_/id/959/lorenzen-wright",
"text": "Player Card"
}
],
"jersey": "55",
"position": {
"abbreviation": "PF"
},
"team": {
"$ref": "http://sports.core.api.espn.pvt/v2/sports/basketball/leagues/nba/seasons/2002/teams/29?lang=en&region=us"
}
},
"statistics": [
{
"name": "rebounds",
"displayName": "Rebounds",
"shortDisplayName": "REB",
"description": "The total number of rebounds (offensive and defensive).",
"abbreviation": "REB",
"value": 11.0,
"displayValue": "11"
},
{
"name": "defensiveRebounds",
"displayName": "Defensive Rebounds",
"shortDisplayName": "DREB",
"description": "The number of times when the defense obtains the possession of the ball after a missed shot by the offense.",
"abbreviation": "DR",
"value": 9.0,
"displayValue": "9"
},
{
"name": "offensiveRebounds",
"displayName": "Offensive Rebounds",
"shortDisplayName": "OREB",
"description": "The number of times when the offense obtains the possession of the ball after a missed shot.",
"abbreviation": "OR",
"value": 2.0,
"displayValue": "2"
}
]
}
]
}
]
}
],
"seasonseries": [
{
"type": "season",
"title": "Regular Season Series",
"description": "Regular Season Series",
"summary": "TOR leads series 1-0",
"completed": false,
"totalCompetitions": 2,
"events": [
{
"id": "211129028",
"uid": "s:40~l:46~e:211129028~c:211129028",
"date": "2001-11-29T23:30:00Z",
"timeValid": true,
"status": "post",
"statusType": {
"id": "3",
"name": "STATUS_FINAL",
"state": "post",
"completed": true,
"description": "Final",
"detail": "Final",
"shortDetail": "Final"
},
"competitors": [
{
"homeAway": "home",
"winner": true,
"team": {
"id": "28",
"uid": "s:40~l:46~t:28",
"displayName": "Toronto Raptors",
"abbreviation": "TOR",
"links": [
{
"href": "https://www.espn.com/nba/team/_/name/tor/toronto-raptors",
"text": "Clubhouse"
},
{
"href": "https://www.espn.com/nba/team/schedule/_/name/tor",
"text": "Schedule"
}
],
"logo": "https://a.espncdn.com/i/teamlogos/nba/500/tor.png",
"logos": [
{
"href": "https://a.espncdn.com/i/teamlogos/nba/500/tor.png",
"width": 500,
"height": 500,
"alt": "",
"rel": [
"full",
"default"
],
"lastUpdated": "2019-04-09T18:15Z"
},
{
"href": "https://a.espncdn.com/i/teamlogos/nba/500-dark/tor.png",
"width": 500,
"height": 500,
"alt": "",
"rel": [
"full",
"dark"
],
"lastUpdated": "2019-05-31T20:44Z"
}
]
},
"score": "91"
},
{
"homeAway": "away",
"winner": false,
"team": {
"id": "29",
"uid": "s:40~l:46~t:29",
"displayName": "Memphis Grizzlies",
"abbreviation": "MEM",
"links": [
{
"href": "https://www.espn.com/nba/team/_/name/mem/memphis-grizzlies",
"text": "Clubhouse"
},
{
"href": "https://www.espn.com/nba/team/schedule/_/name/mem",
"text": "Schedule"
}
],
"logo": "https://a.espncdn.com/i/teamlogos/nba/500/mem.png",
"logos": [
{
"href": "https://a.espncdn.com/i/teamlogos/nba/500/mem.png",
"width": 500,
"height": 500,
"alt": "",
"rel": [
"full",
"default"
],
"lastUpdated": "2018-10-12T14:51Z"
},
{
"href": "https://a.espncdn.com/i/teamlogos/nba/500-dark/mem.png",
"width": 500,
"height": 500,
"alt": "",
"rel": [
"full",
"dark"
],
"lastUpdated": "2018-10-12T14:51Z"
}
]
},
"score": "88"
}
],
"links": [
{
"language": "en-US",
"rel": [
"summary",
"desktop",
"event"
],
"href": "https://www.espn.com/nba/game/_/gameId/211129028",
"text": "Gamecast",
"shortText": "Summary",
"isExternal": false,
"isPremium": false
},
{
"language": "en-US",
"rel": [
"summary",
"sportscenter",
"app",
"event"
],
"href": "sportscenter://x-callback-url/showGame?sportName=basketball&leagueAbbrev=nba&gameId=211129028",
"text": "Gamecast",
"shortText": "Summary",
"isExternal": false,
"isPremium": false
}
]
},
{
"id": "220108029",
"uid": "s:40~l:46~e:220108029~c:220108029",
"date": "2002-01-09T00:00:00Z",
"timeValid": true,
"status": "post",
"statusType": {
"id": "3",
"name": "STATUS_FINAL",
"state": "post",
"completed": true,
"description": "Final",
"detail": "Final",
"shortDetail": "Final"
},
"competitors": [
{
"homeAway": "home",
"winner": true,
"team": {
"id": "29",
"uid": "s:40~l:46~t:29",
"displayName": "Memphis Grizzlies",
"abbreviation": "MEM",
"links": [
{
"href": "https://www.espn.com/nba/team/_/name/mem/memphis-grizzlies",
"text": "Clubhouse"
},
{
"href": "https://www.espn.com/nba/team/schedule/_/name/mem",
"text": "Schedule"
}
],
"logo": "https://a.espncdn.com/i/teamlogos/nba/500/mem.png",
"logos": [
{
"href": "https://a.espncdn.com/i/teamlogos/nba/500/mem.png",
"width": 500,
"height": 500,
"alt": "",
"rel": [
"full",
"default"
],
"lastUpdated": "2018-10-12T14:51Z"
},
{
"href": "https://a.espncdn.com/i/teamlogos/nba/500-dark/mem.png",
"width": 500,
"height": 500,
"alt": "",
"rel": [
"full",
"dark"
],
"lastUpdated": "2018-10-12T14:51Z"
}
]
},
"score": "84"
},
{
"homeAway": "away",
"winner": false,
"team": {
"id": "28",
"uid": "s:40~l:46~t:28",
"displayName": "Toronto Raptors",
"abbreviation": "TOR",
"links": [
{
"href": "https://www.espn.com/nba/team/_/name/tor/toronto-raptors",
"text": "Clubhouse"
},
{
"href": "https://www.espn.com/nba/team/schedule/_/name/tor",
"text": "Schedule"
}
],
"logo": "https://a.espncdn.com/i/teamlogos/nba/500/tor.png",
"logos": [
{
"href": "https://a.espncdn.com/i/teamlogos/nba/500/tor.png",
"width": 500,
"height": 500,
"alt": "",
"rel": [
"full",
"default"
],
"lastUpdated": "2019-04-09T18:15Z"
},
{
"href": "https://a.espncdn.com/i/teamlogos/nba/500-dark/tor.png",
"width": 500,
"height": 500,
"alt": "",
"rel": [
"full",
"dark"
],
"lastUpdated": "2019-05-31T20:44Z"
}
]
},
"score": "81"
}
],
"links": [
{
"language": "en-US",
"rel": [
"summary",
"desktop",
"event"
],
"href": "https://www.espn.com/nba/game/_/gameId/220108029",
"text": "Gamecast",
"shortText": "Summary",
"isExternal": false,
"isPremium": false
},
{
"language": "en-US",
"rel": [
"summary",
"sportscenter",
"app",
"event"
],
"href": "sportscenter://x-callback-url/showGame?sportName=basketball&leagueAbbrev=nba&gameId=220108029",
"text": "Gamecast",
"shortText": "Summary",
"isExternal": false,
"isPremium": false
}
]
}
]
}
],
"broadcasts": [],
"predictor": {},
"pickcenter": [],
"againstTheSpread": [
{
"team": {
"id": "29",
"uid": "s:40~l:46~t:29",
"displayName": "Memphis Grizzlies",
"abbreviation": "MEM",
"links": [
{
"href": "https://www.espn.com/nba/team/_/name/mem/memphis-grizzlies",
"text": "Clubhouse"
},
{
"href": "https://www.espn.com/nba/team/schedule/_/name/mem",
"text": "Schedule"
}
],
"logo": "https://a.espncdn.com/i/teamlogos/nba/500/mem.png",
"logos": [
{
"href": "https://a.espncdn.com/i/teamlogos/nba/500/mem.png",
"width": 500,
"height": 500,
"alt": "",
"rel": [
"full",
"default"
],
"lastUpdated": "2018-10-12T14:51Z"
},
{
"href": "https://a.espncdn.com/i/teamlogos/nba/500-dark/mem.png",
"width": 500,
"height": 500,
"alt": "",
"rel": [
"full",
"dark"
],
"lastUpdated": "2018-10-12T14:51Z"
}
]
},
"records": []
},
{
"team": {
"id": "28",
"uid": "s:40~l:46~t:28",
"displayName": "Toronto Raptors",
"abbreviation": "TOR",
"links": [
{
"href": "https://www.espn.com/nba/team/_/name/tor/toronto-raptors",
"text": "Clubhouse"
},
{
"href": "https://www.espn.com/nba/team/schedule/_/name/tor",
"text": "Schedule"
}
],
"logo": "https://a.espncdn.com/i/teamlogos/nba/500/tor.png",
"logos": [
{
"href": "https://a.espncdn.com/i/teamlogos/nba/500/tor.png",
"width": 500,
"height": 500,
"alt": "",
"rel": [
"full",
"default"
],
"lastUpdated": "2019-04-09T18:15Z"
},
{
"href": "https://a.espncdn.com/i/teamlogos/nba/500-dark/tor.png",
"width": 500,
"height": 500,
"alt": "",
"rel": [
"full",
"dark"
],
"lastUpdated": "2019-05-31T20:44Z"
}
]
},
"records": []
}
],
"odds": [],
"winprobability": [],
"header": {
"id": "211129028",
"uid": "s:40~l:46~e:211129028",
"season": {
"year": 2002,
"type": 2
},
"timeValid": true,
"competitions": [
{
"id": "211129028",
"uid": "s:40~l:46~e:211129028~c:211129028",
"date": "2001-11-29T23:30Z",
"neutralSite": false,
"conferenceCompetition": false,
"boxscoreAvailable": true,
"commentaryAvailable": false,
"liveAvailable": false,
"shotChartAvailable": false,
"timeoutsAvailable": true,
"possessionArrowAvailable": false,
"onWatchESPN": false,
"recent": false,
"boxscoreSource": "full",
"playByPlaySource": "none",
"competitors": [
{
"id": "28",
"uid": "s:40~l:46~t:28",
"order": 0,
"homeAway": "home",
"winner": true,
"team": {
"id": "28",
"uid": "s:40~l:46~t:28",
"location": "Toronto",
"name": "Raptors",
"abbreviation": "TOR",
"displayName": "Toronto Raptors",
"color": "CE0F41",
"alternateColor": "061922",
"logos": [
{
"href": "https://a.espncdn.com/i/teamlogos/nba/500/tor.png",
"width": 500,
"height": 500,
"alt": "",
"rel": [
"full",
"default"
],
"lastUpdated": "2019-04-09T18:15Z"
},
{
"href": "https://a.espncdn.com/i/teamlogos/nba/500-dark/tor.png",
"width": 500,
"height": 500,
"alt": "",
"rel": [
"full",
"dark"
],
"lastUpdated": "2019-05-31T20:44Z"
},
{
"href": "https://a.espncdn.com/i/teamlogos/nba/500/scoreboard/tor.png",
"width": 500,
"height": 500,
"alt": "",
"rel": [
"full",
"scoreboard"
],
"lastUpdated": "2018-10-11T13:47Z"
},
{
"href": "https://a.espncdn.com/i/teamlogos/nba/500-dark/scoreboard/tor.png",
"width": 500,
"height": 500,
"alt": "",
"rel": [
"full",
"scoreboard",
"dark"
],
"lastUpdated": "2020-10-08T19:46Z"
}
],
"links": [
{
"rel": [
"clubhouse",
"desktop",
"team"
],
"href": "https://www.espn.com/nba/team/_/name/tor/toronto-raptors",
"text": "Clubhouse"
}
]
},
"score": "91",
"linescores": [
{
"displayValue": "25"
},
{
"displayValue": "15"
},
{
"displayValue": "38"
},
{
"displayValue": "13"
}
],
"record": [
{
"type": "total",
"summary": "10-6",
"displayValue": "10-6"
},
{
"type": "home",
"summary": "5-2",
"displayValue": "5-2"
},
{
"type": "vsconf",
"summary": "0-0",
"displayValue": "0-0"
}
],
"possession": false
},
{
"id": "29",
"uid": "s:40~l:46~t:29",
"order": 1,
"homeAway": "away",
"winner": false,
"team": {
"id": "29",
"uid": "s:40~l:46~t:29",
"location": "Memphis",
"name": "Grizzlies",
"abbreviation": "MEM",
"displayName": "Memphis Grizzlies",
"color": "5D76A8",
"alternateColor": "7399c6",
"logos": [
{
"href": "https://a.espncdn.com/i/teamlogos/nba/500/mem.png",
"width": 500,
"height": 500,
"alt": "",
"rel": [
"full",
"default"
],
"lastUpdated": "2018-10-12T14:51Z"
},
{
"href": "https://a.espncdn.com/i/teamlogos/nba/500-dark/mem.png",
"width": 500,
"height": 500,
"alt": "",
"rel": [
"full",
"dark"
],
"lastUpdated": "2018-10-12T14:51Z"
},
{
"href": "https://a.espncdn.com/i/teamlogos/nba/500/scoreboard/mem.png",
"width": 500,
"height": 500,
"alt": "",
"rel": [
"full",
"scoreboard"
],
"lastUpdated": "2018-10-12T14:52Z"
},
{
"href": "https://a.espncdn.com/i/teamlogos/nba/500-dark/scoreboard/mem.png",
"width": 500,
"height": 500,
"alt": "",
"rel": [
"full",
"scoreboard",
"dark"
],
"lastUpdated": "2018-10-12T14:50Z"
}
],
"links": [
{
"rel": [
"clubhouse",
"desktop",
"team"
],
"href": "https://www.espn.com/nba/team/_/name/mem/memphis-grizzlies",
"text": "Clubhouse"
}
]
},
"score": "88",
"linescores": [
{
"displayValue": "18"
},
{
"displayValue": "19"
},
{
"displayValue": "28"
},
{
"displayValue": "23"
}
],
"record": [
{
"type": "total",
"summary": "2-12",
"displayValue": "2-12"
},
{
"type": "road",
"summary": "0-7",
"displayValue": "0-7"
},
{
"type": "vsconf",
"summary": "0-0",
"displayValue": "0-0"
}
],
"possession": false
}
],
"status": {
"type": {
"id": "3",
"name": "STATUS_FINAL",
"state": "post",
"completed": true,
"description": "Final",
"detail": "Final",
"shortDetail": "Final"
}
},
"broadcasts": [],
"series": [
{
"type": "season",
"title": "Regular Season Series",
"description": "Regular Season Series",
"summary": "TOR leads series 1-0",
"completed": false,
"totalCompetitions": 2,
"competitors": [
{
"id": "28",
"uid": "s:40~l:46~t:28",
"wins": 1,
"ties": 0,
"team": {
"$ref": "http://sports.core.api.espn.pvt/v2/sports/basketball/leagues/nba/seasons/2002/teams/28?lang=en&region=us"
}
},
{
"id": "29",
"uid": "s:40~l:46~t:29",
"wins": 0,
"ties": 0,
"team": {
"$ref": "http://sports.core.api.espn.pvt/v2/sports/basketball/leagues/nba/seasons/2002/teams/29?lang=en&region=us"
}
}
],
"events": [
{
"$ref": "http://sports.core.api.espn.pvt/v2/sports/basketball/leagues/nba/events/211129028?lang=en&region=us",
"id": "211129028"
},
{
"$ref": "http://sports.core.api.espn.pvt/v2/sports/basketball/leagues/nba/events/220108029?lang=en&region=us",
"id": "220108029"
}
]
}
]
}
],
"links": [
{
"rel": [
"summary",
"desktop",
"event"
],
"href": "https://www.espn.com/nba/game/_/gameId/211129028",
"text": "Gamecast",
"shortText": "Summary",
"isExternal": false,
"isPremium": false
},
{
"rel": [
"recap",
"desktop",
"event"
],
"href": "https://www.espn.com/nba/recap?gameId=211129028",
"text": "Recap",
"shortText": "Recap",
"isExternal": false,
"isPremium": false
},
{
"rel": [
"boxscore",
"desktop",
"event"
],
"href": "https://www.espn.com/nba/boxscore/_/gameId/211129028",
"text": "Box Score",
"shortText": "Box Score",
"isExternal": false,
"isPremium": false
},
{
"rel": [
"teamstats",
"desktop",
"event"
],
"href": "https://www.espn.com/nba/matchup?gameId=211129028",
"text": "Team Stats",
"shortText": "Team Stats",
"isExternal": false,
"isPremium": false
}
],
"week": 5,
"league": {
"id": "46",
"uid": "s:40~l:46",
"name": "National Basketball Association",
"abbreviation": "NBA",
"slug": "nba",
"isTournament": false,
"links": [
{
"rel": [
"index",
"desktop",
"league"
],
"href": "https://www.espn.com/nba/",
"text": "Index"
},
{
"rel": [
"index",
"sportscenter",
"app",
"league"
],
"href": "sportscenter://x-callback-url/showClubhouse?uid=s:40~l:46",
"text": "Index"
},
{
"rel": [
"schedule",
"desktop",
"league"
],
"href": "https://www.espn.com/nba/schedule",
"text": "Schedule"
},
{
"rel": [
"schedule",
"sportscenter",
"app",
"league"
],
"href": "sportscenter://x-callback-url/showClubhouse?uid=s:40~l:46&section=scores",
"text": "Schedule"
},
{
"rel": [
"standings",
"desktop",
"league"
],
"href": "http://www.espn.com/nba/standings",
"text": "Standings"
},
{
"rel": [
"standings",
"sportscenter",
"app",
"league"
],
"href": "sportscenter://x-callback-url/showClubhouse?uid=s:40~l:46&section=standings",
"text": "Standings"
},
{
"rel": [
"rankings",
"desktop",
"league"
],
"href": "https://www.espn.com/nba/rankings",
"text": "Rankings"
},
{
"rel": [
"scores",
"desktop",
"league"
],
"href": "https://www.espn.com/nba/scoreboard",
"text": "Scores"
},
{
"rel": [
"scores",
"sportscenter",
"app",
"league"
],
"href": "sportscenter://x-callback-url/showClubhouse?uid=s:40~l:46&section=scores",
"text": "Scores"
},
{
"rel": [
"stats",
"desktop",
"league"
],
"href": "http://www.espn.com/nba/stats",
"text": "Stats"
},
{
"rel": [
"teams",
"desktop",
"league"
],
"href": "http://www.espn.com/nba/teams",
"text": "Teams"
},
{
"rel": [
"athletes",
"desktop",
"league"
],
"href": "http://www.espn.com/nba/players",
"text": "Players"
},
{
"rel": [
"injuries",
"desktop",
"league"
],
"href": "https://www.espn.com/nba/injuries",
"text": "Injuries"
}
]
}
},
"plays": [],
"article": {
"keywords": [],
"description": "Vince Carter scored 23 points and Antonio Davis collected 20 and 11 rebounds as the Raptors recorded their third three-game winning streak of the season with a 91-88 triumph over the Grizzlies. \r\n",
"video": [],
"type": "Recap",
"nowId": "1-1287283",
"premium": false,
"related": [],
"links": {
"api": {
"news": {
"href": "http://now.core.api.espn.com/v1/sports/news/1287283"
},
"events": {
"href": "http://now.core.api.espn.com/v1/sports/basketball/nba/events/211129028"
}
},
"web": {
"href": "http://espn.go.com/nba/2002/20011129/recap/memtor.html",
"short": {}
},
"app": {
"sportscenter": {
"href": "sportscenter://x-callback-url/showStory?uid=1287283"
}
},
"mobile": {
"href": "http://scores.espn.com/nba/gamecast?gameId=211129028&version=mobile"
}
},
"id": 1287283,
"categories": [],
"headline": "Raptors need all of Carter's 23 points",
"gameId": "211129028",
"images": [],
"linkText": "Grizzlies return to Canada, only to lose close game to Raptors",
"published": "2001-11-30T02:19:01Z",
"lastModified": "2001-11-30T04:47:25Z",
"story": "TORONTO (AP) -- Rookies <a href=\"http://sports.espn.go.com/nba/players/profile?statsId=3513\">Pau Gasol</a> and <a href=\"http://sports.espn.go.com/nba/players/profile?statsId=3516\">Shane Battier</a> are giving the <a href=\"http://sports.espn.go.com/nba/clubhouse?team=mem\">Memphis Grizzlies</a> with hope for the future. <a href=\"http://sports.espn.go.com/nba/players/profile?statsId=3248\">Vince Carter</a> is delivering victories for the <a href=\"http://sports.espn.go.com/nba/clubhouse?team=tor\">Toronto Raptors</a>.\n\n<table align=right border=0 cellspacing=0><tr><td width=2> </td><td\nwidth=65><img src=\"/i/nba/profiles/players/3248.jpg\" width=65\nheight=90 align=right alt=\"Carter\"></td></tr><tr><td width=2>\n</td><td width=65><font face=\"arial\" size=\"-2\"\ncolor=\"#666666\"><b>Carter</b></font></td></tr></table><p>\n\nCarter had 23 points, added eight rebounds and seven assists to lead the Raptors to a 91-88 victory over Memphis on Thursday night, the Grizzlies' first game in Canada since leaving Vancouver.\n\nGasol scored 22 points and Battier added 20 for Memphis, which has won just two of its first 14 games.\n\n\"We're going to take some lumps now, but I think in the future we'll be dishing them out,\" Battier said.\n\n<a href=\"http://sports.espn.go.com/nba/players/profile?statsId=2143\">Antonio Davis</a> finished with 20 points and 11 rebounds for Toronto. He believes the Memphis Grizzlies will be better than the Vancouver version.\n\n\"Gasol has a lot of talent. It's raw, but I think he's going to develop more size and confidence,\" Davis said. \"If the veterans don't give up on the philosophy of team, I think that is going to be a better team than it was in Vancouver.\"\n\nMemphis, which trailed by 15 points late in the third quarter, used an 18-4 run early in the fourth to climb back into contention. Battier scored 10 points in the outburst.\n\n\"They have a lot of fight in them,\" Carter said. \"I'm sure their not happy about their record, but they do whatever it takes for a win.\"\n\nA 3-pointer by Battier helped Memphis close within a point with\n5:55 remaining, and <a href=\"http://sports.espn.go.com/nba/players/profile?statsId=3186\">Brevin Knight</a>'s jumper gave the Grizzlies a\none-point lead.\n\n<a href=\"http://sports.espn.go.com/nba/players/profile?statsId=250\">Hakeem Olajuwon</a> countered with a jumper, giving Toronto a lead it never relinquished.\n\nA tip-in by Davis and a free throw by Olajuwon gave Toronto a\n87-83 with two minutes left.\n\n\"We hung in there and found a way to execute,\" Davis said.\n\n<a href=\"http://sports.espn.go.com/nba/players/profile?statsId=3250\">Jason Williams</a>, who shot 3-for-15, hit a jumper that cut the\nRaptors' lead to two points with 1:34 remaining, but Morris\nPeterson countered with a layup.\n\nJason Williams converted one of two free throws, cutting the lead to three points with 34 seconds left, but Toronto's Alvin Williams made two free throws with 8.5 seconds, giving Toronto a 91-86 lead.\n\nRodney Budford, who had 18 points, then missed a 3-pointer.\n\nBased on the Grizzlies victory over Sacramento on Monday and\ntheir play against the Raptors, Battier believes the team is\nimproving.\n\n\"The last two games we've played were against teams that could play for the NBA finals,\" Battier said. \"There is no substitute for learning. Playing against Vince Carter, I learned a ton about myself tonight.\"\n\nThe Raptors have won six of eight.\n\nThe Raptors, who entered the game with the fifth worst free throw shooting percentage in the NBA, shot 22-for-24 from the line and made all 16 of their attempts in the third quarter.\n\nMemphis trailed by 11 in the second quarter, but Gasol helped\nnarrow it to three at halftime by scoring eight points in the\nperiod.<p>\n\n<font face=\"Arial,Helvetica,sans-serif\" size=3 color=#A50400><b>Game notes</b></font><br>Memphis forward <a href=\"http://sports.espn.go.com/nba/players/profile?statsId=219\">Tony Massenburg</a>, who has played for both Vancouver and Toronto, said he didn't mind playing in Vancouver, but that everyone else did. \"Everybody else looked at Vancouver as\nthe last city to join the NBA, that it was farthest team from the east coast, that we didn't win, and that it rained a lot.\" ... Toronto leads the series 8-4. ... The Raptors had a mock Grizzlies mascot on the court before the game. The skinny grizzly looked more like a weasel than a bear. The word Vancouver was taped over, and Memphis was written over top. ... Memphis center <a href=\"http://sports.espn.go.com/nba/players/profile?statsId=3116\">Lorenzen Wright</a> had 11 points and 11 rebounds for his eighth double-double this season."
},
"videos": [],
"standings": {
"fullViewLink": {
"text": "Full Standings",
"href": "http://www.espn.com/nba/standings"
},
"groups": [
{
"standings": {
"entries": []
},
"header": "2022-23 Midwest Standings",
"href": "https://www.espn.com/nba/standings/_/group/3"
},
{
"standings": {
"entries": [
{
"team": "Milwaukee",
"link": "https://www.espn.com/nba/team/_/name/mil/milwaukee-bucks",
"id": "15",
"uid": "s:40~l:46~t:15",
"stats": [
{
"name": "gamesBehind",
"displayName": "Games Back",
"shortDisplayName": "GB",
"description": "Games Back",
"abbreviation": "GB",
"type": "gamesbehind",
"value": 0.0,
"displayValue": "-"
},
{
"name": "losses",
"displayName": "Losses",
"shortDisplayName": "L",
"description": "Losses",
"abbreviation": "L",
"type": "losses",
"value": 22.0,
"displayValue": "22"
},
{
"name": "streak",
"displayName": "Streak",
"shortDisplayName": "STRK",
"description": "Current Streak",
"abbreviation": "STRK",
"type": "streak",
"value": 3.0,
"displayValue": "W3"
},
{
"name": "winPercent",
"displayName": "Win Percentage",
"shortDisplayName": "PCT",
"description": "Winning Percentage",
"abbreviation": "PCT",
"type": "winpercent",
"value": 0.725,
"displayValue": ".725"
},
{
"name": "wins",
"displayName": "Wins",
"shortDisplayName": "W",
"description": "Wins",
"abbreviation": "W",
"type": "wins",
"value": 58.0,
"displayValue": "58"
}
],
"logo": [
{
"href": "https://a.espncdn.com/i/teamlogos/nba/500/scoreboard/mil.png",
"width": 500,
"height": 500,
"alt": "",
"rel": [
"full",
"scoreboard"
],
"lastUpdated": "2018-06-05T12:08Z"
},
{
"href": "https://a.espncdn.com/i/teamlogos/nba/500-dark/scoreboard/mil.png",
"width": 500,
"height": 500,
"alt": "",
"rel": [
"full",
"scoreboard",
"dark"
],
"lastUpdated": "2018-06-05T12:08Z"
}
]
},
{
"team": "Cleveland",
"link": "https://www.espn.com/nba/team/_/name/cle/cleveland-cavaliers",
"id": "5",
"uid": "s:40~l:46~t:5",
"stats": [
{
"name": "gamesBehind",
"displayName": "Games Back",
"shortDisplayName": "GB",
"description": "Games Back",
"abbreviation": "GB",
"type": "gamesbehind",
"value": 7.5,
"displayValue": "7.5"
},
{
"name": "losses",
"displayName": "Losses",
"shortDisplayName": "L",
"description": "Losses",
"abbreviation": "L",
"type": "losses",
"value": 30.0,
"displayValue": "30"
},
{
"name": "streak",
"displayName": "Streak",
"shortDisplayName": "STRK",
"description": "Current Streak",
"abbreviation": "STRK",
"type": "streak",
"value": 3.0,
"displayValue": "W3"
},
{
"name": "winPercent",
"displayName": "Win Percentage",
"shortDisplayName": "PCT",
"description": "Winning Percentage",
"abbreviation": "PCT",
"type": "winpercent",
"value": 0.6296296,
"displayValue": ".630"
},
{
"name": "wins",
"displayName": "Wins",
"shortDisplayName": "W",
"description": "Wins",
"abbreviation": "W",
"type": "wins",
"value": 51.0,
"displayValue": "51"
}
],
"logo": [
{
"href": "https://a.espncdn.com/i/teamlogos/nba/500/scoreboard/cle.png",
"width": 500,
"height": 500,
"alt": "",
"rel": [
"full",
"scoreboard"
],
"lastUpdated": "2022-06-23T14:03Z"
},
{
"href": "https://a.espncdn.com/i/teamlogos/nba/500-dark/scoreboard/cle.png",
"width": 500,
"height": 500,
"alt": "",
"rel": [
"full",
"scoreboard",
"dark"
],
"lastUpdated": "2018-06-05T12:08Z"
}
]
},
{
"team": "Chicago",
"link": "https://www.espn.com/nba/team/_/name/chi/chicago-bulls",
"id": "4",
"uid": "s:40~l:46~t:4",
"stats": [
{
"name": "gamesBehind",
"displayName": "Games Back",
"shortDisplayName": "GB",
"description": "Games Back",
"abbreviation": "GB",
"type": "gamesbehind",
"value": 20.0,
"displayValue": "20"
},
{
"name": "losses",
"displayName": "Losses",
"shortDisplayName": "L",
"description": "Losses",
"abbreviation": "L",
"type": "losses",
"value": 42.0,
"displayValue": "42"
},
{
"name": "streak",
"displayName": "Streak",
"shortDisplayName": "STRK",
"description": "Current Streak",
"abbreviation": "STRK",
"type": "streak",
"value": -2.0,
"displayValue": "L2"
},
{
"name": "winPercent",
"displayName": "Win Percentage",
"shortDisplayName": "PCT",
"description": "Winning Percentage",
"abbreviation": "PCT",
"type": "winpercent",
"value": 0.475,
"displayValue": ".475"
},
{
"name": "wins",
"displayName": "Wins",
"shortDisplayName": "W",
"description": "Wins",
"abbreviation": "W",
"type": "wins",
"value": 38.0,
"displayValue": "38"
}
],
"logo": [
{
"href": "https://a.espncdn.com/i/teamlogos/nba/500/scoreboard/chi.png",
"width": 500,
"height": 500,
"alt": "",
"rel": [
"full",
"scoreboard"
],
"lastUpdated": "2018-06-05T12:08Z"
},
{
"href": "https://a.espncdn.com/i/teamlogos/nba/500-dark/scoreboard/chi.png",
"width": 500,
"height": 500,
"alt": "",
"rel": [
"full",
"scoreboard",
"dark"
],
"lastUpdated": "2018-06-05T12:08Z"
}
]
},
{
"team": "Indiana",
"link": "https://www.espn.com/nba/team/_/name/ind/indiana-pacers",
"id": "11",
"uid": "s:40~l:46~t:11",
"stats": [
{
"name": "gamesBehind",
"displayName": "Games Back",
"shortDisplayName": "GB",
"description": "Games Back",
"abbreviation": "GB",
"type": "gamesbehind",
"value": 24.0,
"displayValue": "24"
},
{
"name": "losses",
"displayName": "Losses",
"shortDisplayName": "L",
"description": "Losses",
"abbreviation": "L",
"type": "losses",
"value": 46.0,
"displayValue": "46"
},
{
"name": "streak",
"displayName": "Streak",
"shortDisplayName": "STRK",
"description": "Current Streak",
"abbreviation": "STRK",
"type": "streak",
"value": -2.0,
"displayValue": "L2"
},
{
"name": "winPercent",
"displayName": "Win Percentage",
"shortDisplayName": "PCT",
"description": "Winning Percentage",
"abbreviation": "PCT",
"type": "winpercent",
"value": 0.425,
"displayValue": ".425"
},
{
"name": "wins",
"displayName": "Wins",
"shortDisplayName": "W",
"description": "Wins",
"abbreviation": "W",
"type": "wins",
"value": 34.0,
"displayValue": "34"
}
],
"logo": [
{
"href": "https://a.espncdn.com/i/teamlogos/nba/500/scoreboard/ind.png",
"width": 500,
"height": 500,
"alt": "",
"rel": [
"full",
"scoreboard"
],
"lastUpdated": "2018-06-05T12:08Z"
},
{
"href": "https://a.espncdn.com/i/teamlogos/nba/500-dark/scoreboard/ind.png",
"width": 500,
"height": 500,
"alt": "",
"rel": [
"full",
"scoreboard",
"dark"
],
"lastUpdated": "2018-06-05T12:08Z"
}
]
},
{
"team": "Detroit",
"link": "https://www.espn.com/nba/team/_/name/det/detroit-pistons",
"id": "8",
"uid": "s:40~l:46~t:8",
"stats": [
{
"name": "gamesBehind",
"displayName": "Games Back",
"shortDisplayName": "GB",
"description": "Games Back",
"abbreviation": "GB",
"type": "gamesbehind",
"value": 42.0,
"displayValue": "42"
},
{
"name": "losses",
"displayName": "Losses",
"shortDisplayName": "L",
"description": "Losses",
"abbreviation": "L",
"type": "losses",
"value": 64.0,
"displayValue": "64"
},
{
"name": "streak",
"displayName": "Streak",
"shortDisplayName": "STRK",
"description": "Current Streak",
"abbreviation": "STRK",
"type": "streak",
"value": -11.0,
"displayValue": "L11"
},
{
"name": "winPercent",
"displayName": "Win Percentage",
"shortDisplayName": "PCT",
"description": "Winning Percentage",
"abbreviation": "PCT",
"type": "winpercent",
"value": 0.2,
"displayValue": ".200"
},
{
"name": "wins",
"displayName": "Wins",
"shortDisplayName": "W",
"description": "Wins",
"abbreviation": "W",
"type": "wins",
"value": 16.0,
"displayValue": "16"
}
],
"logo": [
{
"href": "https://a.espncdn.com/i/teamlogos/nba/500/scoreboard/det.png",
"width": 500,
"height": 500,
"alt": "",
"rel": [
"full",
"scoreboard"
],
"lastUpdated": "2018-06-05T12:08Z"
},
{
"href": "https://a.espncdn.com/i/teamlogos/nba/500-dark/scoreboard/det.png",
"width": 500,
"height": 500,
"alt": "",
"rel": [
"full",
"scoreboard",
"dark"
],
"lastUpdated": "2018-06-05T12:08Z"
}
]
}
]
},
"header": "2022-23 Central Standings",
"href": "https://www.espn.com/nba/standings/_/group/2"
}
]
},
"teamInfo": [],
"espnWP": [],
"season": {},
"timeouts": []
}