{
"boxscore": {
"teams": [
{
"team": {
"id": "15",
"uid": "s:40~l:46~t:15",
"slug": "milwaukee-bucks",
"location": "Milwaukee",
"name": "Bucks",
"abbreviation": "MIL",
"displayName": "Milwaukee Bucks",
"shortDisplayName": "Bucks",
"color": "003813",
"alternateColor": "f0ebd2",
"logo": "https://a.espncdn.com/i/teamlogos/nba/500/mil.png"
},
"statistics": [
{
"name": "fieldGoalsMade-fieldGoalsAttempted",
"displayValue": "32-75",
"label": "FG"
},
{
"name": "fieldGoalPct",
"displayValue": "42.7",
"abbreviation": "FG%",
"label": "Field Goal %"
},
{
"name": "threePointFieldGoalsMade-threePointFieldGoalsAttempted",
"displayValue": "10-28",
"label": "3PT"
},
{
"name": "threePointFieldGoalPct",
"displayValue": "35.7",
"abbreviation": "3P%",
"label": "Three Point %"
},
{
"name": "freeThrowsMade-freeThrowsAttempted",
"displayValue": "28-35",
"label": "FT"
},
{
"name": "freeThrowPct",
"displayValue": "80.0",
"abbreviation": "FT%",
"label": "Free Throw %"
},
{
"name": "totalRebounds",
"displayValue": "53",
"abbreviation": "REB",
"label": "Rebounds"
},
{
"name": "offensiveRebounds",
"displayValue": "8",
"abbreviation": "OR",
"label": "Offensive Rebounds"
},
{
"name": "defensiveRebounds",
"displayValue": "33",
"abbreviation": "DR",
"label": "Defensive Rebounds"
},
{
"name": "assists",
"displayValue": "18",
"abbreviation": "AST",
"label": "Assists"
},
{
"name": "steals",
"displayValue": "10",
"abbreviation": "STL",
"label": "Steals"
},
{
"name": "blocks",
"displayValue": "3",
"abbreviation": "BLK",
"label": "Blocks"
},
{
"name": "turnovers",
"displayValue": "13",
"abbreviation": "TO",
"label": "Turnovers"
},
{
"name": "teamTurnovers",
"displayValue": "13",
"abbreviation": "TTO",
"label": "Team Turnovers"
},
{
"name": "totalTurnovers",
"displayValue": "26",
"abbreviation": "ToTO",
"label": "Total Turnovers"
},
{
"name": "technicalFouls",
"displayValue": "1",
"abbreviation": "TECH",
"label": "Technical Fouls"
},
{
"name": "totalTechnicalFouls",
"displayValue": "1",
"abbreviation": "TECH",
"label": "Total Technical Fouls"
},
{
"name": "flagrantFouls",
"displayValue": "0",
"abbreviation": "FLAG",
"label": "Flagrant Fouls"
},
{
"name": "turnoverPoints",
"displayValue": "11",
"abbreviation": "PTS OFF TO",
"label": "Points Off Turnovers"
},
{
"name": "fastBreakPoints",
"displayValue": "10",
"abbreviation": "FBPs",
"label": "Fast Break Points"
},
{
"name": "pointsInPaint",
"displayValue": "-1",
"abbreviation": "PIP",
"label": "Points in Paint"
},
{
"name": "fouls",
"displayValue": "23",
"abbreviation": "PF",
"label": "Fouls"
}
]
},
{
"team": {
"id": "18",
"uid": "s:40~l:46~t:18",
"slug": "new-york-knicks",
"location": "New York",
"name": "Knicks",
"abbreviation": "NY",
"displayName": "New York Knicks",
"shortDisplayName": "Knicks",
"color": "225EA8",
"alternateColor": "f58426",
"logo": "https://a.espncdn.com/i/teamlogos/nba/500/ny.png"
},
"statistics": [
{
"name": "fieldGoalsMade-fieldGoalsAttempted",
"displayValue": "33-81",
"label": "FG"
},
{
"name": "fieldGoalPct",
"displayValue": "40.7",
"abbreviation": "FG%",
"label": "Field Goal %"
},
{
"name": "threePointFieldGoalsMade-threePointFieldGoalsAttempted",
"displayValue": "6-18",
"label": "3PT"
},
{
"name": "threePointFieldGoalPct",
"displayValue": "33.3",
"abbreviation": "3P%",
"label": "Three Point %"
},
{
"name": "freeThrowsMade-freeThrowsAttempted",
"displayValue": "25-30",
"label": "FT"
},
{
"name": "freeThrowPct",
"displayValue": "83.3",
"abbreviation": "FT%",
"label": "Free Throw %"
},
{
"name": "totalRebounds",
"displayValue": "50",
"abbreviation": "REB",
"label": "Rebounds"
},
{
"name": "offensiveRebounds",
"displayValue": "6",
"abbreviation": "OR",
"label": "Offensive Rebounds"
},
{
"name": "defensiveRebounds",
"displayValue": "28",
"abbreviation": "DR",
"label": "Defensive Rebounds"
},
{
"name": "assists",
"displayValue": "20",
"abbreviation": "AST",
"label": "Assists"
},
{
"name": "steals",
"displayValue": "8",
"abbreviation": "STL",
"label": "Steals"
},
{
"name": "blocks",
"displayValue": "7",
"abbreviation": "BLK",
"label": "Blocks"
},
{
"name": "turnovers",
"displayValue": "12",
"abbreviation": "TO",
"label": "Turnovers"
},
{
"name": "teamTurnovers",
"displayValue": "12",
"abbreviation": "TTO",
"label": "Team Turnovers"
},
{
"name": "totalTurnovers",
"displayValue": "24",
"abbreviation": "ToTO",
"label": "Total Turnovers"
},
{
"name": "technicalFouls",
"displayValue": "0",
"abbreviation": "TECH",
"label": "Technical Fouls"
},
{
"name": "totalTechnicalFouls",
"displayValue": "0",
"abbreviation": "TECH",
"label": "Total Technical Fouls"
},
{
"name": "flagrantFouls",
"displayValue": "0",
"abbreviation": "FLAG",
"label": "Flagrant Fouls"
},
{
"name": "turnoverPoints",
"displayValue": "14",
"abbreviation": "PTS OFF TO",
"label": "Points Off Turnovers"
},
{
"name": "fastBreakPoints",
"displayValue": "11",
"abbreviation": "FBPs",
"label": "Fast Break Points"
},
{
"name": "pointsInPaint",
"displayValue": "-1",
"abbreviation": "PIP",
"label": "Points in Paint"
},
{
"name": "fouls",
"displayValue": "23",
"abbreviation": "PF",
"label": "Fouls"
}
]
}
],
"players": [
{
"team": {
"id": "15",
"uid": "s:40~l:46~t:15",
"slug": "milwaukee-bucks",
"location": "Milwaukee",
"name": "Bucks",
"abbreviation": "MIL",
"displayName": "Milwaukee Bucks",
"shortDisplayName": "Bucks",
"color": "003813",
"alternateColor": "f0ebd2",
"logo": "https://a.espncdn.com/i/teamlogos/nba/500/mil.png"
},
"statistics": [
{
"names": [
"MIN",
"FG",
"3PT",
"FT",
"OREB",
"DREB",
"REB",
"AST",
"STL",
"BLK",
"TO",
"PF",
"+/-",
"PTS"
],
"keys": [
"minutes",
"fieldGoalsMade-fieldGoalsAttempted",
"threePointFieldGoalsMade-threePointFieldGoalsAttempted",
"freeThrowsMade-freeThrowsAttempted",
"offensiveRebounds",
"defensiveRebounds",
"rebounds",
"assists",
"steals",
"blocks",
"turnovers",
"fouls",
"plusMinus",
"points"
],
"labels": [
"MIN",
"FG",
"3PT",
"FT",
"OREB",
"DREB",
"REB",
"AST",
"STL",
"BLK",
"TO",
"PF",
"+/-",
"PTS"
],
"descriptions": [
"Minutes",
"Field Goals Made/Attempted",
"3-Point Field Goals Made/Attempted",
"Free Throws Made/Attempted",
"Offensive Rebounds",
"Defensive Rebounds",
"Rebounds",
"Assists",
"Steals",
"Blocks",
"Turnovers",
"Personal Fouls",
"Teams net points while player is on the court.",
"Points"
],
"athletes": [
{
"active": false,
"athlete": {
"id": "847",
"uid": "s:40~l:46~a:847",
"guid": "78834bab944ca867e076aee84ede423e",
"displayName": "Tim Thomas",
"shortName": "T. Thomas",
"links": [
{
"rel": [
"playercard",
"desktop",
"athlete"
],
"href": "https://www.espn.com/nba/player/_/id/847/tim-thomas",
"text": "Player Card"
},
{
"rel": [
"stats",
"desktop",
"athlete"
],
"href": "http://www.espn.com/nba/player/stats/_/id/847/tim-thomas",
"text": "Stats"
},
{
"rel": [
"splits",
"desktop",
"athlete"
],
"href": "http://www.espn.com/nba/player/splits/_/id/847/tim-thomas",
"text": "Splits"
},
{
"rel": [
"gamelog",
"desktop",
"athlete"
],
"href": "http://www.espn.com/nba/player/gamelog/_/id/847/tim-thomas",
"text": "Game Log"
},
{
"rel": [
"news",
"desktop",
"athlete"
],
"href": "http://www.espn.com/nba/player/news/_/id/847/tim-thomas",
"text": "News"
},
{
"rel": [
"bio",
"desktop",
"athlete"
],
"href": "http://www.espn.com/nba/player/bio/_/id/847/tim-thomas",
"text": "Bio"
},
{
"rel": [
"overview",
"desktop",
"athlete"
],
"href": "http://www.espn.com/nba/player/_/id/847/tim-thomas",
"text": "Overview"
},
{
"rel": [
"advancedstats",
"desktop",
"athlete"
],
"href": "http://www.espn.com/nba/player/advancedstats/_/id/847/tim-thomas",
"text": "Advanced Stats"
}
],
"jersey": "7",
"position": {
"name": "Power Forward",
"displayName": "Power Forward",
"abbreviation": "PF"
}
},
"starter": true,
"didNotPlay": false,
"ejected": false,
"stats": [
"34",
"3-10",
"0-3",
"3-4",
"0",
"4",
"4",
"2",
"2",
"0",
"4",
"3",
"--",
"9"
]
},
{
"active": false,
"athlete": {
"id": "517",
"uid": "s:40~l:46~a:517",
"guid": "1a1f5b295e16504c56e5c0569ba39d63",
"displayName": "Anthony Mason",
"shortName": "A. Mason",
"links": [
{
"rel": [
"playercard",
"desktop",
"athlete"
],
"href": "https://www.espn.com/nba/player/_/id/517/anthony-mason",
"text": "Player Card"
},
{
"rel": [
"stats",
"desktop",
"athlete"
],
"href": "http://www.espn.com/nba/player/stats/_/id/517/anthony-mason",
"text": "Stats"
},
{
"rel": [
"splits",
"desktop",
"athlete"
],
"href": "http://www.espn.com/nba/player/splits/_/id/517/anthony-mason",
"text": "Splits"
},
{
"rel": [
"gamelog",
"desktop",
"athlete"
],
"href": "http://www.espn.com/nba/player/gamelog/_/id/517/anthony-mason",
"text": "Game Log"
},
{
"rel": [
"news",
"desktop",
"athlete"
],
"href": "http://www.espn.com/nba/player/news/_/id/517/anthony-mason",
"text": "News"
},
{
"rel": [
"bio",
"desktop",
"athlete"
],
"href": "http://www.espn.com/nba/player/bio/_/id/517/anthony-mason",
"text": "Bio"
},
{
"rel": [
"overview",
"desktop",
"athlete"
],
"href": "http://www.espn.com/nba/player/_/id/517/anthony-mason",
"text": "Overview"
},
{
"rel": [
"advancedstats",
"desktop",
"athlete"
],
"href": "http://www.espn.com/nba/player/advancedstats/_/id/517/anthony-mason",
"text": "Advanced Stats"
}
],
"jersey": "99",
"position": {
"name": "Forward",
"displayName": "Forward",
"abbreviation": "F"
}
},
"starter": true,
"didNotPlay": false,
"ejected": false,
"stats": [
"39",
"4-8",
"0-0",
"4-6",
"2",
"7",
"9",
"5",
"1",
"0",
"1",
"2",
"--",
"12"
]
},
{
"active": false,
"athlete": {
"id": "682",
"uid": "s:40~l:46~a:682",
"guid": "5f1863c059b5d8e43883e9a9cdf679c3",
"displayName": "Joel Przybilla",
"shortName": "J. Przybilla",
"links": [
{
"rel": [
"playercard",
"desktop",
"athlete"
],
"href": "https://www.espn.com/nba/player/_/id/682/joel-przybilla",
"text": "Player Card"
},
{
"rel": [
"stats",
"desktop",
"athlete"
],
"href": "http://www.espn.com/nba/player/stats/_/id/682/joel-przybilla",
"text": "Stats"
},
{
"rel": [
"splits",
"desktop",
"athlete"
],
"href": "http://www.espn.com/nba/player/splits/_/id/682/joel-przybilla",
"text": "Splits"
},
{
"rel": [
"gamelog",
"desktop",
"athlete"
],
"href": "http://www.espn.com/nba/player/gamelog/_/id/682/joel-przybilla",
"text": "Game Log"
},
{
"rel": [
"news",
"desktop",
"athlete"
],
"href": "http://www.espn.com/nba/player/news/_/id/682/joel-przybilla",
"text": "News"
},
{
"rel": [
"bio",
"desktop",
"athlete"
],
"href": "http://www.espn.com/nba/player/bio/_/id/682/joel-przybilla",
"text": "Bio"
},
{
"rel": [
"overview",
"desktop",
"athlete"
],
"href": "http://www.espn.com/nba/player/_/id/682/joel-przybilla",
"text": "Overview"
},
{
"rel": [
"advancedstats",
"desktop",
"athlete"
],
"href": "http://www.espn.com/nba/player/advancedstats/_/id/682/joel-przybilla",
"text": "Advanced Stats"
}
],
"headshot": {
"href": "https://a.espncdn.com/i/headshots/nba/players/full/682.png",
"alt": "Joel Przybilla"
},
"jersey": "10",
"position": {
"name": "Center",
"displayName": "Center",
"abbreviation": "C"
}
},
"starter": true,
"didNotPlay": false,
"ejected": false,
"stats": [
"18",
"1-1",
"0-0",
"2-2",
"1",
"2",
"3",
"1",
"0",
"1",
"1",
"2",
"--",
"4"
]
},
{
"active": false,
"athlete": {
"id": "138",
"uid": "s:40~l:46~a:138",
"guid": "472fc4e6384dee34f66c5aba2b947dd9",
"displayName": "Sam Cassell",
"shortName": "S. Cassell",
"links": [
{
"rel": [
"playercard",
"desktop",
"athlete"
],
"href": "https://www.espn.com/nba/player/_/id/138/sam-cassell",
"text": "Player Card"
},
{
"rel": [
"stats",
"desktop",
"athlete"
],
"href": "http://www.espn.com/nba/player/stats/_/id/138/sam-cassell",
"text": "Stats"
},
{
"rel": [
"splits",
"desktop",
"athlete"
],
"href": "http://www.espn.com/nba/player/splits/_/id/138/sam-cassell",
"text": "Splits"
},
{
"rel": [
"gamelog",
"desktop",
"athlete"
],
"href": "http://www.espn.com/nba/player/gamelog/_/id/138/sam-cassell",
"text": "Game Log"
},
{
"rel": [
"news",
"desktop",
"athlete"
],
"href": "http://www.espn.com/nba/player/news/_/id/138/sam-cassell",
"text": "News"
},
{
"rel": [
"bio",
"desktop",
"athlete"
],
"href": "http://www.espn.com/nba/player/bio/_/id/138/sam-cassell",
"text": "Bio"
},
{
"rel": [
"overview",
"desktop",
"athlete"
],
"href": "http://www.espn.com/nba/player/_/id/138/sam-cassell",
"text": "Overview"
},
{
"rel": [
"advancedstats",
"desktop",
"athlete"
],
"href": "http://www.espn.com/nba/player/advancedstats/_/id/138/sam-cassell",
"text": "Advanced Stats"
}
],
"position": {
"name": "Point Guard",
"displayName": "Point Guard",
"abbreviation": "PG"
}
},
"starter": true,
"didNotPlay": false,
"ejected": false,
"stats": [
"40",
"8-21",
"1-7",
"7-8",
"0",
"5",
"5",
"5",
"3",
"0",
"4",
"4",
"--",
"24"
]
},
{
"active": false,
"athlete": {
"id": "9",
"uid": "s:40~l:46~a:9",
"guid": "f0d2ffd468663cea4918f1fd2f8b2ced",
"displayName": "Ray Allen",
"shortName": "R. Allen",
"links": [
{
"rel": [
"playercard",
"desktop",
"athlete"
],
"href": "https://www.espn.com/nba/player/_/id/9/ray-allen",
"text": "Player Card"
},
{
"rel": [
"stats",
"desktop",
"athlete"
],
"href": "http://www.espn.com/nba/player/stats/_/id/9/ray-allen",
"text": "Stats"
},
{
"rel": [
"splits",
"desktop",
"athlete"
],
"href": "http://www.espn.com/nba/player/splits/_/id/9/ray-allen",
"text": "Splits"
},
{
"rel": [
"gamelog",
"desktop",
"athlete"
],
"href": "http://www.espn.com/nba/player/gamelog/_/id/9/ray-allen",
"text": "Game Log"
},
{
"rel": [
"news",
"desktop",
"athlete"
],
"href": "http://www.espn.com/nba/player/news/_/id/9/ray-allen",
"text": "News"
},
{
"rel": [
"bio",
"desktop",
"athlete"
],
"href": "http://www.espn.com/nba/player/bio/_/id/9/ray-allen",
"text": "Bio"
},
{
"rel": [
"overview",
"desktop",
"athlete"
],
"href": "http://www.espn.com/nba/player/_/id/9/ray-allen",
"text": "Overview"
},
{
"rel": [
"advancedstats",
"desktop",
"athlete"
],
"href": "http://www.espn.com/nba/player/advancedstats/_/id/9/ray-allen",
"text": "Advanced Stats"
}
],
"headshot": {
"href": "https://a.espncdn.com/i/headshots/nba/players/full/9.png",
"alt": "Ray Allen"
},
"jersey": "34",
"position": {
"name": "Shooting Guard",
"displayName": "Shooting Guard",
"abbreviation": "SG"
}
},
"starter": true,
"didNotPlay": false,
"ejected": false,
"stats": [
"36",
"10-17",
"8-13",
"9-11",
"1",
"7",
"8",
"2",
"3",
"1",
"2",
"4",
"--",
"37"
]
},
{
"active": false,
"athlete": {
"id": "122",
"uid": "s:40~l:46~a:122",
"guid": "0655bed009271331d10df81c4e2a8e51",
"displayName": "Jason Caffey",
"shortName": "J. Caffey",
"links": [
{
"rel": [
"playercard",
"desktop",
"athlete"
],
"href": "https://www.espn.com/nba/player/_/id/122/jason-caffey",
"text": "Player Card"
},
{
"rel": [
"stats",
"desktop",
"athlete"
],
"href": "http://www.espn.com/nba/player/stats/_/id/122/jason-caffey",
"text": "Stats"
},
{
"rel": [
"splits",
"desktop",
"athlete"
],
"href": "http://www.espn.com/nba/player/splits/_/id/122/jason-caffey",
"text": "Splits"
},
{
"rel": [
"gamelog",
"desktop",
"athlete"
],
"href": "http://www.espn.com/nba/player/gamelog/_/id/122/jason-caffey",
"text": "Game Log"
},
{
"rel": [
"news",
"desktop",
"athlete"
],
"href": "http://www.espn.com/nba/player/news/_/id/122/jason-caffey",
"text": "News"
},
{
"rel": [
"bio",
"desktop",
"athlete"
],
"href": "http://www.espn.com/nba/player/bio/_/id/122/jason-caffey",
"text": "Bio"
},
{
"rel": [
"overview",
"desktop",
"athlete"
],
"href": "http://www.espn.com/nba/player/_/id/122/jason-caffey",
"text": "Overview"
},
{
"rel": [
"advancedstats",
"desktop",
"athlete"
],
"href": "http://www.espn.com/nba/player/advancedstats/_/id/122/jason-caffey",
"text": "Advanced Stats"
}
],
"jersey": "35",
"position": {
"name": "Forward",
"displayName": "Forward",
"abbreviation": "F"
}
},
"starter": false,
"didNotPlay": false,
"ejected": false,
"stats": [
"8",
"0-1",
"0-0",
"0-0",
"0",
"2",
"2",
"1",
"0",
"0",
"0",
"0",
"--",
"0"
]
},
{
"active": false,
"athlete": {
"id": "291",
"uid": "s:40~l:46~a:291",
"guid": "ff0ad91b140a3eab48136f8973cfaa50",
"displayName": "Darvin Ham",
"shortName": "D. Ham",
"links": [
{
"rel": [
"playercard",
"desktop",
"athlete"
],
"href": "https://www.espn.com/nba/player/_/id/291/darvin-ham",
"text": "Player Card"
},
{
"rel": [
"stats",
"desktop",
"athlete"
],
"href": "http://www.espn.com/nba/player/stats/_/id/291/darvin-ham",
"text": "Stats"
},
{
"rel": [
"splits",
"desktop",
"athlete"
],
"href": "http://www.espn.com/nba/player/splits/_/id/291/darvin-ham",
"text": "Splits"
},
{
"rel": [
"gamelog",
"desktop",
"athlete"
],
"href": "http://www.espn.com/nba/player/gamelog/_/id/291/darvin-ham",
"text": "Game Log"
},
{
"rel": [
"news",
"desktop",
"athlete"
],
"href": "http://www.espn.com/nba/player/news/_/id/291/darvin-ham",
"text": "News"
},
{
"rel": [
"bio",
"desktop",
"athlete"
],
"href": "http://www.espn.com/nba/player/bio/_/id/291/darvin-ham",
"text": "Bio"
},
{
"rel": [
"overview",
"desktop",
"athlete"
],
"href": "http://www.espn.com/nba/player/_/id/291/darvin-ham",
"text": "Overview"
},
{
"rel": [
"advancedstats",
"desktop",
"athlete"
],
"href": "http://www.espn.com/nba/player/advancedstats/_/id/291/darvin-ham",
"text": "Advanced Stats"
}
],
"position": {
"name": "Small Forward",
"displayName": "Small Forward",
"abbreviation": "SF"
}
},
"starter": false,
"didNotPlay": false,
"ejected": false,
"stats": [
"22",
"2-4",
"0-1",
"3-3",
"0",
"2",
"2",
"1",
"1",
"1",
"1",
"5",
"--",
"7"
]
},
{
"active": false,
"athlete": {
"id": "393",
"uid": "s:40~l:46~a:393",
"guid": "119ec47b664cc877a0e973a80ec68d45",
"displayName": "Ervin Johnson",
"shortName": "E. Johnson",
"links": [
{
"rel": [
"playercard",
"desktop",
"athlete"
],
"href": "https://www.espn.com/nba/player/_/id/393/ervin-johnson",
"text": "Player Card"
},
{
"rel": [
"stats",
"desktop",
"athlete"
],
"href": "http://www.espn.com/nba/player/stats/_/id/393/ervin-johnson",
"text": "Stats"
},
{
"rel": [
"splits",
"desktop",
"athlete"
],
"href": "http://www.espn.com/nba/player/splits/_/id/393/ervin-johnson",
"text": "Splits"
},
{
"rel": [
"gamelog",
"desktop",
"athlete"
],
"href": "http://www.espn.com/nba/player/gamelog/_/id/393/ervin-johnson",
"text": "Game Log"
},
{
"rel": [
"news",
"desktop",
"athlete"
],
"href": "http://www.espn.com/nba/player/news/_/id/393/ervin-johnson",
"text": "News"
},
{
"rel": [
"bio",
"desktop",
"athlete"
],
"href": "http://www.espn.com/nba/player/bio/_/id/393/ervin-johnson",
"text": "Bio"
},
{
"rel": [
"overview",
"desktop",
"athlete"
],
"href": "http://www.espn.com/nba/player/_/id/393/ervin-johnson",
"text": "Overview"
},
{
"rel": [
"advancedstats",
"desktop",
"athlete"
],
"href": "http://www.espn.com/nba/player/advancedstats/_/id/393/ervin-johnson",
"text": "Advanced Stats"
}
],
"jersey": "40",
"position": {
"name": "Center",
"displayName": "Center",
"abbreviation": "C"
}
},
"starter": false,
"didNotPlay": false,
"ejected": false,
"stats": [
"21",
"1-1",
"0-0",
"0-1",
"1",
"2",
"3",
"0",
"0",
"0",
"0",
"2",
"--",
"2"
]
},
{
"active": false,
"athlete": {
"id": "692",
"uid": "s:40~l:46~a:692",
"guid": "ffdb8c0dff18f409a55332720ab61058",
"displayName": "Michael Redd",
"shortName": "M. Redd",
"links": [
{
"rel": [
"playercard",
"desktop",
"athlete"
],
"href": "https://www.espn.com/nba/player/_/id/692/michael-redd",
"text": "Player Card"
},
{
"rel": [
"stats",
"desktop",
"athlete"
],
"href": "http://www.espn.com/nba/player/stats/_/id/692/michael-redd",
"text": "Stats"
},
{
"rel": [
"splits",
"desktop",
"athlete"
],
"href": "http://www.espn.com/nba/player/splits/_/id/692/michael-redd",
"text": "Splits"
},
{
"rel": [
"gamelog",
"desktop",
"athlete"
],
"href": "http://www.espn.com/nba/player/gamelog/_/id/692/michael-redd",
"text": "Game Log"
},
{
"rel": [
"news",
"desktop",
"athlete"
],
"href": "http://www.espn.com/nba/player/news/_/id/692/michael-redd",
"text": "News"
},
{
"rel": [
"bio",
"desktop",
"athlete"
],
"href": "http://www.espn.com/nba/player/bio/_/id/692/michael-redd",
"text": "Bio"
},
{
"rel": [
"overview",
"desktop",
"athlete"
],
"href": "http://www.espn.com/nba/player/_/id/692/michael-redd",
"text": "Overview"
},
{
"rel": [
"advancedstats",
"desktop",
"athlete"
],
"href": "http://www.espn.com/nba/player/advancedstats/_/id/692/michael-redd",
"text": "Advanced Stats"
}
],
"headshot": {
"href": "https://a.espncdn.com/i/headshots/nba/players/full/692.png",
"alt": "Michael Redd"
},
"jersey": "22",
"position": {
"name": "Shooting Guard",
"displayName": "Shooting Guard",
"abbreviation": "SG"
}
},
"starter": false,
"didNotPlay": false,
"ejected": false,
"stats": [
"22",
"3-12",
"1-4",
"0-0",
"3",
"2",
"5",
"1",
"0",
"0",
"0",
"1",
"--",
"7"
]
},
{
"active": false,
"athlete": {
"id": "717",
"uid": "s:40~l:46~a:717",
"guid": "6fa40f7e59f75be0b6fcd78f58903815",
"displayName": "Glenn Robinson",
"shortName": "G. Robinson",
"links": [
{
"rel": [
"playercard",
"desktop",
"athlete"
],
"href": "https://www.espn.com/nba/player/_/id/717/glenn-robinson",
"text": "Player Card"
},
{
"rel": [
"stats",
"desktop",
"athlete"
],
"href": "http://www.espn.com/nba/player/stats/_/id/717/glenn-robinson",
"text": "Stats"
},
{
"rel": [
"splits",
"desktop",
"athlete"
],
"href": "http://www.espn.com/nba/player/splits/_/id/717/glenn-robinson",
"text": "Splits"
},
{
"rel": [
"gamelog",
"desktop",
"athlete"
],
"href": "http://www.espn.com/nba/player/gamelog/_/id/717/glenn-robinson",
"text": "Game Log"
},
{
"rel": [
"news",
"desktop",
"athlete"
],
"href": "http://www.espn.com/nba/player/news/_/id/717/glenn-robinson",
"text": "News"
},
{
"rel": [
"bio",
"desktop",
"athlete"
],
"href": "http://www.espn.com/nba/player/bio/_/id/717/glenn-robinson",
"text": "Bio"
},
{
"rel": [
"overview",
"desktop",
"athlete"
],
"href": "http://www.espn.com/nba/player/_/id/717/glenn-robinson",
"text": "Overview"
},
{
"rel": [
"advancedstats",
"desktop",
"athlete"
],
"href": "http://www.espn.com/nba/player/advancedstats/_/id/717/glenn-robinson",
"text": "Advanced Stats"
}
],
"jersey": "3",
"position": {
"name": "Small Forward",
"displayName": "Small Forward",
"abbreviation": "SF"
}
},
"starter": false,
"didNotPlay": true,
"ejected": false,
"stats": []
},
{
"active": false,
"athlete": {
"id": "667",
"uid": "s:40~l:46~a:667",
"guid": "6c135a4381cbdb92f6cad3f00206a1a3",
"displayName": "Mark Pope",
"shortName": "M. Pope",
"links": [
{
"rel": [
"playercard",
"desktop",
"athlete"
],
"href": "https://www.espn.com/nba/player/_/id/667/mark-pope",
"text": "Player Card"
},
{
"rel": [
"stats",
"desktop",
"athlete"
],
"href": "http://www.espn.com/nba/player/stats/_/id/667/mark-pope",
"text": "Stats"
},
{
"rel": [
"splits",
"desktop",
"athlete"
],
"href": "http://www.espn.com/nba/player/splits/_/id/667/mark-pope",
"text": "Splits"
},
{
"rel": [
"gamelog",
"desktop",
"athlete"
],
"href": "http://www.espn.com/nba/player/gamelog/_/id/667/mark-pope",
"text": "Game Log"
},
{
"rel": [
"news",
"desktop",
"athlete"
],
"href": "http://www.espn.com/nba/player/news/_/id/667/mark-pope",
"text": "News"
},
{
"rel": [
"bio",
"desktop",
"athlete"
],
"href": "http://www.espn.com/nba/player/bio/_/id/667/mark-pope",
"text": "Bio"
},
{
"rel": [
"overview",
"desktop",
"athlete"
],
"href": "http://www.espn.com/nba/player/_/id/667/mark-pope",
"text": "Overview"
},
{
"rel": [
"advancedstats",
"desktop",
"athlete"
],
"href": "http://www.espn.com/nba/player/advancedstats/_/id/667/mark-pope",
"text": "Advanced Stats"
}
],
"jersey": "41",
"position": {
"name": "Center",
"displayName": "Center",
"abbreviation": "C"
}
},
"starter": false,
"didNotPlay": true,
"ejected": false,
"stats": []
},
{
"active": false,
"athlete": {
"id": "11",
"uid": "s:40~l:46~a:11",
"guid": "cc988e986520fd659f786954e75154a3",
"displayName": "Rafer Alston",
"shortName": "R. Alston",
"links": [
{
"rel": [
"playercard",
"desktop",
"athlete"
],
"href": "https://www.espn.com/nba/player/_/id/11/rafer-alston",
"text": "Player Card"
},
{
"rel": [
"stats",
"desktop",
"athlete"
],
"href": "http://www.espn.com/nba/player/stats/_/id/11/rafer-alston",
"text": "Stats"
},
{
"rel": [
"splits",
"desktop",
"athlete"
],
"href": "http://www.espn.com/nba/player/splits/_/id/11/rafer-alston",
"text": "Splits"
},
{
"rel": [
"gamelog",
"desktop",
"athlete"
],
"href": "http://www.espn.com/nba/player/gamelog/_/id/11/rafer-alston",
"text": "Game Log"
},
{
"rel": [
"news",
"desktop",
"athlete"
],
"href": "http://www.espn.com/nba/player/news/_/id/11/rafer-alston",
"text": "News"
},
{
"rel": [
"bio",
"desktop",
"athlete"
],
"href": "http://www.espn.com/nba/player/bio/_/id/11/rafer-alston",
"text": "Bio"
},
{
"rel": [
"overview",
"desktop",
"athlete"
],
"href": "http://www.espn.com/nba/player/_/id/11/rafer-alston",
"text": "Overview"
},
{
"rel": [
"advancedstats",
"desktop",
"athlete"
],
"href": "http://www.espn.com/nba/player/advancedstats/_/id/11/rafer-alston",
"text": "Advanced Stats"
}
],
"position": {
"name": "Point Guard",
"displayName": "Point Guard",
"abbreviation": "PG"
}
},
"starter": false,
"didNotPlay": true,
"ejected": false,
"stats": []
}
],
"totals": [
"",
"32-75",
"10-28",
"28-35",
"8",
"33",
"41",
"18",
"10",
"3",
"13",
"23",
"",
"102"
]
}
]
},
{
"team": {
"id": "18",
"uid": "s:40~l:46~t:18",
"slug": "new-york-knicks",
"location": "New York",
"name": "Knicks",
"abbreviation": "NY",
"displayName": "New York Knicks",
"shortDisplayName": "Knicks",
"color": "225EA8",
"alternateColor": "f58426",
"logo": "https://a.espncdn.com/i/teamlogos/nba/500/ny.png"
},
"statistics": [
{
"names": [
"MIN",
"FG",
"3PT",
"FT",
"OREB",
"DREB",
"REB",
"AST",
"STL",
"BLK",
"TO",
"PF",
"+/-",
"PTS"
],
"keys": [
"minutes",
"fieldGoalsMade-fieldGoalsAttempted",
"threePointFieldGoalsMade-threePointFieldGoalsAttempted",
"freeThrowsMade-freeThrowsAttempted",
"offensiveRebounds",
"defensiveRebounds",
"rebounds",
"assists",
"steals",
"blocks",
"turnovers",
"fouls",
"plusMinus",
"points"
],
"labels": [
"MIN",
"FG",
"3PT",
"FT",
"OREB",
"DREB",
"REB",
"AST",
"STL",
"BLK",
"TO",
"PF",
"+/-",
"PTS"
],
"descriptions": [
"Minutes",
"Field Goals Made/Attempted",
"3-Point Field Goals Made/Attempted",
"Free Throws Made/Attempted",
"Offensive Rebounds",
"Defensive Rebounds",
"Rebounds",
"Assists",
"Steals",
"Blocks",
"Turnovers",
"Personal Fouls",
"Teams net points while player is on the court.",
"Points"
],
"athletes": [
{
"active": false,
"athlete": {
"id": "846",
"uid": "s:40~l:46~a:846",
"guid": "39d10dd4c0fcd57ac50a5631e2dbabe0",
"displayName": "Kurt Thomas",
"shortName": "K. Thomas",
"links": [
{
"rel": [
"playercard",
"desktop",
"athlete"
],
"href": "https://www.espn.com/nba/player/_/id/846/kurt-thomas",
"text": "Player Card"
},
{
"rel": [
"stats",
"desktop",
"athlete"
],
"href": "http://www.espn.com/nba/player/stats/_/id/846/kurt-thomas",
"text": "Stats"
},
{
"rel": [
"splits",
"desktop",
"athlete"
],
"href": "http://www.espn.com/nba/player/splits/_/id/846/kurt-thomas",
"text": "Splits"
},
{
"rel": [
"gamelog",
"desktop",
"athlete"
],
"href": "http://www.espn.com/nba/player/gamelog/_/id/846/kurt-thomas",
"text": "Game Log"
},
{
"rel": [
"news",
"desktop",
"athlete"
],
"href": "http://www.espn.com/nba/player/news/_/id/846/kurt-thomas",
"text": "News"
},
{
"rel": [
"bio",
"desktop",
"athlete"
],
"href": "http://www.espn.com/nba/player/bio/_/id/846/kurt-thomas",
"text": "Bio"
},
{
"rel": [
"overview",
"desktop",
"athlete"
],
"href": "http://www.espn.com/nba/player/_/id/846/kurt-thomas",
"text": "Overview"
},
{
"rel": [
"advancedstats",
"desktop",
"athlete"
],
"href": "http://www.espn.com/nba/player/advancedstats/_/id/846/kurt-thomas",
"text": "Advanced Stats"
}
],
"headshot": {
"href": "https://a.espncdn.com/i/headshots/nba/players/full/846.png",
"alt": "Kurt Thomas"
},
"jersey": "40",
"position": {
"name": "Power Forward",
"displayName": "Power Forward",
"abbreviation": "PF"
}
},
"starter": true,
"didNotPlay": false,
"ejected": false,
"stats": [
"43",
"3-9",
"0-0",
"4-4",
"2",
"7",
"9",
"1",
"0",
"2",
"0",
"5",
"--",
"10"
]
},
{
"active": false,
"athlete": {
"id": "125",
"uid": "s:40~l:46~a:125",
"guid": "8d94466178df266276dd357f8e3604d5",
"displayName": "Marcus Camby",
"shortName": "M. Camby",
"links": [
{
"rel": [
"playercard",
"desktop",
"athlete"
],
"href": "https://www.espn.com/nba/player/_/id/125/marcus-camby",
"text": "Player Card"
},
{
"rel": [
"stats",
"desktop",
"athlete"
],
"href": "http://www.espn.com/nba/player/stats/_/id/125/marcus-camby",
"text": "Stats"
},
{
"rel": [
"splits",
"desktop",
"athlete"
],
"href": "http://www.espn.com/nba/player/splits/_/id/125/marcus-camby",
"text": "Splits"
},
{
"rel": [
"gamelog",
"desktop",
"athlete"
],
"href": "http://www.espn.com/nba/player/gamelog/_/id/125/marcus-camby",
"text": "Game Log"
},
{
"rel": [
"news",
"desktop",
"athlete"
],
"href": "http://www.espn.com/nba/player/news/_/id/125/marcus-camby",
"text": "News"
},
{
"rel": [
"bio",
"desktop",
"athlete"
],
"href": "http://www.espn.com/nba/player/bio/_/id/125/marcus-camby",
"text": "Bio"
},
{
"rel": [
"overview",
"desktop",
"athlete"
],
"href": "http://www.espn.com/nba/player/_/id/125/marcus-camby",
"text": "Overview"
},
{
"rel": [
"advancedstats",
"desktop",
"athlete"
],
"href": "http://www.espn.com/nba/player/advancedstats/_/id/125/marcus-camby",
"text": "Advanced Stats"
}
],
"headshot": {
"href": "https://a.espncdn.com/i/headshots/nba/players/full/125.png",
"alt": "Marcus Camby"
},
"jersey": "21",
"position": {
"name": "Center",
"displayName": "Center",
"abbreviation": "C"
}
},
"starter": true,
"didNotPlay": false,
"ejected": false,
"stats": [
"35",
"5-7",
"0-0",
"1-2",
"1",
"7",
"8",
"0",
"3",
"1",
"4",
"6",
"--",
"11"
]
},
{
"active": false,
"athlete": {
"id": "370",
"uid": "s:40~l:46~a:370",
"guid": "a05499ab1061fbdd2af7d848546d6678",
"displayName": "Mark Jackson",
"shortName": "M. Jackson",
"links": [
{
"rel": [
"playercard",
"desktop",
"athlete"
],
"href": "https://www.espn.com/nba/player/_/id/370/mark-jackson",
"text": "Player Card"
},
{
"rel": [
"stats",
"desktop",
"athlete"
],
"href": "http://www.espn.com/nba/player/stats/_/id/370/mark-jackson",
"text": "Stats"
},
{
"rel": [
"splits",
"desktop",
"athlete"
],
"href": "http://www.espn.com/nba/player/splits/_/id/370/mark-jackson",
"text": "Splits"
},
{
"rel": [
"gamelog",
"desktop",
"athlete"
],
"href": "http://www.espn.com/nba/player/gamelog/_/id/370/mark-jackson",
"text": "Game Log"
},
{
"rel": [
"news",
"desktop",
"athlete"
],
"href": "http://www.espn.com/nba/player/news/_/id/370/mark-jackson",
"text": "News"
},
{
"rel": [
"bio",
"desktop",
"athlete"
],
"href": "http://www.espn.com/nba/player/bio/_/id/370/mark-jackson",
"text": "Bio"
},
{
"rel": [
"overview",
"desktop",
"athlete"
],
"href": "http://www.espn.com/nba/player/_/id/370/mark-jackson",
"text": "Overview"
},
{
"rel": [
"advancedstats",
"desktop",
"athlete"
],
"href": "http://www.espn.com/nba/player/advancedstats/_/id/370/mark-jackson",
"text": "Advanced Stats"
}
],
"jersey": "31",
"position": {
"name": "Point Guard",
"displayName": "Point Guard",
"abbreviation": "PG"
}
},
"starter": true,
"didNotPlay": false,
"ejected": false,
"stats": [
"35",
"5-10",
"2-4",
"3-6",
"0",
"4",
"4",
"11",
"2",
"0",
"1",
"4",
"--",
"15"
]
},
{
"active": false,
"athlete": {
"id": "349",
"uid": "s:40~l:46~a:349",
"guid": "5aee772a22bec1d9016eb6196d02ee3a",
"displayName": "Allan Houston",
"shortName": "A. Houston",
"links": [
{
"rel": [
"playercard",
"desktop",
"athlete"
],
"href": "https://www.espn.com/nba/player/_/id/349/allan-houston",
"text": "Player Card"
},
{
"rel": [
"stats",
"desktop",
"athlete"
],
"href": "http://www.espn.com/nba/player/stats/_/id/349/allan-houston",
"text": "Stats"
},
{
"rel": [
"splits",
"desktop",
"athlete"
],
"href": "http://www.espn.com/nba/player/splits/_/id/349/allan-houston",
"text": "Splits"
},
{
"rel": [
"gamelog",
"desktop",
"athlete"
],
"href": "http://www.espn.com/nba/player/gamelog/_/id/349/allan-houston",
"text": "Game Log"
},
{
"rel": [
"news",
"desktop",
"athlete"
],
"href": "http://www.espn.com/nba/player/news/_/id/349/allan-houston",
"text": "News"
},
{
"rel": [
"bio",
"desktop",
"athlete"
],
"href": "http://www.espn.com/nba/player/bio/_/id/349/allan-houston",
"text": "Bio"
},
{
"rel": [
"overview",
"desktop",
"athlete"
],
"href": "http://www.espn.com/nba/player/_/id/349/allan-houston",
"text": "Overview"
},
{
"rel": [
"advancedstats",
"desktop",
"athlete"
],
"href": "http://www.espn.com/nba/player/advancedstats/_/id/349/allan-houston",
"text": "Advanced Stats"
}
],
"jersey": "7",
"position": {
"name": "Shooting Guard",
"displayName": "Shooting Guard",
"abbreviation": "SG"
}
},
"starter": true,
"didNotPlay": false,
"ejected": false,
"stats": [
"43",
"13-29",
"4-10",
"14-15",
"1",
"2",
"3",
"5",
"0",
"2",
"2",
"4",
"--",
"44"
]
},
{
"active": false,
"athlete": {
"id": "800",
"uid": "s:40~l:46~a:800",
"guid": "6a3ac1a3ae1b26a377f7b8d8d41539a1",
"displayName": "Latrell Sprewell",
"shortName": "L. Sprewell",
"links": [
{
"rel": [
"playercard",
"desktop",
"athlete"
],
"href": "https://www.espn.com/nba/player/_/id/800/latrell-sprewell",
"text": "Player Card"
},
{
"rel": [
"stats",
"desktop",
"athlete"
],
"href": "http://www.espn.com/nba/player/stats/_/id/800/latrell-sprewell",
"text": "Stats"
},
{
"rel": [
"splits",
"desktop",
"athlete"
],
"href": "http://www.espn.com/nba/player/splits/_/id/800/latrell-sprewell",
"text": "Splits"
},
{
"rel": [
"gamelog",
"desktop",
"athlete"
],
"href": "http://www.espn.com/nba/player/gamelog/_/id/800/latrell-sprewell",
"text": "Game Log"
},
{
"rel": [
"news",
"desktop",
"athlete"
],
"href": "http://www.espn.com/nba/player/news/_/id/800/latrell-sprewell",
"text": "News"
},
{
"rel": [
"bio",
"desktop",
"athlete"
],
"href": "http://www.espn.com/nba/player/bio/_/id/800/latrell-sprewell",
"text": "Bio"
},
{
"rel": [
"overview",
"desktop",
"athlete"
],
"href": "http://www.espn.com/nba/player/_/id/800/latrell-sprewell",
"text": "Overview"
},
{
"rel": [
"advancedstats",
"desktop",
"athlete"
],
"href": "http://www.espn.com/nba/player/advancedstats/_/id/800/latrell-sprewell",
"text": "Advanced Stats"
}
],
"jersey": "8",
"position": {
"name": "Shooting Guard",
"displayName": "Shooting Guard",
"abbreviation": "SG"
}
},
"starter": true,
"didNotPlay": false,
"ejected": false,
"stats": [
"40",
"5-18",
"0-2",
"3-3",
"1",
"2",
"3",
"1",
"1",
"0",
"2",
"3",
"--",
"13"
]
},
{
"active": false,
"athlete": {
"id": "307",
"uid": "s:40~l:46~a:307",
"guid": "cc90b837e4bb15db61ff4e090d732329",
"displayName": "Othella Harrington",
"shortName": "O. Harrington",
"links": [
{
"rel": [
"playercard",
"desktop",
"athlete"
],
"href": "https://www.espn.com/nba/player/_/id/307/othella-harrington",
"text": "Player Card"
},
{
"rel": [
"stats",
"desktop",
"athlete"
],
"href": "http://www.espn.com/nba/player/stats/_/id/307/othella-harrington",
"text": "Stats"
},
{
"rel": [
"splits",
"desktop",
"athlete"
],
"href": "http://www.espn.com/nba/player/splits/_/id/307/othella-harrington",
"text": "Splits"
},
{
"rel": [
"gamelog",
"desktop",
"athlete"
],
"href": "http://www.espn.com/nba/player/gamelog/_/id/307/othella-harrington",
"text": "Game Log"
},
{
"rel": [
"news",
"desktop",
"athlete"
],
"href": "http://www.espn.com/nba/player/news/_/id/307/othella-harrington",
"text": "News"
},
{
"rel": [
"bio",
"desktop",
"athlete"
],
"href": "http://www.espn.com/nba/player/bio/_/id/307/othella-harrington",
"text": "Bio"
},
{
"rel": [
"overview",
"desktop",
"athlete"
],
"href": "http://www.espn.com/nba/player/_/id/307/othella-harrington",
"text": "Overview"
},
{
"rel": [
"advancedstats",
"desktop",
"athlete"
],
"href": "http://www.espn.com/nba/player/advancedstats/_/id/307/othella-harrington",
"text": "Advanced Stats"
}
],
"jersey": "24",
"position": {
"name": "Power Forward",
"displayName": "Power Forward",
"abbreviation": "PF"
}
},
"starter": false,
"didNotPlay": false,
"ejected": false,
"stats": [
"18",
"1-4",
"0-1",
"0-0",
"0",
"2",
"2",
"0",
"0",
"1",
"0",
"1",
"--",
"2"
]
},
{
"active": false,
"athlete": {
"id": "17",
"uid": "s:40~l:46~a:17",
"guid": "8fce971797dd0b6315bb483c3fc8ca12",
"displayName": "Shandon Anderson",
"shortName": "S. Anderson",
"links": [
{
"rel": [
"playercard",
"desktop",
"athlete"
],
"href": "https://www.espn.com/nba/player/_/id/17/shandon-anderson",
"text": "Player Card"
},
{
"rel": [
"stats",
"desktop",
"athlete"
],
"href": "http://www.espn.com/nba/player/stats/_/id/17/shandon-anderson",
"text": "Stats"
},
{
"rel": [
"splits",
"desktop",
"athlete"
],
"href": "http://www.espn.com/nba/player/splits/_/id/17/shandon-anderson",
"text": "Splits"
},
{
"rel": [
"gamelog",
"desktop",
"athlete"
],
"href": "http://www.espn.com/nba/player/gamelog/_/id/17/shandon-anderson",
"text": "Game Log"
},
{
"rel": [
"news",
"desktop",
"athlete"
],
"href": "http://www.espn.com/nba/player/news/_/id/17/shandon-anderson",
"text": "News"
},
{
"rel": [
"bio",
"desktop",
"athlete"
],
"href": "http://www.espn.com/nba/player/bio/_/id/17/shandon-anderson",
"text": "Bio"
},
{
"rel": [
"overview",
"desktop",
"athlete"
],
"href": "http://www.espn.com/nba/player/_/id/17/shandon-anderson",
"text": "Overview"
},
{
"rel": [
"advancedstats",
"desktop",
"athlete"
],
"href": "http://www.espn.com/nba/player/advancedstats/_/id/17/shandon-anderson",
"text": "Advanced Stats"
}
],
"jersey": "49",
"position": {
"name": "Small Forward",
"displayName": "Small Forward",
"abbreviation": "SF"
}
},
"starter": false,
"didNotPlay": false,
"ejected": false,
"stats": [
"13",
"1-4",
"0-1",
"0-0",
"1",
"2",
"3",
"1",
"2",
"0",
"1",
"0",
"--",
"2"
]
},
{
"active": false,
"athlete": {
"id": "888",
"uid": "s:40~l:46~a:888",
"guid": "1960f530f8b1d27b288a11e8d52918b8",
"displayName": "Charlie Ward",
"shortName": "C. Ward",
"links": [
{
"rel": [
"playercard",
"desktop",
"athlete"
],
"href": "https://www.espn.com/nba/player/_/id/888/charlie-ward",
"text": "Player Card"
},
{
"rel": [
"stats",
"desktop",
"athlete"
],
"href": "http://www.espn.com/nba/player/stats/_/id/888/charlie-ward",
"text": "Stats"
},
{
"rel": [
"splits",
"desktop",
"athlete"
],
"href": "http://www.espn.com/nba/player/splits/_/id/888/charlie-ward",
"text": "Splits"
},
{
"rel": [
"gamelog",
"desktop",
"athlete"
],
"href": "http://www.espn.com/nba/player/gamelog/_/id/888/charlie-ward",
"text": "Game Log"
},
{
"rel": [
"news",
"desktop",
"athlete"
],
"href": "http://www.espn.com/nba/player/news/_/id/888/charlie-ward",
"text": "News"
},
{
"rel": [
"bio",
"desktop",
"athlete"
],
"href": "http://www.espn.com/nba/player/bio/_/id/888/charlie-ward",
"text": "Bio"
},
{
"rel": [
"overview",
"desktop",
"athlete"
],
"href": "http://www.espn.com/nba/player/_/id/888/charlie-ward",
"text": "Overview"
},
{
"rel": [
"advancedstats",
"desktop",
"athlete"
],
"href": "http://www.espn.com/nba/player/advancedstats/_/id/888/charlie-ward",
"text": "Advanced Stats"
}
],
"jersey": "17",
"position": {
"name": "Point Guard",
"displayName": "Point Guard",
"abbreviation": "PG"
}
},
"starter": false,
"didNotPlay": false,
"ejected": false,
"stats": [
"13",
"0-0",
"0-0",
"0-0",
"0",
"2",
"2",
"1",
"0",
"1",
"0",
"0",
"--",
"0"
]
},
{
"active": false,
"athlete": {
"id": "799",
"uid": "s:40~l:46~a:799",
"guid": "4289d53f2df69721f0c2473d37bcc356",
"displayName": "Felton Spencer",
"shortName": "F. Spencer",
"links": [
{
"rel": [
"playercard",
"desktop",
"athlete"
],
"href": "https://www.espn.com/nba/player/_/id/799/felton-spencer",
"text": "Player Card"
},
{
"rel": [
"stats",
"desktop",
"athlete"
],
"href": "http://www.espn.com/nba/player/stats/_/id/799/felton-spencer",
"text": "Stats"
},
{
"rel": [
"splits",
"desktop",
"athlete"
],
"href": "http://www.espn.com/nba/player/splits/_/id/799/felton-spencer",
"text": "Splits"
},
{
"rel": [
"gamelog",
"desktop",
"athlete"
],
"href": "http://www.espn.com/nba/player/gamelog/_/id/799/felton-spencer",
"text": "Game Log"
},
{
"rel": [
"news",
"desktop",
"athlete"
],
"href": "http://www.espn.com/nba/player/news/_/id/799/felton-spencer",
"text": "News"
},
{
"rel": [
"bio",
"desktop",
"athlete"
],
"href": "http://www.espn.com/nba/player/bio/_/id/799/felton-spencer",
"text": "Bio"
},
{
"rel": [
"overview",
"desktop",
"athlete"
],
"href": "http://www.espn.com/nba/player/_/id/799/felton-spencer",
"text": "Overview"
},
{
"rel": [
"advancedstats",
"desktop",
"athlete"
],
"href": "http://www.espn.com/nba/player/advancedstats/_/id/799/felton-spencer",
"text": "Advanced Stats"
}
],
"jersey": "50",
"position": {
"name": "Center",
"displayName": "Center",
"abbreviation": "C"
}
},
"starter": false,
"didNotPlay": true,
"ejected": false,
"stats": []
},
{
"active": false,
"athlete": {
"id": "220",
"uid": "s:40~l:46~a:220",
"guid": "29a3abc78974ce5439cd66dc12655b90",
"displayName": "Howard Eisley",
"shortName": "H. Eisley",
"links": [
{
"rel": [
"playercard",
"desktop",
"athlete"
],
"href": "https://www.espn.com/nba/player/_/id/220/howard-eisley",
"text": "Player Card"
},
{
"rel": [
"stats",
"desktop",
"athlete"
],
"href": "http://www.espn.com/nba/player/stats/_/id/220/howard-eisley",
"text": "Stats"
},
{
"rel": [
"splits",
"desktop",
"athlete"
],
"href": "http://www.espn.com/nba/player/splits/_/id/220/howard-eisley",
"text": "Splits"
},
{
"rel": [
"gamelog",
"desktop",
"athlete"
],
"href": "http://www.espn.com/nba/player/gamelog/_/id/220/howard-eisley",
"text": "Game Log"
},
{
"rel": [
"news",
"desktop",
"athlete"
],
"href": "http://www.espn.com/nba/player/news/_/id/220/howard-eisley",
"text": "News"
},
{
"rel": [
"bio",
"desktop",
"athlete"
],
"href": "http://www.espn.com/nba/player/bio/_/id/220/howard-eisley",
"text": "Bio"
},
{
"rel": [
"overview",
"desktop",
"athlete"
],
"href": "http://www.espn.com/nba/player/_/id/220/howard-eisley",
"text": "Overview"
},
{
"rel": [
"advancedstats",
"desktop",
"athlete"
],
"href": "http://www.espn.com/nba/player/advancedstats/_/id/220/howard-eisley",
"text": "Advanced Stats"
}
],
"jersey": "10",
"position": {
"name": "Point Guard",
"displayName": "Point Guard",
"abbreviation": "PG"
}
},
"starter": false,
"didNotPlay": true,
"ejected": false,
"stats": []
},
{
"active": false,
"athlete": {
"id": "672",
"uid": "s:40~l:46~a:672",
"guid": "d9d1cef6b99c7f3219420028d9c51a21",
"displayName": "Lavor Postell",
"shortName": "L. Postell",
"links": [
{
"rel": [
"playercard",
"desktop",
"athlete"
],
"href": "https://www.espn.com/nba/player/_/id/672/lavor-postell",
"text": "Player Card"
},
{
"rel": [
"stats",
"desktop",
"athlete"
],
"href": "http://www.espn.com/nba/player/stats/_/id/672/lavor-postell",
"text": "Stats"
},
{
"rel": [
"splits",
"desktop",
"athlete"
],
"href": "http://www.espn.com/nba/player/splits/_/id/672/lavor-postell",
"text": "Splits"
},
{
"rel": [
"gamelog",
"desktop",
"athlete"
],
"href": "http://www.espn.com/nba/player/gamelog/_/id/672/lavor-postell",
"text": "Game Log"
},
{
"rel": [
"news",
"desktop",
"athlete"
],
"href": "http://www.espn.com/nba/player/news/_/id/672/lavor-postell",
"text": "News"
},
{
"rel": [
"bio",
"desktop",
"athlete"
],
"href": "http://www.espn.com/nba/player/bio/_/id/672/lavor-postell",
"text": "Bio"
},
{
"rel": [
"overview",
"desktop",
"athlete"
],
"href": "http://www.espn.com/nba/player/_/id/672/lavor-postell",
"text": "Overview"
},
{
"rel": [
"advancedstats",
"desktop",
"athlete"
],
"href": "http://www.espn.com/nba/player/advancedstats/_/id/672/lavor-postell",
"text": "Advanced Stats"
}
],
"jersey": "7",
"position": {
"name": "Guard",
"displayName": "Guard",
"abbreviation": "G"
}
},
"starter": false,
"didNotPlay": true,
"ejected": false,
"stats": []
},
{
"active": false,
"athlete": {
"id": "716",
"uid": "s:40~l:46~a:716",
"guid": "a461e1bace1cc34a559c05a4651734a8",
"displayName": "Larry Robinson",
"shortName": "L. Robinson",
"links": [
{
"rel": [
"playercard",
"desktop",
"athlete"
],
"href": "https://www.espn.com/nba/player/_/id/716/larry-robinson",
"text": "Player Card"
},
{
"rel": [
"stats",
"desktop",
"athlete"
],
"href": "http://www.espn.com/nba/player/stats/_/id/716/larry-robinson",
"text": "Stats"
},
{
"rel": [
"splits",
"desktop",
"athlete"
],
"href": "http://www.espn.com/nba/player/splits/_/id/716/larry-robinson",
"text": "Splits"
},
{
"rel": [
"gamelog",
"desktop",
"athlete"
],
"href": "http://www.espn.com/nba/player/gamelog/_/id/716/larry-robinson",
"text": "Game Log"
},
{
"rel": [
"news",
"desktop",
"athlete"
],
"href": "http://www.espn.com/nba/player/news/_/id/716/larry-robinson",
"text": "News"
},
{
"rel": [
"bio",
"desktop",
"athlete"
],
"href": "http://www.espn.com/nba/player/bio/_/id/716/larry-robinson",
"text": "Bio"
},
{
"rel": [
"overview",
"desktop",
"athlete"
],
"href": "http://www.espn.com/nba/player/_/id/716/larry-robinson",
"text": "Overview"
},
{
"rel": [
"advancedstats",
"desktop",
"athlete"
],
"href": "http://www.espn.com/nba/player/advancedstats/_/id/716/larry-robinson",
"text": "Advanced Stats"
}
],
"jersey": "25",
"position": {
"name": "Guard",
"displayName": "Guard",
"abbreviation": "G"
}
},
"starter": false,
"didNotPlay": true,
"ejected": false,
"stats": []
}
],
"totals": [
"",
"33-81",
"6-18",
"25-30",
"6",
"28",
"34",
"20",
"8",
"7",
"12",
"23",
"",
"97"
]
}
]
}
]
},
"format": {
"regulation": {
"periods": 4,
"displayName": "Quarter",
"slug": "quarter",
"clock": 720.0
},
"overtime": {
"clock": 300.0
}
},
"gameInfo": {
"venue": {
"id": "1830",
"fullName": "Madison Square Garden",
"shortName": "Madison Square Garde",
"address": {
"city": "New York",
"state": "NY"
},
"capacity": 19763,
"grass": false,
"images": [
{
"href": "https://a.espncdn.com/i/venues/nba/day/1830.jpg",
"width": 2000,
"height": 1125,
"alt": "",
"rel": [
"full",
"day"
]
}
]
},
"attendance": 19763,
"officials": [
{
"fullName": "Joe Forte",
"displayName": "Joe Forte",
"position": {
"name": "Referee",
"displayName": "Referee",
"id": "40"
},
"order": 1
},
{
"fullName": "Ken Mauer",
"displayName": "Ken Mauer",
"position": {
"name": "Referee",
"displayName": "Referee",
"id": "40"
},
"order": 2
},
{
"fullName": "George Toliver",
"displayName": "George Toliver",
"position": {
"name": "Referee",
"displayName": "Referee",
"id": "40"
},
"order": 3
}
]
},
"leaders": [
{
"team": {
"id": "18",
"uid": "s:40~l:46~t:18",
"displayName": "New York Knicks",
"abbreviation": "NY",
"links": [
{
"href": "https://www.espn.com/nba/team/_/name/ny/new-york-knicks",
"text": "Clubhouse"
},
{
"href": "https://www.espn.com/nba/team/schedule/_/name/ny",
"text": "Schedule"
}
],
"logo": "https://a.espncdn.com/i/teamlogos/nba/500/ny.png",
"logos": [
{
"href": "https://a.espncdn.com/i/teamlogos/nba/500/ny.png",
"width": 500,
"height": 500,
"alt": "",
"rel": [
"full",
"default"
],
"lastUpdated": "2018-06-05T12:08Z"
},
{
"href": "https://a.espncdn.com/i/teamlogos/nba/500-dark/ny.png",
"width": 500,
"height": 500,
"alt": "",
"rel": [
"full",
"dark"
],
"lastUpdated": "2018-06-05T12:08Z"
}
]
},
"leaders": [
{
"name": "points",
"displayName": "Points",
"leaders": [
{
"displayValue": "44",
"athlete": {
"id": "349",
"uid": "s:40~l:46~a:349",
"guid": "5aee772a22bec1d9016eb6196d02ee3a",
"lastName": "Houston",
"fullName": "Allan Houston",
"displayName": "Allan Houston",
"shortName": "A. Houston",
"links": [
{
"rel": [
"playercard",
"desktop",
"athlete"
],
"href": "https://www.espn.com/nba/player/_/id/349/allan-houston",
"text": "Player Card"
}
],
"jersey": "7",
"position": {
"abbreviation": "SG"
},
"team": {
"$ref": "http://sports.core.api.espn.pvt/v2/sports/basketball/leagues/nba/seasons/2002/teams/18?lang=en&region=us"
}
},
"statistics": [
{
"name": "points",
"displayName": "Points",
"shortDisplayName": "PTS",
"description": "The number of points scored.",
"abbreviation": "PTS",
"value": 44.0,
"displayValue": "44"
},
{
"name": "fieldGoals",
"displayName": "Field Goals",
"shortDisplayName": "FG",
"description": "Field Goal makes and attempts.",
"abbreviation": "FG",
"value": 0.448276,
"displayValue": "13/29"
},
{
"name": "freeThrows",
"displayName": "Free Throws",
"shortDisplayName": "FT",
"description": "Free Throw makes and attempts.",
"abbreviation": "FT",
"value": 0.933333,
"displayValue": "14/15"
}
]
}
]
},
{
"name": "assists",
"displayName": "Assists",
"leaders": [
{
"displayValue": "11",
"athlete": {
"id": "370",
"uid": "s:40~l:46~a:370",
"guid": "a05499ab1061fbdd2af7d848546d6678",
"lastName": "Jackson",
"fullName": "Mark Jackson",
"displayName": "Mark Jackson",
"shortName": "M. Jackson",
"links": [
{
"rel": [
"playercard",
"desktop",
"athlete"
],
"href": "https://www.espn.com/nba/player/_/id/370/mark-jackson",
"text": "Player Card"
}
],
"jersey": "31",
"position": {
"abbreviation": "PG"
},
"team": {
"$ref": "http://sports.core.api.espn.pvt/v2/sports/basketball/leagues/nba/seasons/2002/teams/18?lang=en&region=us"
}
},
"statistics": [
{
"name": "assists",
"displayName": "Assists",
"shortDisplayName": "AST",
"description": "The number of times a player who passes the ball to a teammate in a way that leads to a score by field goal, meaning that he or she was \"assisting\" in the basket. There is some judgment involved in deciding whether a passer should be credited with an assist.",
"abbreviation": "AST",
"value": 11.0,
"displayValue": "11"
},
{
"name": "turnovers",
"displayName": "Turnovers",
"shortDisplayName": "TO",
"description": "The number of times a player loses possession to the other team.",
"abbreviation": "TO",
"value": 1.0,
"displayValue": "1"
},
{
"name": "minutes",
"displayName": "Minutes",
"shortDisplayName": "MIN",
"description": "The total number of minutes played.",
"abbreviation": "MIN",
"value": 35.0,
"displayValue": "35"
},
{
"name": "assistTurnoverRatio",
"displayName": "Assist To Turnover Ratio",
"shortDisplayName": "AST/TO",
"description": "The average number of assists a player or team records per turnover",
"abbreviation": "AST/TO",
"value": 11.0,
"displayValue": "11.0"
}
]
}
]
},
{
"name": "rebounds",
"displayName": "Rebounds",
"leaders": [
{
"displayValue": "9",
"athlete": {
"id": "846",
"uid": "s:40~l:46~a:846",
"guid": "39d10dd4c0fcd57ac50a5631e2dbabe0",
"lastName": "Thomas",
"fullName": "Kurt Thomas",
"displayName": "Kurt Thomas",
"shortName": "K. Thomas",
"links": [
{
"rel": [
"playercard",
"desktop",
"athlete"
],
"href": "https://www.espn.com/nba/player/_/id/846/kurt-thomas",
"text": "Player Card"
}
],
"headshot": {
"href": "https://a.espncdn.com/i/headshots/nba/players/full/846.png",
"alt": "Kurt Thomas"
},
"jersey": "40",
"position": {
"abbreviation": "PF"
},
"team": {
"$ref": "http://sports.core.api.espn.pvt/v2/sports/basketball/leagues/nba/seasons/2002/teams/18?lang=en&region=us"
}
},
"statistics": [
{
"name": "rebounds",
"displayName": "Rebounds",
"shortDisplayName": "REB",
"description": "The total number of rebounds (offensive and defensive).",
"abbreviation": "REB",
"value": 9.0,
"displayValue": "9"
},
{
"name": "defensiveRebounds",
"displayName": "Defensive Rebounds",
"shortDisplayName": "DREB",
"description": "The number of times when the defense obtains the possession of the ball after a missed shot by the offense.",
"abbreviation": "DR",
"value": 7.0,
"displayValue": "7"
},
{
"name": "offensiveRebounds",
"displayName": "Offensive Rebounds",
"shortDisplayName": "OREB",
"description": "The number of times when the offense obtains the possession of the ball after a missed shot.",
"abbreviation": "OR",
"value": 2.0,
"displayValue": "2"
}
]
}
]
}
]
},
{
"team": {
"id": "15",
"uid": "s:40~l:46~t:15",
"displayName": "Milwaukee Bucks",
"abbreviation": "MIL",
"links": [
{
"href": "https://www.espn.com/nba/team/_/name/mil/milwaukee-bucks",
"text": "Clubhouse"
},
{
"href": "https://www.espn.com/nba/team/schedule/_/name/mil",
"text": "Schedule"
}
],
"logo": "https://a.espncdn.com/i/teamlogos/nba/500/mil.png",
"logos": [
{
"href": "https://a.espncdn.com/i/teamlogos/nba/500/mil.png",
"width": 500,
"height": 500,
"alt": "",
"rel": [
"full",
"default"
],
"lastUpdated": "2018-06-05T12:08Z"
},
{
"href": "https://a.espncdn.com/i/teamlogos/nba/500-dark/mil.png",
"width": 500,
"height": 500,
"alt": "",
"rel": [
"full",
"dark"
],
"lastUpdated": "2018-06-05T12:08Z"
}
]
},
"leaders": [
{
"name": "points",
"displayName": "Points",
"leaders": [
{
"displayValue": "37",
"athlete": {
"id": "9",
"uid": "s:40~l:46~a:9",
"guid": "f0d2ffd468663cea4918f1fd2f8b2ced",
"lastName": "Allen",
"fullName": "Ray Allen",
"displayName": "Ray Allen",
"shortName": "R. Allen",
"links": [
{
"rel": [
"playercard",
"desktop",
"athlete"
],
"href": "https://www.espn.com/nba/player/_/id/9/ray-allen",
"text": "Player Card"
}
],
"headshot": {
"href": "https://a.espncdn.com/i/headshots/nba/players/full/9.png",
"alt": "Ray Allen"
},
"jersey": "34",
"position": {
"abbreviation": "SG"
},
"team": {
"$ref": "http://sports.core.api.espn.pvt/v2/sports/basketball/leagues/nba/seasons/2002/teams/15?lang=en&region=us"
}
},
"statistics": [
{
"name": "points",
"displayName": "Points",
"shortDisplayName": "PTS",
"description": "The number of points scored.",
"abbreviation": "PTS",
"value": 37.0,
"displayValue": "37"
},
{
"name": "fieldGoals",
"displayName": "Field Goals",
"shortDisplayName": "FG",
"description": "Field Goal makes and attempts.",
"abbreviation": "FG",
"value": 0.588235,
"displayValue": "10/17"
},
{
"name": "freeThrows",
"displayName": "Free Throws",
"shortDisplayName": "FT",
"description": "Free Throw makes and attempts.",
"abbreviation": "FT",
"value": 0.818182,
"displayValue": "9/11"
}
]
}
]
},
{
"name": "assists",
"displayName": "Assists",
"leaders": [
{
"displayValue": "5",
"athlete": {
"id": "138",
"uid": "s:40~l:46~a:138",
"guid": "472fc4e6384dee34f66c5aba2b947dd9",
"lastName": "Cassell",
"fullName": "Sam Cassell",
"displayName": "Sam Cassell",
"shortName": "S. Cassell",
"links": [
{
"rel": [
"playercard",
"desktop",
"athlete"
],
"href": "https://www.espn.com/nba/player/_/id/138/sam-cassell",
"text": "Player Card"
}
],
"position": {
"abbreviation": "PG"
},
"team": {
"$ref": "http://sports.core.api.espn.pvt/v2/sports/basketball/leagues/nba/seasons/2002/teams/15?lang=en&region=us"
}
},
"statistics": [
{
"name": "assists",
"displayName": "Assists",
"shortDisplayName": "AST",
"description": "The number of times a player who passes the ball to a teammate in a way that leads to a score by field goal, meaning that he or she was \"assisting\" in the basket. There is some judgment involved in deciding whether a passer should be credited with an assist.",
"abbreviation": "AST",
"value": 5.0,
"displayValue": "5"
},
{
"name": "turnovers",
"displayName": "Turnovers",
"shortDisplayName": "TO",
"description": "The number of times a player loses possession to the other team.",
"abbreviation": "TO",
"value": 4.0,
"displayValue": "4"
},
{
"name": "minutes",
"displayName": "Minutes",
"shortDisplayName": "MIN",
"description": "The total number of minutes played.",
"abbreviation": "MIN",
"value": 40.0,
"displayValue": "40"
},
{
"name": "assistTurnoverRatio",
"displayName": "Assist To Turnover Ratio",
"shortDisplayName": "AST/TO",
"description": "The average number of assists a player or team records per turnover",
"abbreviation": "AST/TO",
"value": 1.25,
"displayValue": "1.3"
}
]
}
]
},
{
"name": "rebounds",
"displayName": "Rebounds",
"leaders": [
{
"displayValue": "9",
"athlete": {
"id": "517",
"uid": "s:40~l:46~a:517",
"guid": "1a1f5b295e16504c56e5c0569ba39d63",
"lastName": "Mason",
"fullName": "Anthony Mason",
"displayName": "Anthony Mason",
"shortName": "A. Mason",
"links": [
{
"rel": [
"playercard",
"desktop",
"athlete"
],
"href": "https://www.espn.com/nba/player/_/id/517/anthony-mason",
"text": "Player Card"
}
],
"jersey": "99",
"position": {
"abbreviation": "F"
},
"team": {
"$ref": "http://sports.core.api.espn.pvt/v2/sports/basketball/leagues/nba/seasons/2002/teams/15?lang=en&region=us"
}
},
"statistics": [
{
"name": "rebounds",
"displayName": "Rebounds",
"shortDisplayName": "REB",
"description": "The total number of rebounds (offensive and defensive).",
"abbreviation": "REB",
"value": 9.0,
"displayValue": "9"
},
{
"name": "defensiveRebounds",
"displayName": "Defensive Rebounds",
"shortDisplayName": "DREB",
"description": "The number of times when the defense obtains the possession of the ball after a missed shot by the offense.",
"abbreviation": "DR",
"value": 7.0,
"displayValue": "7"
},
{
"name": "offensiveRebounds",
"displayName": "Offensive Rebounds",
"shortDisplayName": "OREB",
"description": "The number of times when the offense obtains the possession of the ball after a missed shot.",
"abbreviation": "OR",
"value": 2.0,
"displayValue": "2"
}
]
}
]
}
]
}
],
"seasonseries": [
{
"type": "season",
"title": "Regular Season Series",
"description": "Regular Season Series",
"summary": "Series tied 1-1",
"completed": false,
"totalCompetitions": 4,
"events": [
{
"id": "211204015",
"uid": "s:40~l:46~e:211204015~c:211204015",
"date": "2001-12-05T00:00:00Z",
"timeValid": true,
"status": "post",
"statusType": {
"id": "3",
"name": "STATUS_FINAL",
"state": "post",
"completed": true,
"description": "Final",
"detail": "Final",
"shortDetail": "Final"
},
"competitors": [
{
"homeAway": "home",
"winner": false,
"team": {
"id": "15",
"uid": "s:40~l:46~t:15",
"displayName": "Milwaukee Bucks",
"abbreviation": "MIL",
"links": [
{
"href": "https://www.espn.com/nba/team/_/name/mil/milwaukee-bucks",
"text": "Clubhouse"
},
{
"href": "https://www.espn.com/nba/team/schedule/_/name/mil",
"text": "Schedule"
}
],
"logo": "https://a.espncdn.com/i/teamlogos/nba/500/mil.png",
"logos": [
{
"href": "https://a.espncdn.com/i/teamlogos/nba/500/mil.png",
"width": 500,
"height": 500,
"alt": "",
"rel": [
"full",
"default"
],
"lastUpdated": "2018-06-05T12:08Z"
},
{
"href": "https://a.espncdn.com/i/teamlogos/nba/500-dark/mil.png",
"width": 500,
"height": 500,
"alt": "",
"rel": [
"full",
"dark"
],
"lastUpdated": "2018-06-05T12:08Z"
}
]
},
"score": "71"
},
{
"homeAway": "away",
"winner": true,
"team": {
"id": "18",
"uid": "s:40~l:46~t:18",
"displayName": "New York Knicks",
"abbreviation": "NY",
"links": [
{
"href": "https://www.espn.com/nba/team/_/name/ny/new-york-knicks",
"text": "Clubhouse"
},
{
"href": "https://www.espn.com/nba/team/schedule/_/name/ny",
"text": "Schedule"
}
],
"logo": "https://a.espncdn.com/i/teamlogos/nba/500/ny.png",
"logos": [
{
"href": "https://a.espncdn.com/i/teamlogos/nba/500/ny.png",
"width": 500,
"height": 500,
"alt": "",
"rel": [
"full",
"default"
],
"lastUpdated": "2018-06-05T12:08Z"
},
{
"href": "https://a.espncdn.com/i/teamlogos/nba/500-dark/ny.png",
"width": 500,
"height": 500,
"alt": "",
"rel": [
"full",
"dark"
],
"lastUpdated": "2018-06-05T12:08Z"
}
]
},
"score": "85"
}
],
"links": [
{
"language": "en-US",
"rel": [
"summary",
"desktop",
"event"
],
"href": "https://www.espn.com/nba/game/_/gameId/211204015",
"text": "Gamecast",
"shortText": "Summary",
"isExternal": false,
"isPremium": false
},
{
"language": "en-US",
"rel": [
"summary",
"sportscenter",
"app",
"event"
],
"href": "sportscenter://x-callback-url/showGame?sportName=basketball&leagueAbbrev=nba&gameId=211204015",
"text": "Gamecast",
"shortText": "Summary",
"isExternal": false,
"isPremium": false
}
]
},
{
"id": "220112018",
"uid": "s:40~l:46~e:220112018~c:220112018",
"date": "2002-01-13T00:30:00Z",
"timeValid": true,
"status": "post",
"statusType": {
"id": "3",
"name": "STATUS_FINAL",
"state": "post",
"completed": true,
"description": "Final",
"detail": "Final",
"shortDetail": "Final"
},
"competitors": [
{
"homeAway": "home",
"winner": false,
"team": {
"id": "18",
"uid": "s:40~l:46~t:18",
"displayName": "New York Knicks",
"abbreviation": "NY",
"links": [
{
"href": "https://www.espn.com/nba/team/_/name/ny/new-york-knicks",
"text": "Clubhouse"
},
{
"href": "https://www.espn.com/nba/team/schedule/_/name/ny",
"text": "Schedule"
}
],
"logo": "https://a.espncdn.com/i/teamlogos/nba/500/ny.png",
"logos": [
{
"href": "https://a.espncdn.com/i/teamlogos/nba/500/ny.png",
"width": 500,
"height": 500,
"alt": "",
"rel": [
"full",
"default"
],
"lastUpdated": "2018-06-05T12:08Z"
},
{
"href": "https://a.espncdn.com/i/teamlogos/nba/500-dark/ny.png",
"width": 500,
"height": 500,
"alt": "",
"rel": [
"full",
"dark"
],
"lastUpdated": "2018-06-05T12:08Z"
}
]
},
"score": "97"
},
{
"homeAway": "away",
"winner": true,
"team": {
"id": "15",
"uid": "s:40~l:46~t:15",
"displayName": "Milwaukee Bucks",
"abbreviation": "MIL",
"links": [
{
"href": "https://www.espn.com/nba/team/_/name/mil/milwaukee-bucks",
"text": "Clubhouse"
},
{
"href": "https://www.espn.com/nba/team/schedule/_/name/mil",
"text": "Schedule"
}
],
"logo": "https://a.espncdn.com/i/teamlogos/nba/500/mil.png",
"logos": [
{
"href": "https://a.espncdn.com/i/teamlogos/nba/500/mil.png",
"width": 500,
"height": 500,
"alt": "",
"rel": [
"full",
"default"
],
"lastUpdated": "2018-06-05T12:08Z"
},
{
"href": "https://a.espncdn.com/i/teamlogos/nba/500-dark/mil.png",
"width": 500,
"height": 500,
"alt": "",
"rel": [
"full",
"dark"
],
"lastUpdated": "2018-06-05T12:08Z"
}
]
},
"score": "102"
}
],
"links": [
{
"language": "en-US",
"rel": [
"summary",
"desktop",
"event"
],
"href": "https://www.espn.com/nba/game/_/gameId/220112018",
"text": "Gamecast",
"shortText": "Summary",
"isExternal": false,
"isPremium": false
},
{
"language": "en-US",
"rel": [
"summary",
"sportscenter",
"app",
"event"
],
"href": "sportscenter://x-callback-url/showGame?sportName=basketball&leagueAbbrev=nba&gameId=220112018",
"text": "Gamecast",
"shortText": "Summary",
"isExternal": false,
"isPremium": false
}
]
},
{
"id": "220126015",
"uid": "s:40~l:46~e:220126015~c:220126015",
"date": "2002-01-26T19:00:00Z",
"timeValid": true,
"status": "post",
"statusType": {
"id": "3",
"name": "STATUS_FINAL",
"state": "post",
"completed": true,
"description": "Final",
"detail": "Final",
"shortDetail": "Final"
},
"competitors": [
{
"homeAway": "home",
"winner": false,
"team": {
"id": "15",
"uid": "s:40~l:46~t:15",
"displayName": "Milwaukee Bucks",
"abbreviation": "MIL",
"links": [
{
"href": "https://www.espn.com/nba/team/_/name/mil/milwaukee-bucks",
"text": "Clubhouse"
},
{
"href": "https://www.espn.com/nba/team/schedule/_/name/mil",
"text": "Schedule"
}
],
"logo": "https://a.espncdn.com/i/teamlogos/nba/500/mil.png",
"logos": [
{
"href": "https://a.espncdn.com/i/teamlogos/nba/500/mil.png",
"width": 500,
"height": 500,
"alt": "",
"rel": [
"full",
"default"
],
"lastUpdated": "2018-06-05T12:08Z"
},
{
"href": "https://a.espncdn.com/i/teamlogos/nba/500-dark/mil.png",
"width": 500,
"height": 500,
"alt": "",
"rel": [
"full",
"dark"
],
"lastUpdated": "2018-06-05T12:08Z"
}
]
},
"score": "127"
},
{
"homeAway": "away",
"winner": true,
"team": {
"id": "18",
"uid": "s:40~l:46~t:18",
"displayName": "New York Knicks",
"abbreviation": "NY",
"links": [
{
"href": "https://www.espn.com/nba/team/_/name/ny/new-york-knicks",
"text": "Clubhouse"
},
{
"href": "https://www.espn.com/nba/team/schedule/_/name/ny",
"text": "Schedule"
}
],
"logo": "https://a.espncdn.com/i/teamlogos/nba/500/ny.png",
"logos": [
{
"href": "https://a.espncdn.com/i/teamlogos/nba/500/ny.png",
"width": 500,
"height": 500,
"alt": "",
"rel": [
"full",
"default"
],
"lastUpdated": "2018-06-05T12:08Z"
},
{
"href": "https://a.espncdn.com/i/teamlogos/nba/500-dark/ny.png",
"width": 500,
"height": 500,
"alt": "",
"rel": [
"full",
"dark"
],
"lastUpdated": "2018-06-05T12:08Z"
}
]
},
"score": "129"
}
],
"links": [
{
"language": "en-US",
"rel": [
"summary",
"desktop",
"event"
],
"href": "https://www.espn.com/nba/game/_/gameId/220126015",
"text": "Gamecast",
"shortText": "Summary",
"isExternal": false,
"isPremium": false
},
{
"language": "en-US",
"rel": [
"summary",
"sportscenter",
"app",
"event"
],
"href": "sportscenter://x-callback-url/showGame?sportName=basketball&leagueAbbrev=nba&gameId=220126015",
"text": "Gamecast",
"shortText": "Summary",
"isExternal": false,
"isPremium": false
}
]
},
{
"id": "220305018",
"uid": "s:40~l:46~e:220305018~c:220305018",
"date": "2002-03-06T00:30:00Z",
"timeValid": true,
"status": "post",
"statusType": {
"id": "3",
"name": "STATUS_FINAL",
"state": "post",
"completed": true,
"description": "Final",
"detail": "Final",
"shortDetail": "Final"
},
"competitors": [
{
"homeAway": "home",
"winner": true,
"team": {
"id": "18",
"uid": "s:40~l:46~t:18",
"displayName": "New York Knicks",
"abbreviation": "NY",
"links": [
{
"href": "https://www.espn.com/nba/team/_/name/ny/new-york-knicks",
"text": "Clubhouse"
},
{
"href": "https://www.espn.com/nba/team/schedule/_/name/ny",
"text": "Schedule"
}
],
"logo": "https://a.espncdn.com/i/teamlogos/nba/500/ny.png",
"logos": [
{
"href": "https://a.espncdn.com/i/teamlogos/nba/500/ny.png",
"width": 500,
"height": 500,
"alt": "",
"rel": [
"full",
"default"
],
"lastUpdated": "2018-06-05T12:08Z"
},
{
"href": "https://a.espncdn.com/i/teamlogos/nba/500-dark/ny.png",
"width": 500,
"height": 500,
"alt": "",
"rel": [
"full",
"dark"
],
"lastUpdated": "2018-06-05T12:08Z"
}
]
},
"score": "102"
},
{
"homeAway": "away",
"winner": false,
"team": {
"id": "15",
"uid": "s:40~l:46~t:15",
"displayName": "Milwaukee Bucks",
"abbreviation": "MIL",
"links": [
{
"href": "https://www.espn.com/nba/team/_/name/mil/milwaukee-bucks",
"text": "Clubhouse"
},
{
"href": "https://www.espn.com/nba/team/schedule/_/name/mil",
"text": "Schedule"
}
],
"logo": "https://a.espncdn.com/i/teamlogos/nba/500/mil.png",
"logos": [
{
"href": "https://a.espncdn.com/i/teamlogos/nba/500/mil.png",
"width": 500,
"height": 500,
"alt": "",
"rel": [
"full",
"default"
],
"lastUpdated": "2018-06-05T12:08Z"
},
{
"href": "https://a.espncdn.com/i/teamlogos/nba/500-dark/mil.png",
"width": 500,
"height": 500,
"alt": "",
"rel": [
"full",
"dark"
],
"lastUpdated": "2018-06-05T12:08Z"
}
]
},
"score": "89"
}
],
"links": [
{
"language": "en-US",
"rel": [
"summary",
"desktop",
"event"
],
"href": "https://www.espn.com/nba/game/_/gameId/220305018",
"text": "Gamecast",
"shortText": "Summary",
"isExternal": false,
"isPremium": false
},
{
"language": "en-US",
"rel": [
"summary",
"sportscenter",
"app",
"event"
],
"href": "sportscenter://x-callback-url/showGame?sportName=basketball&leagueAbbrev=nba&gameId=220305018",
"text": "Gamecast",
"shortText": "Summary",
"isExternal": false,
"isPremium": false
}
]
}
]
}
],
"broadcasts": [],
"predictor": {},
"pickcenter": [],
"againstTheSpread": [
{
"team": {
"id": "15",
"uid": "s:40~l:46~t:15",
"displayName": "Milwaukee Bucks",
"abbreviation": "MIL",
"links": [
{
"href": "https://www.espn.com/nba/team/_/name/mil/milwaukee-bucks",
"text": "Clubhouse"
},
{
"href": "https://www.espn.com/nba/team/schedule/_/name/mil",
"text": "Schedule"
}
],
"logo": "https://a.espncdn.com/i/teamlogos/nba/500/mil.png",
"logos": [
{
"href": "https://a.espncdn.com/i/teamlogos/nba/500/mil.png",
"width": 500,
"height": 500,
"alt": "",
"rel": [
"full",
"default"
],
"lastUpdated": "2018-06-05T12:08Z"
},
{
"href": "https://a.espncdn.com/i/teamlogos/nba/500-dark/mil.png",
"width": 500,
"height": 500,
"alt": "",
"rel": [
"full",
"dark"
],
"lastUpdated": "2018-06-05T12:08Z"
}
]
},
"records": []
},
{
"team": {
"id": "18",
"uid": "s:40~l:46~t:18",
"displayName": "New York Knicks",
"abbreviation": "NY",
"links": [
{
"href": "https://www.espn.com/nba/team/_/name/ny/new-york-knicks",
"text": "Clubhouse"
},
{
"href": "https://www.espn.com/nba/team/schedule/_/name/ny",
"text": "Schedule"
}
],
"logo": "https://a.espncdn.com/i/teamlogos/nba/500/ny.png",
"logos": [
{
"href": "https://a.espncdn.com/i/teamlogos/nba/500/ny.png",
"width": 500,
"height": 500,
"alt": "",
"rel": [
"full",
"default"
],
"lastUpdated": "2018-06-05T12:08Z"
},
{
"href": "https://a.espncdn.com/i/teamlogos/nba/500-dark/ny.png",
"width": 500,
"height": 500,
"alt": "",
"rel": [
"full",
"dark"
],
"lastUpdated": "2018-06-05T12:08Z"
}
]
},
"records": []
}
],
"odds": [],
"winprobability": [],
"header": {
"id": "220112018",
"uid": "s:40~l:46~e:220112018",
"season": {
"year": 2002,
"type": 2
},
"timeValid": true,
"competitions": [
{
"id": "220112018",
"uid": "s:40~l:46~e:220112018~c:220112018",
"date": "2002-01-13T00:30Z",
"neutralSite": false,
"conferenceCompetition": false,
"boxscoreAvailable": true,
"commentaryAvailable": false,
"liveAvailable": false,
"shotChartAvailable": false,
"timeoutsAvailable": true,
"possessionArrowAvailable": false,
"onWatchESPN": false,
"recent": false,
"boxscoreSource": "full",
"playByPlaySource": "none",
"competitors": [
{
"id": "18",
"uid": "s:40~l:46~t:18",
"order": 0,
"homeAway": "home",
"winner": false,
"team": {
"id": "18",
"uid": "s:40~l:46~t:18",
"location": "New York",
"name": "Knicks",
"abbreviation": "NY",
"displayName": "New York Knicks",
"color": "225EA8",
"alternateColor": "f58426",
"logos": [
{
"href": "https://a.espncdn.com/i/teamlogos/nba/500/ny.png",
"width": 500,
"height": 500,
"alt": "",
"rel": [
"full",
"default"
],
"lastUpdated": "2018-06-05T12:08Z"
},
{
"href": "https://a.espncdn.com/i/teamlogos/nba/500-dark/ny.png",
"width": 500,
"height": 500,
"alt": "",
"rel": [
"full",
"dark"
],
"lastUpdated": "2018-06-05T12:08Z"
},
{
"href": "https://a.espncdn.com/i/teamlogos/nba/500/scoreboard/ny.png",
"width": 500,
"height": 500,
"alt": "",
"rel": [
"full",
"scoreboard"
],
"lastUpdated": "2018-06-05T12:08Z"
},
{
"href": "https://a.espncdn.com/i/teamlogos/nba/500-dark/scoreboard/ny.png",
"width": 500,
"height": 500,
"alt": "",
"rel": [
"full",
"scoreboard",
"dark"
],
"lastUpdated": "2018-06-05T12:08Z"
}
],
"links": [
{
"rel": [
"clubhouse",
"desktop",
"team"
],
"href": "https://www.espn.com/nba/team/_/name/ny/new-york-knicks",
"text": "Clubhouse"
}
]
},
"score": "97",
"linescores": [
{
"displayValue": "12"
},
{
"displayValue": "22"
},
{
"displayValue": "30"
},
{
"displayValue": "33"
}
],
"record": [
{
"type": "total",
"summary": "14-22",
"displayValue": "14-22"
},
{
"type": "home",
"summary": "10-9",
"displayValue": "10-9"
},
{
"type": "vsconf",
"summary": "0-0",
"displayValue": "0-0"
}
],
"possession": false
},
{
"id": "15",
"uid": "s:40~l:46~t:15",
"order": 1,
"homeAway": "away",
"winner": true,
"team": {
"id": "15",
"uid": "s:40~l:46~t:15",
"location": "Milwaukee",
"name": "Bucks",
"abbreviation": "MIL",
"displayName": "Milwaukee Bucks",
"color": "003813",
"alternateColor": "f0ebd2",
"logos": [
{
"href": "https://a.espncdn.com/i/teamlogos/nba/500/mil.png",
"width": 500,
"height": 500,
"alt": "",
"rel": [
"full",
"default"
],
"lastUpdated": "2018-06-05T12:08Z"
},
{
"href": "https://a.espncdn.com/i/teamlogos/nba/500-dark/mil.png",
"width": 500,
"height": 500,
"alt": "",
"rel": [
"full",
"dark"
],
"lastUpdated": "2018-06-05T12:08Z"
},
{
"href": "https://a.espncdn.com/i/teamlogos/nba/500/scoreboard/mil.png",
"width": 500,
"height": 500,
"alt": "",
"rel": [
"full",
"scoreboard"
],
"lastUpdated": "2018-06-05T12:08Z"
},
{
"href": "https://a.espncdn.com/i/teamlogos/nba/500-dark/scoreboard/mil.png",
"width": 500,
"height": 500,
"alt": "",
"rel": [
"full",
"scoreboard",
"dark"
],
"lastUpdated": "2018-06-05T12:08Z"
}
],
"links": [
{
"rel": [
"clubhouse",
"desktop",
"team"
],
"href": "https://www.espn.com/nba/team/_/name/mil/milwaukee-bucks",
"text": "Clubhouse"
}
]
},
"score": "102",
"linescores": [
{
"displayValue": "26"
},
{
"displayValue": "23"
},
{
"displayValue": "25"
},
{
"displayValue": "28"
}
],
"record": [
{
"type": "total",
"summary": "21-13",
"displayValue": "21-13"
},
{
"type": "road",
"summary": "10-11",
"displayValue": "10-11"
},
{
"type": "vsconf",
"summary": "0-0",
"displayValue": "0-0"
}
],
"possession": false
}
],
"status": {
"type": {
"id": "3",
"name": "STATUS_FINAL",
"state": "post",
"completed": true,
"description": "Final",
"detail": "Final",
"shortDetail": "Final"
}
},
"broadcasts": [
{
"type": {
"id": "1",
"shortName": "TV"
},
"market": {
"id": "2",
"type": "Home"
},
"media": {
"shortName": "MSG"
},
"lang": "en",
"region": "us"
}
],
"series": [
{
"type": "season",
"title": "Regular Season Series",
"description": "Regular Season Series",
"summary": "Series tied 1-1",
"completed": false,
"totalCompetitions": 4,
"competitors": [
{
"id": "18",
"uid": "s:40~l:46~t:18",
"wins": 1,
"ties": 0,
"team": {
"$ref": "http://sports.core.api.espn.pvt/v2/sports/basketball/leagues/nba/seasons/2002/teams/18?lang=en&region=us"
}
},
{
"id": "15",
"uid": "s:40~l:46~t:15",
"wins": 1,
"ties": 0,
"team": {
"$ref": "http://sports.core.api.espn.pvt/v2/sports/basketball/leagues/nba/seasons/2002/teams/15?lang=en&region=us"
}
}
],
"events": [
{
"$ref": "http://sports.core.api.espn.pvt/v2/sports/basketball/leagues/nba/events/211204015?lang=en&region=us",
"id": "211204015"
},
{
"$ref": "http://sports.core.api.espn.pvt/v2/sports/basketball/leagues/nba/events/220112018?lang=en&region=us",
"id": "220112018"
},
{
"$ref": "http://sports.core.api.espn.pvt/v2/sports/basketball/leagues/nba/events/220126015?lang=en&region=us",
"id": "220126015"
},
{
"$ref": "http://sports.core.api.espn.pvt/v2/sports/basketball/leagues/nba/events/220305018?lang=en&region=us",
"id": "220305018"
}
]
}
]
}
],
"links": [
{
"rel": [
"summary",
"desktop",
"event"
],
"href": "https://www.espn.com/nba/game/_/gameId/220112018",
"text": "Gamecast",
"shortText": "Summary",
"isExternal": false,
"isPremium": false
},
{
"rel": [
"boxscore",
"desktop",
"event"
],
"href": "https://www.espn.com/nba/boxscore/_/gameId/220112018",
"text": "Box Score",
"shortText": "Box Score",
"isExternal": false,
"isPremium": false
},
{
"rel": [
"teamstats",
"desktop",
"event"
],
"href": "https://www.espn.com/nba/matchup?gameId=220112018",
"text": "Team Stats",
"shortText": "Team Stats",
"isExternal": false,
"isPremium": false
}
],
"week": 11,
"league": {
"id": "46",
"uid": "s:40~l:46",
"name": "National Basketball Association",
"abbreviation": "NBA",
"slug": "nba",
"isTournament": false,
"links": [
{
"rel": [
"index",
"desktop",
"league"
],
"href": "https://www.espn.com/nba/",
"text": "Index"
},
{
"rel": [
"index",
"sportscenter",
"app",
"league"
],
"href": "sportscenter://x-callback-url/showClubhouse?uid=s:40~l:46",
"text": "Index"
},
{
"rel": [
"schedule",
"desktop",
"league"
],
"href": "https://www.espn.com/nba/schedule",
"text": "Schedule"
},
{
"rel": [
"schedule",
"sportscenter",
"app",
"league"
],
"href": "sportscenter://x-callback-url/showClubhouse?uid=s:40~l:46&section=scores",
"text": "Schedule"
},
{
"rel": [
"standings",
"desktop",
"league"
],
"href": "http://www.espn.com/nba/standings",
"text": "Standings"
},
{
"rel": [
"standings",
"sportscenter",
"app",
"league"
],
"href": "sportscenter://x-callback-url/showClubhouse?uid=s:40~l:46&section=standings",
"text": "Standings"
},
{
"rel": [
"rankings",
"desktop",
"league"
],
"href": "https://www.espn.com/nba/rankings",
"text": "Rankings"
},
{
"rel": [
"scores",
"desktop",
"league"
],
"href": "https://www.espn.com/nba/scoreboard",
"text": "Scores"
},
{
"rel": [
"scores",
"sportscenter",
"app",
"league"
],
"href": "sportscenter://x-callback-url/showClubhouse?uid=s:40~l:46&section=scores",
"text": "Scores"
},
{
"rel": [
"stats",
"desktop",
"league"
],
"href": "http://www.espn.com/nba/stats",
"text": "Stats"
},
{
"rel": [
"teams",
"desktop",
"league"
],
"href": "http://www.espn.com/nba/teams",
"text": "Teams"
},
{
"rel": [
"athletes",
"desktop",
"league"
],
"href": "http://www.espn.com/nba/players",
"text": "Players"
},
{
"rel": [
"injuries",
"desktop",
"league"
],
"href": "https://www.espn.com/nba/injuries",
"text": "Injuries"
}
]
}
},
"plays": [],
"article": {},
"videos": [],
"standings": {
"fullViewLink": {
"text": "Full Standings",
"href": "http://www.espn.com/nba/standings"
},
"groups": [
{
"standings": {
"entries": [
{
"team": "Milwaukee",
"link": "https://www.espn.com/nba/team/_/name/mil/milwaukee-bucks",
"id": "15",
"uid": "s:40~l:46~t:15",
"stats": [
{
"name": "gamesBehind",
"displayName": "Games Back",
"shortDisplayName": "GB",
"description": "Games Back",
"abbreviation": "GB",
"type": "gamesbehind",
"value": 0.0,
"displayValue": "-"
},
{
"name": "losses",
"displayName": "Losses",
"shortDisplayName": "L",
"description": "Losses",
"abbreviation": "L",
"type": "losses",
"value": 22.0,
"displayValue": "22"
},
{
"name": "streak",
"displayName": "Streak",
"shortDisplayName": "STRK",
"description": "Current Streak",
"abbreviation": "STRK",
"type": "streak",
"value": 3.0,
"displayValue": "W3"
},
{
"name": "winPercent",
"displayName": "Win Percentage",
"shortDisplayName": "PCT",
"description": "Winning Percentage",
"abbreviation": "PCT",
"type": "winpercent",
"value": 0.725,
"displayValue": ".725"
},
{
"name": "wins",
"displayName": "Wins",
"shortDisplayName": "W",
"description": "Wins",
"abbreviation": "W",
"type": "wins",
"value": 58.0,
"displayValue": "58"
}
],
"logo": [
{
"href": "https://a.espncdn.com/i/teamlogos/nba/500/scoreboard/mil.png",
"width": 500,
"height": 500,
"alt": "",
"rel": [
"full",
"scoreboard"
],
"lastUpdated": "2018-06-05T12:08Z"
},
{
"href": "https://a.espncdn.com/i/teamlogos/nba/500-dark/scoreboard/mil.png",
"width": 500,
"height": 500,
"alt": "",
"rel": [
"full",
"scoreboard",
"dark"
],
"lastUpdated": "2018-06-05T12:08Z"
}
]
},
{
"team": "Cleveland",
"link": "https://www.espn.com/nba/team/_/name/cle/cleveland-cavaliers",
"id": "5",
"uid": "s:40~l:46~t:5",
"stats": [
{
"name": "gamesBehind",
"displayName": "Games Back",
"shortDisplayName": "GB",
"description": "Games Back",
"abbreviation": "GB",
"type": "gamesbehind",
"value": 7.5,
"displayValue": "7.5"
},
{
"name": "losses",
"displayName": "Losses",
"shortDisplayName": "L",
"description": "Losses",
"abbreviation": "L",
"type": "losses",
"value": 30.0,
"displayValue": "30"
},
{
"name": "streak",
"displayName": "Streak",
"shortDisplayName": "STRK",
"description": "Current Streak",
"abbreviation": "STRK",
"type": "streak",
"value": 3.0,
"displayValue": "W3"
},
{
"name": "winPercent",
"displayName": "Win Percentage",
"shortDisplayName": "PCT",
"description": "Winning Percentage",
"abbreviation": "PCT",
"type": "winpercent",
"value": 0.6296296,
"displayValue": ".630"
},
{
"name": "wins",
"displayName": "Wins",
"shortDisplayName": "W",
"description": "Wins",
"abbreviation": "W",
"type": "wins",
"value": 51.0,
"displayValue": "51"
}
],
"logo": [
{
"href": "https://a.espncdn.com/i/teamlogos/nba/500/scoreboard/cle.png",
"width": 500,
"height": 500,
"alt": "",
"rel": [
"full",
"scoreboard"
],
"lastUpdated": "2022-06-23T14:03Z"
},
{
"href": "https://a.espncdn.com/i/teamlogos/nba/500-dark/scoreboard/cle.png",
"width": 500,
"height": 500,
"alt": "",
"rel": [
"full",
"scoreboard",
"dark"
],
"lastUpdated": "2018-06-05T12:08Z"
}
]
},
{
"team": "Chicago",
"link": "https://www.espn.com/nba/team/_/name/chi/chicago-bulls",
"id": "4",
"uid": "s:40~l:46~t:4",
"stats": [
{
"name": "gamesBehind",
"displayName": "Games Back",
"shortDisplayName": "GB",
"description": "Games Back",
"abbreviation": "GB",
"type": "gamesbehind",
"value": 20.0,
"displayValue": "20"
},
{
"name": "losses",
"displayName": "Losses",
"shortDisplayName": "L",
"description": "Losses",
"abbreviation": "L",
"type": "losses",
"value": 42.0,
"displayValue": "42"
},
{
"name": "streak",
"displayName": "Streak",
"shortDisplayName": "STRK",
"description": "Current Streak",
"abbreviation": "STRK",
"type": "streak",
"value": -2.0,
"displayValue": "L2"
},
{
"name": "winPercent",
"displayName": "Win Percentage",
"shortDisplayName": "PCT",
"description": "Winning Percentage",
"abbreviation": "PCT",
"type": "winpercent",
"value": 0.475,
"displayValue": ".475"
},
{
"name": "wins",
"displayName": "Wins",
"shortDisplayName": "W",
"description": "Wins",
"abbreviation": "W",
"type": "wins",
"value": 38.0,
"displayValue": "38"
}
],
"logo": [
{
"href": "https://a.espncdn.com/i/teamlogos/nba/500/scoreboard/chi.png",
"width": 500,
"height": 500,
"alt": "",
"rel": [
"full",
"scoreboard"
],
"lastUpdated": "2018-06-05T12:08Z"
},
{
"href": "https://a.espncdn.com/i/teamlogos/nba/500-dark/scoreboard/chi.png",
"width": 500,
"height": 500,
"alt": "",
"rel": [
"full",
"scoreboard",
"dark"
],
"lastUpdated": "2018-06-05T12:08Z"
}
]
},
{
"team": "Indiana",
"link": "https://www.espn.com/nba/team/_/name/ind/indiana-pacers",
"id": "11",
"uid": "s:40~l:46~t:11",
"stats": [
{
"name": "gamesBehind",
"displayName": "Games Back",
"shortDisplayName": "GB",
"description": "Games Back",
"abbreviation": "GB",
"type": "gamesbehind",
"value": 24.0,
"displayValue": "24"
},
{
"name": "losses",
"displayName": "Losses",
"shortDisplayName": "L",
"description": "Losses",
"abbreviation": "L",
"type": "losses",
"value": 46.0,
"displayValue": "46"
},
{
"name": "streak",
"displayName": "Streak",
"shortDisplayName": "STRK",
"description": "Current Streak",
"abbreviation": "STRK",
"type": "streak",
"value": -2.0,
"displayValue": "L2"
},
{
"name": "winPercent",
"displayName": "Win Percentage",
"shortDisplayName": "PCT",
"description": "Winning Percentage",
"abbreviation": "PCT",
"type": "winpercent",
"value": 0.425,
"displayValue": ".425"
},
{
"name": "wins",
"displayName": "Wins",
"shortDisplayName": "W",
"description": "Wins",
"abbreviation": "W",
"type": "wins",
"value": 34.0,
"displayValue": "34"
}
],
"logo": [
{
"href": "https://a.espncdn.com/i/teamlogos/nba/500/scoreboard/ind.png",
"width": 500,
"height": 500,
"alt": "",
"rel": [
"full",
"scoreboard"
],
"lastUpdated": "2018-06-05T12:08Z"
},
{
"href": "https://a.espncdn.com/i/teamlogos/nba/500-dark/scoreboard/ind.png",
"width": 500,
"height": 500,
"alt": "",
"rel": [
"full",
"scoreboard",
"dark"
],
"lastUpdated": "2018-06-05T12:08Z"
}
]
},
{
"team": "Detroit",
"link": "https://www.espn.com/nba/team/_/name/det/detroit-pistons",
"id": "8",
"uid": "s:40~l:46~t:8",
"stats": [
{
"name": "gamesBehind",
"displayName": "Games Back",
"shortDisplayName": "GB",
"description": "Games Back",
"abbreviation": "GB",
"type": "gamesbehind",
"value": 42.0,
"displayValue": "42"
},
{
"name": "losses",
"displayName": "Losses",
"shortDisplayName": "L",
"description": "Losses",
"abbreviation": "L",
"type": "losses",
"value": 64.0,
"displayValue": "64"
},
{
"name": "streak",
"displayName": "Streak",
"shortDisplayName": "STRK",
"description": "Current Streak",
"abbreviation": "STRK",
"type": "streak",
"value": -11.0,
"displayValue": "L11"
},
{
"name": "winPercent",
"displayName": "Win Percentage",
"shortDisplayName": "PCT",
"description": "Winning Percentage",
"abbreviation": "PCT",
"type": "winpercent",
"value": 0.2,
"displayValue": ".200"
},
{
"name": "wins",
"displayName": "Wins",
"shortDisplayName": "W",
"description": "Wins",
"abbreviation": "W",
"type": "wins",
"value": 16.0,
"displayValue": "16"
}
],
"logo": [
{
"href": "https://a.espncdn.com/i/teamlogos/nba/500/scoreboard/det.png",
"width": 500,
"height": 500,
"alt": "",
"rel": [
"full",
"scoreboard"
],
"lastUpdated": "2018-06-05T12:08Z"
},
{
"href": "https://a.espncdn.com/i/teamlogos/nba/500-dark/scoreboard/det.png",
"width": 500,
"height": 500,
"alt": "",
"rel": [
"full",
"scoreboard",
"dark"
],
"lastUpdated": "2018-06-05T12:08Z"
}
]
}
]
},
"header": "2022-23 Central Standings",
"href": "https://www.espn.com/nba/standings/_/group/2"
},
{
"standings": {
"entries": [
{
"team": "Boston",
"link": "https://www.espn.com/nba/team/_/name/bos/boston-celtics",
"id": "2",
"uid": "s:40~l:46~t:2",
"stats": [
{
"name": "gamesBehind",
"displayName": "Games Back",
"shortDisplayName": "GB",
"description": "Games Back",
"abbreviation": "GB",
"type": "gamesbehind",
"value": 0.0,
"displayValue": "-"
},
{
"name": "losses",
"displayName": "Losses",
"shortDisplayName": "L",
"description": "Losses",
"abbreviation": "L",
"type": "losses",
"value": 25.0,
"displayValue": "25"
},
{
"name": "streak",
"displayName": "Streak",
"shortDisplayName": "STRK",
"description": "Current Streak",
"abbreviation": "STRK",
"type": "streak",
"value": 1.0,
"displayValue": "W1"
},
{
"name": "winPercent",
"displayName": "Win Percentage",
"shortDisplayName": "PCT",
"description": "Winning Percentage",
"abbreviation": "PCT",
"type": "winpercent",
"value": 0.6875,
"displayValue": ".688"
},
{
"name": "wins",
"displayName": "Wins",
"shortDisplayName": "W",
"description": "Wins",
"abbreviation": "W",
"type": "wins",
"value": 55.0,
"displayValue": "55"
}
],
"logo": [
{
"href": "https://a.espncdn.com/i/teamlogos/nba/500/scoreboard/bos.png",
"width": 500,
"height": 500,
"alt": "",
"rel": [
"full",
"scoreboard"
],
"lastUpdated": "2018-06-05T12:08Z"
},
{
"href": "https://a.espncdn.com/i/teamlogos/nba/500-dark/scoreboard/bos.png",
"width": 500,
"height": 500,
"alt": "",
"rel": [
"full",
"scoreboard",
"dark"
],
"lastUpdated": "2018-06-05T12:08Z"
}
]
},
{
"team": "Philadelphia",
"link": "https://www.espn.com/nba/team/_/name/phi/philadelphia-76ers",
"id": "20",
"uid": "s:40~l:46~t:20",
"stats": [
{
"name": "gamesBehind",
"displayName": "Games Back",
"shortDisplayName": "GB",
"description": "Games Back",
"abbreviation": "GB",
"type": "gamesbehind",
"value": 3.0,
"displayValue": "3"
},
{
"name": "losses",
"displayName": "Losses",
"shortDisplayName": "L",
"description": "Losses",
"abbreviation": "L",
"type": "losses",
"value": 28.0,
"displayValue": "28"
},
{
"name": "streak",
"displayName": "Streak",
"shortDisplayName": "STRK",
"description": "Current Streak",
"abbreviation": "STRK",
"type": "streak",
"value": -1.0,
"displayValue": "L1"
},
{
"name": "winPercent",
"displayName": "Win Percentage",
"shortDisplayName": "PCT",
"description": "Winning Percentage",
"abbreviation": "PCT",
"type": "winpercent",
"value": 0.65,
"displayValue": ".650"
},
{
"name": "wins",
"displayName": "Wins",
"shortDisplayName": "W",
"description": "Wins",
"abbreviation": "W",
"type": "wins",
"value": 52.0,
"displayValue": "52"
}
],
"logo": [
{
"href": "https://a.espncdn.com/i/teamlogos/nba/500/scoreboard/phi.png",
"width": 500,
"height": 500,
"alt": "",
"rel": [
"full",
"scoreboard"
],
"lastUpdated": "2018-10-11T14:16Z"
},
{
"href": "https://a.espncdn.com/i/teamlogos/nba/500-dark/scoreboard/phi.png",
"width": 500,
"height": 500,
"alt": "",
"rel": [
"full",
"scoreboard",
"dark"
],
"lastUpdated": "2018-10-11T14:17Z"
}
]
},
{
"team": "New York",
"link": "https://www.espn.com/nba/team/_/name/ny/new-york-knicks",
"id": "18",
"uid": "s:40~l:46~t:18",
"stats": [
{
"name": "gamesBehind",
"displayName": "Games Back",
"shortDisplayName": "GB",
"description": "Games Back",
"abbreviation": "GB",
"type": "gamesbehind",
"value": 8.0,
"displayValue": "8"
},
{
"name": "losses",
"displayName": "Losses",
"shortDisplayName": "L",
"description": "Losses",
"abbreviation": "L",
"type": "losses",
"value": 33.0,
"displayValue": "33"
},
{
"name": "streak",
"displayName": "Streak",
"shortDisplayName": "STRK",
"description": "Current Streak",
"abbreviation": "STRK",
"type": "streak",
"value": 5.0,
"displayValue": "W5"
},
{
"name": "winPercent",
"displayName": "Win Percentage",
"shortDisplayName": "PCT",
"description": "Winning Percentage",
"abbreviation": "PCT",
"type": "winpercent",
"value": 0.5875,
"displayValue": ".588"
},
{
"name": "wins",
"displayName": "Wins",
"shortDisplayName": "W",
"description": "Wins",
"abbreviation": "W",
"type": "wins",
"value": 47.0,
"displayValue": "47"
}
],
"logo": [
{
"href": "https://a.espncdn.com/i/teamlogos/nba/500/scoreboard/ny.png",
"width": 500,
"height": 500,
"alt": "",
"rel": [
"full",
"scoreboard"
],
"lastUpdated": "2018-06-05T12:08Z"
},
{
"href": "https://a.espncdn.com/i/teamlogos/nba/500-dark/scoreboard/ny.png",
"width": 500,
"height": 500,
"alt": "",
"rel": [
"full",
"scoreboard",
"dark"
],
"lastUpdated": "2018-06-05T12:08Z"
}
]
},
{
"team": "Brooklyn",
"link": "https://www.espn.com/nba/team/_/name/bkn/brooklyn-nets",
"id": "17",
"uid": "s:40~l:46~t:17",
"stats": [
{
"name": "gamesBehind",
"displayName": "Games Back",
"shortDisplayName": "GB",
"description": "Games Back",
"abbreviation": "GB",
"type": "gamesbehind",
"value": 11.0,
"displayValue": "11"
},
{
"name": "losses",
"displayName": "Losses",
"shortDisplayName": "L",
"description": "Losses",
"abbreviation": "L",
"type": "losses",
"value": 36.0,
"displayValue": "36"
},
{
"name": "streak",
"displayName": "Streak",
"shortDisplayName": "STRK",
"description": "Current Streak",
"abbreviation": "STRK",
"type": "streak",
"value": 1.0,
"displayValue": "W1"
},
{
"name": "winPercent",
"displayName": "Win Percentage",
"shortDisplayName": "PCT",
"description": "Winning Percentage",
"abbreviation": "PCT",
"type": "winpercent",
"value": 0.55,
"displayValue": ".550"
},
{
"name": "wins",
"displayName": "Wins",
"shortDisplayName": "W",
"description": "Wins",
"abbreviation": "W",
"type": "wins",
"value": 44.0,
"displayValue": "44"
}
],
"logo": [
{
"href": "https://a.espncdn.com/i/teamlogos/nba/500/scoreboard/bkn.png",
"width": 500,
"height": 500,
"alt": "",
"rel": [
"full",
"scoreboard"
],
"lastUpdated": "2018-06-05T12:08Z"
},
{
"href": "https://a.espncdn.com/i/teamlogos/nba/500-dark/scoreboard/bkn.png",
"width": 500,
"height": 500,
"alt": "",
"rel": [
"full",
"scoreboard",
"dark"
],
"lastUpdated": "2018-06-05T12:08Z"
}
]
},
{
"team": "Toronto",
"link": "https://www.espn.com/nba/team/_/name/tor/toronto-raptors",
"id": "28",
"uid": "s:40~l:46~t:28",
"stats": [
{
"name": "gamesBehind",
"displayName": "Games Back",
"shortDisplayName": "GB",
"description": "Games Back",
"abbreviation": "GB",
"type": "gamesbehind",
"value": 15.0,
"displayValue": "15"
},
{
"name": "losses",
"displayName": "Losses",
"shortDisplayName": "L",
"description": "Losses",
"abbreviation": "L",
"type": "losses",
"value": 40.0,
"displayValue": "40"
},
{
"name": "streak",
"displayName": "Streak",
"shortDisplayName": "STRK",
"description": "Current Streak",
"abbreviation": "STRK",
"type": "streak",
"value": -1.0,
"displayValue": "L1"
},
{
"name": "winPercent",
"displayName": "Win Percentage",
"shortDisplayName": "PCT",
"description": "Winning Percentage",
"abbreviation": "PCT",
"type": "winpercent",
"value": 0.5,
"displayValue": ".500"
},
{
"name": "wins",
"displayName": "Wins",
"shortDisplayName": "W",
"description": "Wins",
"abbreviation": "W",
"type": "wins",
"value": 40.0,
"displayValue": "40"
}
],
"logo": [
{
"href": "https://a.espncdn.com/i/teamlogos/nba/500/scoreboard/tor.png",
"width": 500,
"height": 500,
"alt": "",
"rel": [
"full",
"scoreboard"
],
"lastUpdated": "2018-10-11T13:47Z"
},
{
"href": "https://a.espncdn.com/i/teamlogos/nba/500-dark/scoreboard/tor.png",
"width": 500,
"height": 500,
"alt": "",
"rel": [
"full",
"scoreboard",
"dark"
],
"lastUpdated": "2020-10-08T19:46Z"
}
]
}
]
},
"header": "2022-23 Atlantic Standings",
"href": "https://www.espn.com/nba/standings/_/group/1"
}
]
},
"teamInfo": [],
"espnWP": [],
"season": {},
"timeouts": []
}